Workbook

Sheet 使い方
A1: 弥生販売 仕入伝票 インポート用CSV たたき台
A3: ■ このファイルについて
A4: 元テンプレート「弥生販売 仕入伝票 インポート用データ作成テンプレート」を元に、必須・推奨項目のうち本当に人が判断しないと決まらない項目だけを「入力シート」に入力すれば、残りの41項目（伝票区分・端数処理設定・行番号・金額・消費税明細行など）を自動計算し、43列すべて（見出し行なし）の「CSV出力」シートを自動生成するたたき台です。
A6: ■ シート構成
A7: ・商品マスタ … 商品コードごとの商品名/単位/課税区分/数量小数桁/単価小数桁/原価の対応表。サンプル5商品のみ登録済み。ご自身の商品台帳の内容に置き換え・追記してください。
A8: ・入力シート … 実際に入力するシート。黄色い列だけ入力すればOKです。
A9: ・CSV出力 … 43列すべてを自動計算した最終データ（見出し行なし）。このシートの内容をコピーしてCSVとして保存します。
A11: ■ 入力手順
A12: ① 「商品マスタ」シートに自社の商品コード・商品名・単位・課税区分・数量小数桁・単価小数桁（・原価）を追記/修正する。
A13: ② 「入力シート」B2セルに、この回でインポートする最初の伝票番号（数字のみ、例:95）を入力する。
A14: ③ 「入力シート」の5行目以降、明細行を1行ずつ入力する。入力するのは【伝票日付・仕入先コード・仕入先名称・商品コード・数量・単価】の必須項目のみ。課税区分・明細区分・備考は空欄でも構いません（空欄なら自動判定/自動設定されます）。
A15: ④ 同じ「伝票日付」×「仕入先コード」が連続する行は、自動的に同じ1枚の伝票（同じ伝票番号）としてまとめられます。日付か仕入先コードが変わった時点で、自動的に次の伝票番号が採番されます。1行ずつ順番に入力していくだけで、伝票のグルーピングと行番号（明細の連番）はすべて自動計算されます。
... A27: ・入力シートは200行分（最大200明細行）まで対応しています。不足する場合はご相談ください。

Sheet 商品マスタ
A1: 商品マスタ（商品コード→商品名・単位・課税区分等の対応表）
A2: 課税区分: 13=通常課税10% / 30=軽減税率8% / 0=対象外。数量小数桁・単価小数桁は0〜4。
A4: 商品コード | B4: 商品名 | C4: 単位 | D4: 課税区分 | E4: 数量小数桁 | F4: 単価小数桁 | G4: 原価
A5: 1 | B5: 鉢マグロプレートA | C5: kg | D5: 30 | E5: 1 | F5: 1 | G5: 0
A6: 2 | B6: 黄肌鮪プレートA | C6: kg | D6: 30 | E6: 1 | F6: 1 | G6: 0
A7: 3 | B7: 黄肌鮪プレートB | C7: kg | D7: 30 | E7: 1 | F7: 1 | G7: 0
A8: 9 | B8: 畜養本鮪腹1 | C8: kg | D8: 30 | E8: 1 | F8: 1 | G8: 0
A9: 47 | B9: 鮪尾身 | C9: kg | D9: 30 | E9: 1 | F9: 1 | G9: 0

Sheet 入力シート
A1: 入力シート（必須項目だけ入力してください／黄色い列が入力欄、グレーの列は自動計算）
A2: 開始伝票番号: | B2: 90 | C2: ← この回でインポートする最初の伝票番号（数字のみ）。以降は日付・仕入先コードの変化に応じて自動的に+1されます。
A3: ↓ 以下2行（5〜6行目）は入力例です。同じ日付・仕入先コードの行は自動で同じ伝票にまとまることを確認できます。実データを入力する際はこの2行を書き換えてください。
A4: 伝票日付(必須) | B4: 仕入先コード(必須) | C4: 仕入先名称(推奨) | D4: 商品コード(必須) | E4: 数量(必須) | F4: 単価(必須) | G4: 明細区分 (空欄=通常/2=返品/3=値引/4=諸経費) | H4: 課税区分 (空欄=商品マスタから自動取得) | I4: 備考(任意) | J4: 商品名(自動) | K4: 単位(自動) | L4: 適用課税区分(自動) | M4: 数量小数桁(自動) | N4: 単価小数桁(自動) | O4: 金額(自動) | P4: 税抜額(自動) | Q4: =$B$2-1 -> 89 | R4: 行番号(自動) | S4: 伝票先頭フラグ(内部用) | T4: 伝票先頭連番(内部用) | U4: 原価(自動)
A5: 46238 | B5: 50 | C5: 株式会社オリエンタルフーズ | D5: 2 | E5: 1000 | F5: 2700 | J5: =IF($D5="","",IFERROR(VLOOKUP($D5,商品マスタ!$A$5:$G$1000,2,FALSE()),"※商品マスタ未登録")) -> 黄肌鮪プレートA | K5: =IF($D5="","",IFERROR(VLOOKUP($D5,商品マスタ!$A$5:$G$1000,3,FALSE()),"")) -> kg | L5: =IF($D5="","",IF($H5<>"",$H5,IFERROR(VLOOKUP($D5,商品マスタ!$A$5:$G$1000,4,FALSE()),""))) -> 30 | M5: =IF($D5="","",IFERROR(VLOOKUP($D5,商品マスタ!$A$5:$G$1000,5,FALSE()),0)) -> 1 | N5: =IF($D5="","",IFERROR(VLOOKUP($D5,商品マスタ!$A$5:$G$1000,6,FALSE()),0)) -> 1 | O5: =IF($D5="","",ROUND($E5*$F5,0)) -> 2700000 | P5: =IF($D5="","",$O5) -> 2700000 | Q5: =IF($A5="","",IF($S5=1,$Q4+1,$Q4)) -> 90 | R5: =IF($A5="","",IF($Q5=$Q4,$R4+1,1)) -> 1 | S5: =IF($A5="","",IF(AND($A5=$A4,$B5=$B4),0,1)) -> 1 | T5: =IF($A5="","",IF($S5=1,COUNTIF($S$5:$S5,1),"")) -> 1 | U5: =IF($D5="","",IFERROR(VLOOKUP($D5,商品マスタ!$A$5:$G$1000,7,FALSE()),0)) -> 0
A6: 46238 | B6: 50 | C6: 株式会社オリエンタルフーズ | D6: 3 | E6: 1000 | F6: 2450 | J6: =IF($D6="","",IFERROR(VLOOKUP($D6,商品マスタ!$A$5:$G$1000,2,FALSE()),"※商品マスタ未登録")) -> 黄肌鮪プレートB | K6: =IF($D6="","",IFERROR(VLOOKUP($D6,商品マスタ!$A$5:$G$1000,3,FALSE()),"")) -> kg | L6: =IF($D6="","",IF($H6<>"",$H6,IFERROR(VLOOKUP($D6,商品マスタ!$A$5:$G$1000,4,FALSE()),""))) -> 30 | M6: =IF($D6="","",IFERROR(VLOOKUP($D6,商品マスタ!$A$5:$G$1000,5,FALSE()),0)) -> 1 | N6: =IF($D6="","",IFERROR(VLOOKUP($D6,商品マスタ!$A$5:$G$1000,6,FALSE()),0)) -> 1 | O6: =IF($D6="","",ROUND($E6*$F6,0)) -> 2450000 | P6: =IF($D6="","",$O6) -> 2450000 | Q6: =IF($A6="","",IF($S6=1,$Q5+1,$Q5)) -> 90 | R6: =IF($A6="","",IF($Q6=$Q5,$R5+1,1)) -> 2 | S6: =IF($A6="","",IF(AND($A6=$A5,$B6=$B5),0,1)) -> 0 | T6: =IF($A6="","",IF($S6=1,COUNTIF($S$5:$S6,1),"")) | U6: =IF($D6="","",IFERROR(VLOOKUP($D6,商品マスタ!$A$5:$G$1000,7,FALSE()),0)) -> 0
J7: =IF($D7="","",IFERROR(VLOOKUP($D7,商品マスタ!$A$5:$G$1000,2,FALSE()),"※商品マスタ未登録")) | K7: =IF($D7="","",IFERROR(VLOOKUP($D7,商品マスタ!$A$5:$G$1000,3,FALSE()),"")) | L7: =IF($D7="","",IF($H7<>"",$H7,IFERROR(VLOOKUP($D7,商品マスタ!$A$5:$G$1000,4,FALSE()),""))) | M7: =IF($D7="","",IFERROR(VLOOKUP($D7,商品マスタ!$A$5:$G$1000,5,FALSE()),0)) | N7: =IF($D7="","",IFERROR(VLOOKUP($D7,商品マスタ!$A$5:$G$1000,6,FALSE()),0)) | O7: =IF($D7="","",ROUND($E7*$F7,0)) | P7: =IF($D7="","",$O7) | Q7: =IF($A7="","",IF($S7=1,$Q6+1,$Q6)) | R7: =IF($A7="","",IF($Q7=$Q6,$R6+1,1)) | S7: =IF($A7="","",IF(AND($A7=$A6,$B7=$B6),0,1)) | T7: =IF($A7="","",IF($S7=1,COUNTIF($S$5:$S7,1),"")) | U7: =IF($D7="","",IFERROR(VLOOKUP($D7,商品マスタ!$A$5:$G$1000,7,FALSE()),0))
J8: =IF($D8="","",IFERROR(VLOOKUP($D8,商品マスタ!$A$5:$G$1000,2,FALSE()),"※商品マスタ未登録")) | K8: =IF($D8="","",IFERROR(VLOOKUP($D8,商品マスタ!$A$5:$G$1000,3,FALSE()),"")) | L8: =IF($D8="","",IF($H8<>"",$H8,IFERROR(VLOOKUP($D8,商品マスタ!$A$5:$G$1000,4,FALSE()),""))) | M8: =IF($D8="","",IFERROR(VLOOKUP($D8,商品マスタ!$A$5:$G$1000,5,FALSE()),0)) | N8: =IF($D8="","",IFERROR(VLOOKUP($D8,商品マスタ!$A$5:$G$1000,6,FALSE()),0)) | O8: =IF($D8="","",ROUND($E8*$F8,0)) | P8: =IF($D8="","",$O8) | Q8: =IF($A8="","",IF($S8=1,$Q7+1,$Q7)) | R8: =IF($A8="","",IF($Q8=$Q7,$R7+1,1)) | S8: =IF($A8="","",IF(AND($A8=$A7,$B8=$B7),0,1)) | T8: =IF($A8="","",IF($S8=1,COUNTIF($S$5:$S8,1),"")) | U8: =IF($D8="","",IFERROR(VLOOKUP($D8,商品マスタ!$A$5:$G$1000,7,FALSE()),0))
J9: =IF($D9="","",IFERROR(VLOOKUP($D9,商品マスタ!$A$5:$G$1000,2,FALSE()),"※商品マスタ未登録")) | K9: =IF($D9="","",IFERROR(VLOOKUP($D9,商品マスタ!$A$5:$G$1000,3,FALSE()),"")) | L9: =IF($D9="","",IF($H9<>"",$H9,IFERROR(VLOOKUP($D9,商品マスタ!$A$5:$G$1000,4,FALSE()),""))) | M9: =IF($D9="","",IFERROR(VLOOKUP($D9,商品マスタ!$A$5:$G$1000,5,FALSE()),0)) | N9: =IF($D9="","",IFERROR(VLOOKUP($D9,商品マスタ!$A$5:$G$1000,6,FALSE()),0)) | O9: =IF($D9="","",ROUND($E9*$F9,0)) | P9: =IF($D9="","",$O9) | Q9: =IF($A9="","",IF($S9=1,$Q8+1,$Q8)) | R9: =IF($A9="","",IF($Q9=$Q8,$R8+1,1)) | S9: =IF($A9="","",IF(AND($A9=$A8,$B9=$B8),0,1)) | T9: =IF($A9="","",IF($S9=1,COUNTIF($S$5:$S9,1),"")) | U9: =IF($D9="","",IFERROR(VLOOKUP($D9,商品マスタ!$A$5:$G$1000,7,FALSE()),0))
J10: =IF($D10="","",IFERROR(VLOOKUP($D10,商品マスタ!$A$5:$G$1000,2,FALSE()),"※商品マスタ未登録")) | K10: =IF($D10="","",IFERROR(VLOOKUP($D10,商品マスタ!$A$5:$G$1000,3,FALSE()),"")) | L10: =IF($D10="","",IF($H10<>"",$H10,IFERROR(VLOOKUP($D10,商品マスタ!$A$5:$G$1000,4,FALSE()),""))) | M10: =IF($D10="","",IFERROR(VLOOKUP($D10,商品マスタ!$A$5:$G$1000,5,FALSE()),0)) | N10: =IF($D10="","",IFERROR(VLOOKUP($D10,商品マスタ!$A$5:$G$1000,6,FALSE()),0)) | O10: =IF($D10="","",ROUND($E10*$F10,0)) | P10: =IF($D10="","",$O10) | Q10: =IF($A10="","",IF($S10=1,$Q9+1,$Q9)) | R10: =IF($A10="","",IF($Q10=$Q9,$R9+1,1)) | S10: =IF($A10="","",IF(AND($A10=$A9,$B10=$B9),0,1)) | T10: =IF($A10="","",IF($S10=1,COUNTIF($S$5:$S10,1),"")) | U10: =IF($D10="","",IFERROR(VLOOKUP($D10,商品マスタ!$A$5:$G$1000,7,FALSE()),0))
J11: =IF($D11="","",IFERROR(VLOOKUP($D11,商品マスタ!$A$5:$G$1000,2,FALSE()),"※商品マスタ未登録")) | K11: =IF($D11="","",IFERROR(VLOOKUP($D11,商品マスタ!$A$5:$G$1000,3,FALSE()),"")) | L11: =IF($D11="","",IF($H11<>"",$H11,IFERROR(VLOOKUP($D11,商品マスタ!$A$5:$G$1000,4,FALSE()),""))) | M11: =IF($D11="","",IFERROR(VLOOKUP($D11,商品マスタ!$A$5:$G$1000,5,FALSE()),0)) | N11: =IF($D11="","",IFERROR(VLOOKUP($D11,商品マスタ!$A$5:$G$1000,6,FALSE()),0)) | O11: =IF($D11="","",ROUND($E11*$F11,0)) | P11: =IF($D11="","",$O11) | Q11: =IF($A11="","",IF($S11=1,$Q10+1,$Q10)) | R11: =IF($A11="","",IF($Q11=$Q10,$R10+1,1)) | S11: =IF($A11="","",IF(AND($A11=$A10,$B11=$B10),0,1)) | T11: =IF($A11="","",IF($S11=1,COUNTIF($S$5:$S11,1),"")) | U11: =IF($D11="","",IFERROR(VLOOKUP($D11,商品マスタ!$A$5:$G$1000,7,FALSE()),0))
J12: =IF($D12="","",IFERROR(VLOOKUP($D12,商品マスタ!$A$5:$G$1000,2,FALSE()),"※商品マスタ未登録")) | K12: =IF($D12="","",IFERROR(VLOOKUP($D12,商品マスタ!$A$5:$G$1000,3,FALSE()),"")) | L12: =IF($D12="","",IF($H12<>"",$H12,IFERROR(VLOOKUP($D12,商品マスタ!$A$5:$G$1000,4,FALSE()),""))) | M12: =IF($D12="","",IFERROR(VLOOKUP($D12,商品マスタ!$A$5:$G$1000,5,FALSE()),0)) | N12: =IF($D12="","",IFERROR(VLOOKUP($D12,商品マスタ!$A$5:$G$1000,6,FALSE()),0)) | O12: =IF($D12="","",ROUND($E12*$F12,0)) | P12: =IF($D12="","",$O12) | Q12: =IF($A12="","",IF($S12=1,$Q11+1,$Q11)) | R12: =IF($A12="","",IF($Q12=$Q11,$R11+1,1)) | S12: =IF($A12="","",IF(AND($A12=$A11,$B12=$B11),0,1)) | T12: =IF($A12="","",IF($S12=1,COUNTIF($S$5:$S12,1),"")) | U12: =IF($D12="","",IFERROR(VLOOKUP($D12,商品マスタ!$A$5:$G$1000,7,FALSE()),0))
J13: =IF($D13="","",IFERROR(VLOOKUP($D13,商品マスタ!$A$5:$G$1000,2,FALSE()),"※商品マスタ未登録")) | K13: =IF($D13="","",IFERROR(VLOOKUP($D13,商品マスタ!$A$5:$G$1000,3,FALSE()),"")) | L13: =IF($D13="","",IF($H13<>"",$H13,IFERROR(VLOOKUP($D13,商品マスタ!$A$5:$G$1000,4,FALSE()),""))) | M13: =IF($D13="","",IFERROR(VLOOKUP($D13,商品マスタ!$A$5:$G$1000,5,FALSE()),0)) | N13: =IF($D13="","",IFERROR(VLOOKUP($D13,商品マスタ!$A$5:$G$1000,6,FALSE()),0)) | O13: =IF($D13="","",ROUND($E13*$F13,0)) | P13: =IF($D13="","",$O13) | Q13: =IF($A13="","",IF($S13=1,$Q12+1,$Q12)) | R13: =IF($A13="","",IF($Q13=$Q12,$R12+1,1)) | S13: =IF($A13="","",IF(AND($A13=$A12,$B13=$B12),0,1)) | T13: =IF($A13="","",IF($S13=1,COUNTIF($S$5:$S13,1),"")) | U13: =IF($D13="","",IFERROR(VLOOKUP($D13,商品マスタ!$A$5:$G$1000,7,FALSE()),0))
J14: =IF($D14="","",IFERROR(VLOOKUP($D14,商品マスタ!$A$5:$G$1000,2,FALSE()),"※商品マスタ未登録")) | K14: =IF($D14="","",IFERROR(VLOOKUP($D14,商品マスタ!$A$5:$G$1000,3,FALSE()),"")) | L14: =IF($D14="","",IF($H14<>"",$H14,IFERROR(VLOOKUP($D14,商品マスタ!$A$5:$G$1000,4,FALSE()),""))) | M14: =IF($D14="","",IFERROR(VLOOKUP($D14,商品マスタ!$A$5:$G$1000,5,FALSE()),0)) | N14: =IF($D14="","",IFERROR(VLOOKUP($D14,商品マスタ!$A$5:$G$1000,6,FALSE()),0)) | O14: =IF($D14="","",ROUND($E14*$F14,0)) | P14: =IF($D14="","",$O14) | Q14: =IF($A14="","",IF($S14=1,$Q13+1,$Q13)) | R14: =IF($A14="","",IF($Q14=$Q13,$R13+1,1)) | S14: =IF($A14="","",IF(AND($A14=$A13,$B14=$B13),0,1)) | T14: =IF($A14="","",IF($S14=1,COUNTIF($S$5:$S14,1),"")) | U14: =IF($D14="","",IFERROR(VLOOKUP($D14,商品マスタ!$A$5:$G$1000,7,FALSE()),0))
J15: =IF($D15="","",IFERROR(VLOOKUP($D15,商品マスタ!$A$5:$G$1000,2,FALSE()),"※商品マスタ未登録")) | K15: =IF($D15="","",IFERROR(VLOOKUP($D15,商品マスタ!$A$5:$G$1000,3,FALSE()),"")) | L15: =IF($D15="","",IF($H15<>"",$H15,IFERROR(VLOOKUP($D15,商品マスタ!$A$5:$G$1000,4,FALSE()),""))) | M15: =IF($D15="","",IFERROR(VLOOKUP($D15,商品マスタ!$A$5:$G$1000,5,FALSE()),0)) | N15: =IF($D15="","",IFERROR(VLOOKUP($D15,商品マスタ!$A$5:$G$1000,6,FALSE()),0)) | O15: =IF($D15="","",ROUND($E15*$F15,0)) | P15: =IF($D15="","",$O15) | Q15: =IF($A15="","",IF($S15=1,$Q14+1,$Q14)) | R15: =IF($A15="","",IF($Q15=$Q14,$R14+1,1)) | S15: =IF($A15="","",IF(AND($A15=$A14,$B15=$B14),0,1)) | T15: =IF($A15="","",IF($S15=1,COUNTIF($S$5:$S15,1),"")) | U15: =IF($D15="","",IFERROR(VLOOKUP($D15,商品マスタ!$A$5:$G$1000,7,FALSE()),0))
J16: =IF($D16="","",IFERROR(VLOOKUP($D16,商品マスタ!$A$5:$G$1000,2,FALSE()),"※商品マスタ未登録")) | K16: =IF($D16="","",IFERROR(VLOOKUP($D16,商品マスタ!$A$5:$G$1000,3,FALSE()),"")) | L16: =IF($D16="","",IF($H16<>"",$H16,IFERROR(VLOOKUP($D16,商品マスタ!$A$5:$G$1000,4,FALSE()),""))) | M16: =IF($D16="","",IFERROR(VLOOKUP($D16,商品マスタ!$A$5:$G$1000,5,FALSE()),0)) | N16: =IF($D16="","",IFERROR(VLOOKUP($D16,商品マスタ!$A$5:$G$1000,6,FALSE()),0)) | O16: =IF($D16="","",ROUND($E16*$F16,0)) | P16: =IF($D16="","",$O16) | Q16: =IF($A16="","",IF($S16=1,$Q15+1,$Q15)) | R16: =IF($A16="","",IF($Q16=$Q15,$R15+1,1)) | S16: =IF($A16="","",IF(AND($A16=$A15,$B16=$B15),0,1)) | T16: =IF($A16="","",IF($S16=1,COUNTIF($S$5:$S16,1),"")) | U16: =IF($D16="","",IFERROR(VLOOKUP($D16,商品マスタ!$A$5:$G$1000,7,FALSE()),0))
J17: =IF($D17="","",IFERROR(VLOOKUP($D17,商品マスタ!$A$5:$G$1000,2,FALSE()),"※商品マスタ未登録")) | K17: =IF($D17="","",IFERROR(VLOOKUP($D17,商品マスタ!$A$5:$G$1000,3,FALSE()),"")) | L17: =IF($D17="","",IF($H17<>"",$H17,IFERROR(VLOOKUP($D17,商品マスタ!$A$5:$G$1000,4,FALSE()),""))) | M17: =IF($D17="","",IFERROR(VLOOKUP($D17,商品マスタ!$A$5:$G$1000,5,FALSE()),0)) | N17: =IF($D17="","",IFERROR(VLOOKUP($D17,商品マスタ!$A$5:$G$1000,6,FALSE()),0)) | O17: =IF($D17="","",ROUND($E17*$F17,0)) | P17: =IF($D17="","",$O17) | Q17: =IF($A17="","",IF($S17=1,$Q16+1,$Q16)) | R17: =IF($A17="","",IF($Q17=$Q16,$R16+1,1)) | S17: =IF($A17="","",IF(AND($A17=$A16,$B17=$B16),0,1)) | T17: =IF($A17="","",IF($S17=1,COUNTIF($S$5:$S17,1),"")) | U17: =IF($D17="","",IFERROR(VLOOKUP($D17,商品マスタ!$A$5:$G$1000,7,FALSE()),0))
J18: =IF($D18="","",IFERROR(VLOOKUP($D18,商品マスタ!$A$5:$G$1000,2,FALSE()),"※商品マスタ未登録")) | K18: =IF($D18="","",IFERROR(VLOOKUP($D18,商品マスタ!$A$5:$G$1000,3,FALSE()),"")) | L18: =IF($D18="","",IF($H18<>"",$H18,IFERROR(VLOOKUP($D18,商品マスタ!$A$5:$G$1000,4,FALSE()),""))) | M18: =IF($D18="","",IFERROR(VLOOKUP($D18,商品マスタ!$A$5:$G$1000,5,FALSE()),0)) | N18: =IF($D18="","",IFERROR(VLOOKUP($D18,商品マスタ!$A$5:$G$1000,6,FALSE()),0)) | O18: =IF($D18="","",ROUND($E18*$F18,0)) | P18: =IF($D18="","",$O18) | Q18: =IF($A18="","",IF($S18=1,$Q17+1,$Q17)) | R18: =IF($A18="","",IF($Q18=$Q17,$R17+1,1)) | S18: =IF($A18="","",IF(AND($A18=$A17,$B18=$B17),0,1)) | T18: =IF($A18="","",IF($S18=1,COUNTIF($S$5:$S18,1),"")) | U18: =IF($D18="","",IFERROR(VLOOKUP($D18,商品マスタ!$A$5:$G$1000,7,FALSE()),0))
... J204: =IF($D204="","",IFERROR(VLOOKUP($D204,商品マスタ!$A$5:$G$1000,2,FALSE()),"※商品マスタ未登録")) | K204: =IF($D204="","",IFERROR(VLOOKUP($D204,商品マスタ!$A$5:$G$1000,3,FALSE()),"")) | L204: =IF($D204="","",IF($H204<>"",$H204,IFERROR(VLOOKUP($D204,商品マスタ!$A$5:$G$1000,4,FALSE()),""))) | M204: =IF($D204="","",IFERROR(VLOOKUP($D204,商品マスタ!$A$5:$G$1000,5,FALSE()),0)) | N204: =IF($D204="","",IFERROR(VLOOKUP($D204,商品マスタ!$A$5:$G$1000,6,FALSE()),0)) | O204: =IF($D204="","",ROUND($E204*$F204,0)) | P204: =IF($D204="","",$O204) | Q204: =IF($A204="","",IF($S204=1,$Q203+1,$Q203)) | R204: =IF($A204="","",IF($Q204=$Q203,$R203+1,1)) | S204: =IF($A204="","",IF(AND($A204=$A203,$B204=$B203),0,1)) | T204: =IF($A204="","",IF($S204=1,COUNTIF($S$5:$S204,1),"")) | U204: =IF($D204="","",IFERROR(VLOOKUP($D204,商品マスタ!$A$5:$G$1000,7,FALSE()),0))

Sheet CSV出力
A1: =IF(入力シート!$A5="","",1) -> 1 | B1: =IF(入力シート!$A5="","",1) -> 1 | C1: =IF(入力シート!$A5="","",0) -> 0 | D1: =IF(入力シート!$A5="","",TEXT(入力シート!A5,"YYYYMMDD")) -> 20260804 | E1: =IF(入力シート!$A5="","",TEXT(入力シート!Q5,"00000000")) -> 00000090 | F1: =IF(入力シート!$A5="","",14) -> 14 | G1: =IF(入力シート!$A5="","",1) -> 1 | H1: =IF(入力シート!$A5="","",1) -> 1 | I1: =IF(入力シート!$A5="","",3) -> 3 | J1: =IF(入力シート!$A5="","",1) -> 1 | K1: =IF(入力シート!$A5="","",入力シート!B5) -> 50 | L1: =IF(入力シート!$A5="","","") | M1: =IF(入力シート!$A5="","","") | N1: =IF(入力シート!$A5="","",入力シート!R5) -> 1 | O1: =IF(入力シート!$A5="","",IF(入力シート!G5="",1,入力シート!G5)) -> 1 | P1: =IF(入力シート!$A5="","",入力シート!D5) -> 2 | Q1: =IF(入力シート!$A5="","","") | R1: =IF(入力シート!$A5="","",入力シート!J5) -> 黄肌鮪プレートA | S1: =IF(入力シート!$A5="","",入力シート!L5) -> 30 | T1: =IF(入力シート!$A5="","",入力シート!K5) -> kg | U1: =IF(入力シート!$A5="","",0) -> 0 | V1: =IF(入力シート!$A5="","",0) -> 0 | W1: =IF(入力シート!$A5="","","0000") -> 0000 | X1: =IF(入力シート!$A5="","",入力シート!E5) -> 1000 | Y1: =IF(入力シート!$A5="","",入力シート!F5) -> 2700 | Z1: =IF(入力シート!$A5="","",入力シート!O5) -> 2700000 | AA1: =IF(入力シート!$A5="","","") | AB1: =IF(入力シート!$A5="","",入力シート!P5) -> 2700000 | AC1: =IF(入力シート!$A5="","",入力シート!U5) -> 0 | AD1: =IF(入力シート!$A5="","",0) -> 0 | AE1: =IF(入力シート!$A5="","",入力シート!I5) -> 0 | AF1: =IF(入力シート!$A5="","",入力シート!M5) -> 1 | AG1: =IF(入力シート!$A5="","",入力シート!N5) -> 1 | AH1: =IF(入力シート!$A5="","","") | AI1: =IF(入力シート!$A5="","","") | AJ1: =IF(入力シート!$A5="","","") | AK1: =IF(入力シート!$A5="","",2) -> 2 | AL1: =IF(入力シート!$A5="","","") | AM1: =IF(入力シート!$A5="","","") | AN1: =IF(入力シート!$A5="","",入力シート!C5) -> 株式会社オリエンタルフーズ | AO1: =IF(入力シート!$A5="","","") | AP1: =IF(入力シート!$A5="","","") | AQ1: =IF(入力シート!$A5="","","") | AT1: (内部計算用/非表示予定)
A2: =IF(入力シート!$A6="","",1) -> 1 | B2: =IF(入力シート!$A6="","",1) -> 1 | C2: =IF(入力シート!$A6="","",0) -> 0 | D2: =IF(入力シート!$A6="","",TEXT(入力シート!A6,"YYYYMMDD")) -> 20260804 | E2: =IF(入力シート!$A6="","",TEXT(入力シート!Q6,"00000000")) -> 00000090 | F2: =IF(入力シート!$A6="","",14) -> 14 | G2: =IF(入力シート!$A6="","",1) -> 1 | H2: =IF(入力シート!$A6="","",1) -> 1 | I2: =IF(入力シート!$A6="","",3) -> 3 | J2: =IF(入力シート!$A6="","",1) -> 1 | K2: =IF(入力シート!$A6="","",入力シート!B6) -> 50 | L2: =IF(入力シート!$A6="","","") | M2: =IF(入力シート!$A6="","","") | N2: =IF(入力シート!$A6="","",入力シート!R6) -> 2 | O2: =IF(入力シート!$A6="","",IF(入力シート!G6="",1,入力シート!G6)) -> 1 | P2: =IF(入力シート!$A6="","",入力シート!D6) -> 3 | Q2: =IF(入力シート!$A6="","","") | R2: =IF(入力シート!$A6="","",入力シート!J6) -> 黄肌鮪プレートB | S2: =IF(入力シート!$A6="","",入力シート!L6) -> 30 | T2: =IF(入力シート!$A6="","",入力シート!K6) -> kg | U2: =IF(入力シート!$A6="","",0) -> 0 | V2: =IF(入力シート!$A6="","",0) -> 0 | W2: =IF(入力シート!$A6="","","0000") -> 0000 | X2: =IF(入力シート!$A6="","",入力シート!E6) -> 1000 | Y2: =IF(入力シート!$A6="","",入力シート!F6) -> 2450 | Z2: =IF(入力シート!$A6="","",入力シート!O6) -> 2450000 | AA2: =IF(入力シート!$A6="","","") | AB2: =IF(入力シート!$A6="","",入力シート!P6) -> 2450000 | AC2: =IF(入力シート!$A6="","",入力シート!U6) -> 0 | AD2: =IF(入力シート!$A6="","",0) -> 0 | AE2: =IF(入力シート!$A6="","",入力シート!I6) -> 0 | AF2: =IF(入力シート!$A6="","",入力シート!M6) -> 1 | AG2: =IF(入力シート!$A6="","",入力シート!N6) -> 1 | AH2: =IF(入力シート!$A6="","","") | AI2: =IF(入力シート!$A6="","","") | AJ2: =IF(入力シート!$A6="","","") | AK2: =IF(入力シート!$A6="","",2) -> 2 | AL2: =IF(入力シート!$A6="","","") | AM2: =IF(入力シート!$A6="","","") | AN2: =IF(入力シート!$A6="","",入力シート!C6) -> 株式会社オリエンタルフーズ | AO2: =IF(入力シート!$A6="","","") | AP2: =IF(入力シート!$A6="","","") | AQ2: =IF(入力シート!$A6="","","")
A3: =IF(入力シート!$A7="","",1) | B3: =IF(入力シート!$A7="","",1) | C3: =IF(入力シート!$A7="","",0) | D3: =IF(入力シート!$A7="","",TEXT(入力シート!A7,"YYYYMMDD")) | E3: =IF(入力シート!$A7="","",TEXT(入力シート!Q7,"00000000")) | F3: =IF(入力シート!$A7="","",14) | G3: =IF(入力シート!$A7="","",1) | H3: =IF(入力シート!$A7="","",1) | I3: =IF(入力シート!$A7="","",3) | J3: =IF(入力シート!$A7="","",1) | K3: =IF(入力シート!$A7="","",入力シート!B7) | L3: =IF(入力シート!$A7="","","") | M3: =IF(入力シート!$A7="","","") | N3: =IF(入力シート!$A7="","",入力シート!R7) | O3: =IF(入力シート!$A7="","",IF(入力シート!G7="",1,入力シート!G7)) | P3: =IF(入力シート!$A7="","",入力シート!D7) | Q3: =IF(入力シート!$A7="","","") | R3: =IF(入力シート!$A7="","",入力シート!J7) | S3: =IF(入力シート!$A7="","",入力シート!L7) | T3: =IF(入力シート!$A7="","",入力シート!K7) | U3: =IF(入力シート!$A7="","",0) | V3: =IF(入力シート!$A7="","",0) | W3: =IF(入力シート!$A7="","","0000") | X3: =IF(入力シート!$A7="","",入力シート!E7) | Y3: =IF(入力シート!$A7="","",入力シート!F7) | Z3: =IF(入力シート!$A7="","",入力シート!O7) | AA3: =IF(入力シート!$A7="","","") | AB3: =IF(入力シート!$A7="","",入力シート!P7) | AC3: =IF(入力シート!$A7="","",入力シート!U7) | AD3: =IF(入力シート!$A7="","",0) | AE3: =IF(入力シート!$A7="","",入力シート!I7) | AF3: =IF(入力シート!$A7="","",入力シート!M7) | AG3: =IF(入力シート!$A7="","",入力シート!N7) | AH3: =IF(入力シート!$A7="","","") | AI3: =IF(入力シート!$A7="","","") | AJ3: =IF(入力シート!$A7="","","") | AK3: =IF(入力シート!$A7="","",2) | AL3: =IF(入力シート!$A7="","","") | AM3: =IF(入力シート!$A7="","","") | AN3: =IF(入力シート!$A7="","",入力シート!C7) | AO3: =IF(入力シート!$A7="","","") | AP3: =IF(入力シート!$A7="","","") | AQ3: =IF(入力シート!$A7="","","")
A4: =IF(入力シート!$A8="","",1) | B4: =IF(入力シート!$A8="","",1) | C4: =IF(入力シート!$A8="","",0) | D4: =IF(入力シート!$A8="","",TEXT(入力シート!A8,"YYYYMMDD")) | E4: =IF(入力シート!$A8="","",TEXT(入力シート!Q8,"00000000")) | F4: =IF(入力シート!$A8="","",14) | G4: =IF(入力シート!$A8="","",1) | H4: =IF(入力シート!$A8="","",1) | I4: =IF(入力シート!$A8="","",3) | J4: =IF(入力シート!$A8="","",1) | K4: =IF(入力シート!$A8="","",入力シート!B8) | L4: =IF(入力シート!$A8="","","") | M4: =IF(入力シート!$A8="","","") | N4: =IF(入力シート!$A8="","",入力シート!R8) | O4: =IF(入力シート!$A8="","",IF(入力シート!G8="",1,入力シート!G8)) | P4: =IF(入力シート!$A8="","",入力シート!D8) | Q4: =IF(入力シート!$A8="","","") | R4: =IF(入力シート!$A8="","",入力シート!J8) | S4: =IF(入力シート!$A8="","",入力シート!L8) | T4: =IF(入力シート!$A8="","",入力シート!K8) | U4: =IF(入力シート!$A8="","",0) | V4: =IF(入力シート!$A8="","",0) | W4: =IF(入力シート!$A8="","","0000") | X4: =IF(入力シート!$A8="","",入力シート!E8) | Y4: =IF(入力シート!$A8="","",入力シート!F8) | Z4: =IF(入力シート!$A8="","",入力シート!O8) | AA4: =IF(入力シート!$A8="","","") | AB4: =IF(入力シート!$A8="","",入力シート!P8) | AC4: =IF(入力シート!$A8="","",入力シート!U8) | AD4: =IF(入力シート!$A8="","",0) | AE4: =IF(入力シート!$A8="","",入力シート!I8) | AF4: =IF(入力シート!$A8="","",入力シート!M8) | AG4: =IF(入力シート!$A8="","",入力シート!N8) | AH4: =IF(入力シート!$A8="","","") | AI4: =IF(入力シート!$A8="","","") | AJ4: =IF(入力シート!$A8="","","") | AK4: =IF(入力シート!$A8="","",2) | AL4: =IF(入力シート!$A8="","","") | AM4: =IF(入力シート!$A8="","","") | AN4: =IF(入力シート!$A8="","",入力シート!C8) | AO4: =IF(入力シート!$A8="","","") | AP4: =IF(入力シート!$A8="","","") | AQ4: =IF(入力シート!$A8="","","")
A5: =IF(入力シート!$A9="","",1) | B5: =IF(入力シート!$A9="","",1) | C5: =IF(入力シート!$A9="","",0) | D5: =IF(入力シート!$A9="","",TEXT(入力シート!A9,"YYYYMMDD")) | E5: =IF(入力シート!$A9="","",TEXT(入力シート!Q9,"00000000")) | F5: =IF(入力シート!$A9="","",14) | G5: =IF(入力シート!$A9="","",1) | H5: =IF(入力シート!$A9="","",1) | I5: =IF(入力シート!$A9="","",3) | J5: =IF(入力シート!$A9="","",1) | K5: =IF(入力シート!$A9="","",入力シート!B9) | L5: =IF(入力シート!$A9="","","") | M5: =IF(入力シート!$A9="","","") | N5: =IF(入力シート!$A9="","",入力シート!R9) | O5: =IF(入力シート!$A9="","",IF(入力シート!G9="",1,入力シート!G9)) | P5: =IF(入力シート!$A9="","",入力シート!D9) | Q5: =IF(入力シート!$A9="","","") | R5: =IF(入力シート!$A9="","",入力シート!J9) | S5: =IF(入力シート!$A9="","",入力シート!L9) | T5: =IF(入力シート!$A9="","",入力シート!K9) | U5: =IF(入力シート!$A9="","",0) | V5: =IF(入力シート!$A9="","",0) | W5: =IF(入力シート!$A9="","","0000") | X5: =IF(入力シート!$A9="","",入力シート!E9) | Y5: =IF(入力シート!$A9="","",入力シート!F9) | Z5: =IF(入力シート!$A9="","",入力シート!O9) | AA5: =IF(入力シート!$A9="","","") | AB5: =IF(入力シート!$A9="","",入力シート!P9) | AC5: =IF(入力シート!$A9="","",入力シート!U9) | AD5: =IF(入力シート!$A9="","",0) | AE5: =IF(入力シート!$A9="","",入力シート!I9) | AF5: =IF(入力シート!$A9="","",入力シート!M9) | AG5: =IF(入力シート!$A9="","",入力シート!N9) | AH5: =IF(入力シート!$A9="","","") | AI5: =IF(入力シート!$A9="","","") | AJ5: =IF(入力シート!$A9="","","") | AK5: =IF(入力シート!$A9="","",2) | AL5: =IF(入力シート!$A9="","","") | AM5: =IF(入力シート!$A9="","","") | AN5: =IF(入力シート!$A9="","",入力シート!C9) | AO5: =IF(入力シート!$A9="","","") | AP5: =IF(入力シート!$A9="","","") | AQ5: =IF(入力シート!$A9="","","")
A6: =IF(入力シート!$A10="","",1) | B6: =IF(入力シート!$A10="","",1) | C6: =IF(入力シート!$A10="","",0) | D6: =IF(入力シート!$A10="","",TEXT(入力シート!A10,"YYYYMMDD")) | E6: =IF(入力シート!$A10="","",TEXT(入力シート!Q10,"00000000")) | F6: =IF(入力シート!$A10="","",14) | G6: =IF(入力シート!$A10="","",1) | H6: =IF(入力シート!$A10="","",1) | I6: =IF(入力シート!$A10="","",3) | J6: =IF(入力シート!$A10="","",1) | K6: =IF(入力シート!$A10="","",入力シート!B10) | L6: =IF(入力シート!$A10="","","") | M6: =IF(入力シート!$A10="","","") | N6: =IF(入力シート!$A10="","",入力シート!R10) | O6: =IF(入力シート!$A10="","",IF(入力シート!G10="",1,入力シート!G10)) | P6: =IF(入力シート!$A10="","",入力シート!D10) | Q6: =IF(入力シート!$A10="","","") | R6: =IF(入力シート!$A10="","",入力シート!J10) | S6: =IF(入力シート!$A10="","",入力シート!L10) | T6: =IF(入力シート!$A10="","",入力シート!K10) | U6: =IF(入力シート!$A10="","",0) | V6: =IF(入力シート!$A10="","",0) | W6: =IF(入力シート!$A10="","","0000") | X6: =IF(入力シート!$A10="","",入力シート!E10) | Y6: =IF(入力シート!$A10="","",入力シート!F10) | Z6: =IF(入力シート!$A10="","",入力シート!O10) | AA6: =IF(入力シート!$A10="","","") | AB6: =IF(入力シート!$A10="","",入力シート!P10) | AC6: =IF(入力シート!$A10="","",入力シート!U10) | AD6: =IF(入力シート!$A10="","",0) | AE6: =IF(入力シート!$A10="","",入力シート!I10) | AF6: =IF(入力シート!$A10="","",入力シート!M10) | AG6: =IF(入力シート!$A10="","",入力シート!N10) | AH6: =IF(入力シート!$A10="","","") | AI6: =IF(入力シート!$A10="","","") | AJ6: =IF(入力シート!$A10="","","") | AK6: =IF(入力シート!$A10="","",2) | AL6: =IF(入力シート!$A10="","","") | AM6: =IF(入力シート!$A10="","","") | AN6: =IF(入力シート!$A10="","",入力シート!C10) | AO6: =IF(入力シート!$A10="","","") | AP6: =IF(入力シート!$A10="","","") | AQ6: =IF(入力シート!$A10="","","")
A7: =IF(入力シート!$A11="","",1) | B7: =IF(入力シート!$A11="","",1) | C7: =IF(入力シート!$A11="","",0) | D7: =IF(入力シート!$A11="","",TEXT(入力シート!A11,"YYYYMMDD")) | E7: =IF(入力シート!$A11="","",TEXT(入力シート!Q11,"00000000")) | F7: =IF(入力シート!$A11="","",14) | G7: =IF(入力シート!$A11="","",1) | H7: =IF(入力シート!$A11="","",1) | I7: =IF(入力シート!$A11="","",3) | J7: =IF(入力シート!$A11="","",1) | K7: =IF(入力シート!$A11="","",入力シート!B11) | L7: =IF(入力シート!$A11="","","") | M7: =IF(入力シート!$A11="","","") | N7: =IF(入力シート!$A11="","",入力シート!R11) | O7: =IF(入力シート!$A11="","",IF(入力シート!G11="",1,入力シート!G11)) | P7: =IF(入力シート!$A11="","",入力シート!D11) | Q7: =IF(入力シート!$A11="","","") | R7: =IF(入力シート!$A11="","",入力シート!J11) | S7: =IF(入力シート!$A11="","",入力シート!L11) | T7: =IF(入力シート!$A11="","",入力シート!K11) | U7: =IF(入力シート!$A11="","",0) | V7: =IF(入力シート!$A11="","",0) | W7: =IF(入力シート!$A11="","","0000") | X7: =IF(入力シート!$A11="","",入力シート!E11) | Y7: =IF(入力シート!$A11="","",入力シート!F11) | Z7: =IF(入力シート!$A11="","",入力シート!O11) | AA7: =IF(入力シート!$A11="","","") | AB7: =IF(入力シート!$A11="","",入力シート!P11) | AC7: =IF(入力シート!$A11="","",入力シート!U11) | AD7: =IF(入力シート!$A11="","",0) | AE7: =IF(入力シート!$A11="","",入力シート!I11) | AF7: =IF(入力シート!$A11="","",入力シート!M11) | AG7: =IF(入力シート!$A11="","",入力シート!N11) | AH7: =IF(入力シート!$A11="","","") | AI7: =IF(入力シート!$A11="","","") | AJ7: =IF(入力シート!$A11="","","") | AK7: =IF(入力シート!$A11="","",2) | AL7: =IF(入力シート!$A11="","","") | AM7: =IF(入力シート!$A11="","","") | AN7: =IF(入力シート!$A11="","",入力シート!C11) | AO7: =IF(入力シート!$A11="","","") | AP7: =IF(入力シート!$A11="","","") | AQ7: =IF(入力シート!$A11="","","")
A8: =IF(入力シート!$A12="","",1) | B8: =IF(入力シート!$A12="","",1) | C8: =IF(入力シート!$A12="","",0) | D8: =IF(入力シート!$A12="","",TEXT(入力シート!A12,"YYYYMMDD")) | E8: =IF(入力シート!$A12="","",TEXT(入力シート!Q12,"00000000")) | F8: =IF(入力シート!$A12="","",14) | G8: =IF(入力シート!$A12="","",1) | H8: =IF(入力シート!$A12="","",1) | I8: =IF(入力シート!$A12="","",3) | J8: =IF(入力シート!$A12="","",1) | K8: =IF(入力シート!$A12="","",入力シート!B12) | L8: =IF(入力シート!$A12="","","") | M8: =IF(入力シート!$A12="","","") | N8: =IF(入力シート!$A12="","",入力シート!R12) | O8: =IF(入力シート!$A12="","",IF(入力シート!G12="",1,入力シート!G12)) | P8: =IF(入力シート!$A12="","",入力シート!D12) | Q8: =IF(入力シート!$A12="","","") | R8: =IF(入力シート!$A12="","",入力シート!J12) | S8: =IF(入力シート!$A12="","",入力シート!L12) | T8: =IF(入力シート!$A12="","",入力シート!K12) | U8: =IF(入力シート!$A12="","",0) | V8: =IF(入力シート!$A12="","",0) | W8: =IF(入力シート!$A12="","","0000") | X8: =IF(入力シート!$A12="","",入力シート!E12) | Y8: =IF(入力シート!$A12="","",入力シート!F12) | Z8: =IF(入力シート!$A12="","",入力シート!O12) | AA8: =IF(入力シート!$A12="","","") | AB8: =IF(入力シート!$A12="","",入力シート!P12) | AC8: =IF(入力シート!$A12="","",入力シート!U12) | AD8: =IF(入力シート!$A12="","",0) | AE8: =IF(入力シート!$A12="","",入力シート!I12) | AF8: =IF(入力シート!$A12="","",入力シート!M12) | AG8: =IF(入力シート!$A12="","",入力シート!N12) | AH8: =IF(入力シート!$A12="","","") | AI8: =IF(入力シート!$A12="","","") | AJ8: =IF(入力シート!$A12="","","") | AK8: =IF(入力シート!$A12="","",2) | AL8: =IF(入力シート!$A12="","","") | AM8: =IF(入力シート!$A12="","","") | AN8: =IF(入力シート!$A12="","",入力シート!C12) | AO8: =IF(入力シート!$A12="","","") | AP8: =IF(入力シート!$A12="","","") | AQ8: =IF(入力シート!$A12="","","")
A9: =IF(入力シート!$A13="","",1) | B9: =IF(入力シート!$A13="","",1) | C9: =IF(入力シート!$A13="","",0) | D9: =IF(入力シート!$A13="","",TEXT(入力シート!A13,"YYYYMMDD")) | E9: =IF(入力シート!$A13="","",TEXT(入力シート!Q13,"00000000")) | F9: =IF(入力シート!$A13="","",14) | G9: =IF(入力シート!$A13="","",1) | H9: =IF(入力シート!$A13="","",1) | I9: =IF(入力シート!$A13="","",3) | J9: =IF(入力シート!$A13="","",1) | K9: =IF(入力シート!$A13="","",入力シート!B13) | L9: =IF(入力シート!$A13="","","") | M9: =IF(入力シート!$A13="","","") | N9: =IF(入力シート!$A13="","",入力シート!R13) | O9: =IF(入力シート!$A13="","",IF(入力シート!G13="",1,入力シート!G13)) | P9: =IF(入力シート!$A13="","",入力シート!D13) | Q9: =IF(入力シート!$A13="","","") | R9: =IF(入力シート!$A13="","",入力シート!J13) | S9: =IF(入力シート!$A13="","",入力シート!L13) | T9: =IF(入力シート!$A13="","",入力シート!K13) | U9: =IF(入力シート!$A13="","",0) | V9: =IF(入力シート!$A13="","",0) | W9: =IF(入力シート!$A13="","","0000") | X9: =IF(入力シート!$A13="","",入力シート!E13) | Y9: =IF(入力シート!$A13="","",入力シート!F13) | Z9: =IF(入力シート!$A13="","",入力シート!O13) | AA9: =IF(入力シート!$A13="","","") | AB9: =IF(入力シート!$A13="","",入力シート!P13) | AC9: =IF(入力シート!$A13="","",入力シート!U13) | AD9: =IF(入力シート!$A13="","",0) | AE9: =IF(入力シート!$A13="","",入力シート!I13) | AF9: =IF(入力シート!$A13="","",入力シート!M13) | AG9: =IF(入力シート!$A13="","",入力シート!N13) | AH9: =IF(入力シート!$A13="","","") | AI9: =IF(入力シート!$A13="","","") | AJ9: =IF(入力シート!$A13="","","") | AK9: =IF(入力シート!$A13="","",2) | AL9: =IF(入力シート!$A13="","","") | AM9: =IF(入力シート!$A13="","","") | AN9: =IF(入力シート!$A13="","",入力シート!C13) | AO9: =IF(入力シート!$A13="","","") | AP9: =IF(入力シート!$A13="","","") | AQ9: =IF(入力シート!$A13="","","")
A10: =IF(入力シート!$A14="","",1) | B10: =IF(入力シート!$A14="","",1) | C10: =IF(入力シート!$A14="","",0) | D10: =IF(入力シート!$A14="","",TEXT(入力シート!A14,"YYYYMMDD")) | E10: =IF(入力シート!$A14="","",TEXT(入力シート!Q14,"00000000")) | F10: =IF(入力シート!$A14="","",14) | G10: =IF(入力シート!$A14="","",1) | H10: =IF(入力シート!$A14="","",1) | I10: =IF(入力シート!$A14="","",3) | J10: =IF(入力シート!$A14="","",1) | K10: =IF(入力シート!$A14="","",入力シート!B14) | L10: =IF(入力シート!$A14="","","") | M10: =IF(入力シート!$A14="","","") | N10: =IF(入力シート!$A14="","",入力シート!R14) | O10: =IF(入力シート!$A14="","",IF(入力シート!G14="",1,入力シート!G14)) | P10: =IF(入力シート!$A14="","",入力シート!D14) | Q10: =IF(入力シート!$A14="","","") | R10: =IF(入力シート!$A14="","",入力シート!J14) | S10: =IF(入力シート!$A14="","",入力シート!L14) | T10: =IF(入力シート!$A14="","",入力シート!K14) | U10: =IF(入力シート!$A14="","",0) | V10: =IF(入力シート!$A14="","",0) | W10: =IF(入力シート!$A14="","","0000") | X10: =IF(入力シート!$A14="","",入力シート!E14) | Y10: =IF(入力シート!$A14="","",入力シート!F14) | Z10: =IF(入力シート!$A14="","",入力シート!O14) | AA10: =IF(入力シート!$A14="","","") | AB10: =IF(入力シート!$A14="","",入力シート!P14) | AC10: =IF(入力シート!$A14="","",入力シート!U14) | AD10: =IF(入力シート!$A14="","",0) | AE10: =IF(入力シート!$A14="","",入力シート!I14) | AF10: =IF(入力シート!$A14="","",入力シート!M14) | AG10: =IF(入力シート!$A14="","",入力シート!N14) | AH10: =IF(入力シート!$A14="","","") | AI10: =IF(入力シート!$A14="","","") | AJ10: =IF(入力シート!$A14="","","") | AK10: =IF(入力シート!$A14="","",2) | AL10: =IF(入力シート!$A14="","","") | AM10: =IF(入力シート!$A14="","","") | AN10: =IF(入力シート!$A14="","",入力シート!C14) | AO10: =IF(入力シート!$A14="","","") | AP10: =IF(入力シート!$A14="","","") | AQ10: =IF(入力シート!$A14="","","")
A11: =IF(入力シート!$A15="","",1) | B11: =IF(入力シート!$A15="","",1) | C11: =IF(入力シート!$A15="","",0) | D11: =IF(入力シート!$A15="","",TEXT(入力シート!A15,"YYYYMMDD")) | E11: =IF(入力シート!$A15="","",TEXT(入力シート!Q15,"00000000")) | F11: =IF(入力シート!$A15="","",14) | G11: =IF(入力シート!$A15="","",1) | H11: =IF(入力シート!$A15="","",1) | I11: =IF(入力シート!$A15="","",3) | J11: =IF(入力シート!$A15="","",1) | K11: =IF(入力シート!$A15="","",入力シート!B15) | L11: =IF(入力シート!$A15="","","") | M11: =IF(入力シート!$A15="","","") | N11: =IF(入力シート!$A15="","",入力シート!R15) | O11: =IF(入力シート!$A15="","",IF(入力シート!G15="",1,入力シート!G15)) | P11: =IF(入力シート!$A15="","",入力シート!D15) | Q11: =IF(入力シート!$A15="","","") | R11: =IF(入力シート!$A15="","",入力シート!J15) | S11: =IF(入力シート!$A15="","",入力シート!L15) | T11: =IF(入力シート!$A15="","",入力シート!K15) | U11: =IF(入力シート!$A15="","",0) | V11: =IF(入力シート!$A15="","",0) | W11: =IF(入力シート!$A15="","","0000") | X11: =IF(入力シート!$A15="","",入力シート!E15) | Y11: =IF(入力シート!$A15="","",入力シート!F15) | Z11: =IF(入力シート!$A15="","",入力シート!O15) | AA11: =IF(入力シート!$A15="","","") | AB11: =IF(入力シート!$A15="","",入力シート!P15) | AC11: =IF(入力シート!$A15="","",入力シート!U15) | AD11: =IF(入力シート!$A15="","",0) | AE11: =IF(入力シート!$A15="","",入力シート!I15) | AF11: =IF(入力シート!$A15="","",入力シート!M15) | AG11: =IF(入力シート!$A15="","",入力シート!N15) | AH11: =IF(入力シート!$A15="","","") | AI11: =IF(入力シート!$A15="","","") | AJ11: =IF(入力シート!$A15="","","") | AK11: =IF(入力シート!$A15="","",2) | AL11: =IF(入力シート!$A15="","","") | AM11: =IF(入力シート!$A15="","","") | AN11: =IF(入力シート!$A15="","",入力シート!C15) | AO11: =IF(入力シート!$A15="","","") | AP11: =IF(入力シート!$A15="","","") | AQ11: =IF(入力シート!$A15="","","")
A12: =IF(入力シート!$A16="","",1) | B12: =IF(入力シート!$A16="","",1) | C12: =IF(入力シート!$A16="","",0) | D12: =IF(入力シート!$A16="","",TEXT(入力シート!A16,"YYYYMMDD")) | E12: =IF(入力シート!$A16="","",TEXT(入力シート!Q16,"00000000")) | F12: =IF(入力シート!$A16="","",14) | G12: =IF(入力シート!$A16="","",1) | H12: =IF(入力シート!$A16="","",1) | I12: =IF(入力シート!$A16="","",3) | J12: =IF(入力シート!$A16="","",1) | K12: =IF(入力シート!$A16="","",入力シート!B16) | L12: =IF(入力シート!$A16="","","") | M12: =IF(入力シート!$A16="","","") | N12: =IF(入力シート!$A16="","",入力シート!R16) | O12: =IF(入力シート!$A16="","",IF(入力シート!G16="",1,入力シート!G16)) | P12: =IF(入力シート!$A16="","",入力シート!D16) | Q12: =IF(入力シート!$A16="","","") | R12: =IF(入力シート!$A16="","",入力シート!J16) | S12: =IF(入力シート!$A16="","",入力シート!L16) | T12: =IF(入力シート!$A16="","",入力シート!K16) | U12: =IF(入力シート!$A16="","",0) | V12: =IF(入力シート!$A16="","",0) | W12: =IF(入力シート!$A16="","","0000") | X12: =IF(入力シート!$A16="","",入力シート!E16) | Y12: =IF(入力シート!$A16="","",入力シート!F16) | Z12: =IF(入力シート!$A16="","",入力シート!O16) | AA12: =IF(入力シート!$A16="","","") | AB12: =IF(入力シート!$A16="","",入力シート!P16) | AC12: =IF(入力シート!$A16="","",入力シート!U16) | AD12: =IF(入力シート!$A16="","",0) | AE12: =IF(入力シート!$A16="","",入力シート!I16) | AF12: =IF(入力シート!$A16="","",入力シート!M16) | AG12: =IF(入力シート!$A16="","",入力シート!N16) | AH12: =IF(入力シート!$A16="","","") | AI12: =IF(入力シート!$A16="","","") | AJ12: =IF(入力シート!$A16="","","") | AK12: =IF(入力シート!$A16="","",2) | AL12: =IF(入力シート!$A16="","","") | AM12: =IF(入力シート!$A16="","","") | AN12: =IF(入力シート!$A16="","",入力シート!C16) | AO12: =IF(入力シート!$A16="","","") | AP12: =IF(入力シート!$A16="","","") | AQ12: =IF(入力シート!$A16="","","")
A13: =IF(入力シート!$A17="","",1) | B13: =IF(入力シート!$A17="","",1) | C13: =IF(入力シート!$A17="","",0) | D13: =IF(入力シート!$A17="","",TEXT(入力シート!A17,"YYYYMMDD")) | E13: =IF(入力シート!$A17="","",TEXT(入力シート!Q17,"00000000")) | F13: =IF(入力シート!$A17="","",14) | G13: =IF(入力シート!$A17="","",1) | H13: =IF(入力シート!$A17="","",1) | I13: =IF(入力シート!$A17="","",3) | J13: =IF(入力シート!$A17="","",1) | K13: =IF(入力シート!$A17="","",入力シート!B17) | L13: =IF(入力シート!$A17="","","") | M13: =IF(入力シート!$A17="","","") | N13: =IF(入力シート!$A17="","",入力シート!R17) | O13: =IF(入力シート!$A17="","",IF(入力シート!G17="",1,入力シート!G17)) | P13: =IF(入力シート!$A17="","",入力シート!D17) | Q13: =IF(入力シート!$A17="","","") | R13: =IF(入力シート!$A17="","",入力シート!J17) | S13: =IF(入力シート!$A17="","",入力シート!L17) | T13: =IF(入力シート!$A17="","",入力シート!K17) | U13: =IF(入力シート!$A17="","",0) | V13: =IF(入力シート!$A17="","",0) | W13: =IF(入力シート!$A17="","","0000") | X13: =IF(入力シート!$A17="","",入力シート!E17) | Y13: =IF(入力シート!$A17="","",入力シート!F17) | Z13: =IF(入力シート!$A17="","",入力シート!O17) | AA13: =IF(入力シート!$A17="","","") | AB13: =IF(入力シート!$A17="","",入力シート!P17) | AC13: =IF(入力シート!$A17="","",入力シート!U17) | AD13: =IF(入力シート!$A17="","",0) | AE13: =IF(入力シート!$A17="","",入力シート!I17) | AF13: =IF(入力シート!$A17="","",入力シート!M17) | AG13: =IF(入力シート!$A17="","",入力シート!N17) | AH13: =IF(入力シート!$A17="","","") | AI13: =IF(入力シート!$A17="","","") | AJ13: =IF(入力シート!$A17="","","") | AK13: =IF(入力シート!$A17="","",2) | AL13: =IF(入力シート!$A17="","","") | AM13: =IF(入力シート!$A17="","","") | AN13: =IF(入力シート!$A17="","",入力シート!C17) | AO13: =IF(入力シート!$A17="","","") | AP13: =IF(入力シート!$A17="","","") | AQ13: =IF(入力シート!$A17="","","")
... A200: =IF(入力シート!$A204="","",1) | B200: =IF(入力シート!$A204="","",1) | C200: =IF(入力シート!$A204="","",0) | D200: =IF(入力シート!$A204="","",TEXT(入力シート!A204,"YYYYMMDD")) | E200: =IF(入力シート!$A204="","",TEXT(入力シート!Q204,"00000000")) | F200: =IF(入力シート!$A204="","",14) | G200: =IF(入力シート!$A204="","",1) | H200: =IF(入力シート!$A204="","",1) | I200: =IF(入力シート!$A204="","",3) | J200: =IF(入力シート!$A204="","",1) | K200: =IF(入力シート!$A204="","",入力シート!B204) | L200: =IF(入力シート!$A204="","","") | M200: =IF(入力シート!$A204="","","") | N200: =IF(入力シート!$A204="","",入力シート!R204) | O200: =IF(入力シート!$A204="","",IF(入力シート!G204="",1,入力シート!G204)) | P200: =IF(入力シート!$A204="","",入力シート!D204) | Q200: =IF(入力シート!$A204="","","") | R200: =IF(入力シート!$A204="","",入力シート!J204) | S200: =IF(入力シート!$A204="","",入力シート!L204) | T200: =IF(入力シート!$A204="","",入力シート!K204) | U200: =IF(入力シート!$A204="","",0) | V200: =IF(入力シート!$A204="","",0) | W200: =IF(入力シート!$A204="","","0000") | X200: =IF(入力シート!$A204="","",入力シート!E204) | Y200: =IF(入力シート!$A204="","",入力シート!F204) | Z200: =IF(入力シート!$A204="","",入力シート!O204) | AA200: =IF(入力シート!$A204="","","") | AB200: =IF(入力シート!$A204="","",入力シート!P204) | AC200: =IF(入力シート!$A204="","",入力シート!U204) | AD200: =IF(入力シート!$A204="","",0) | AE200: =IF(入力シート!$A204="","",入力シート!I204) | AF200: =IF(入力シート!$A204="","",入力シート!M204) | AG200: =IF(入力シート!$A204="","",入力シート!N204) | AH200: =IF(入力シート!$A204="","","") | AI200: =IF(入力シート!$A204="","","") | AJ200: =IF(入力シート!$A204="","","") | AK200: =IF(入力シート!$A204="","",2) | AL200: =IF(入力シート!$A204="","","") | AM200: =IF(入力シート!$A204="","","") | AN200: =IF(入力シート!$A204="","",入力シート!C204) | AO200: =IF(入力シート!$A204="","","") | AP200: =IF(入力シート!$A204="","","") | AQ200: =IF(入力シート!$A204="","","")
A201: =IF(AT201="","",1) -> 1 | B201: =IF(AT201="","",1) -> 1 | C201: =IF(AT201="","",0) -> 0 | D201: =IF(AT201="","",TEXT(INDEX(入力シート!$A$5:$A$204,AT201),"YYYYMMDD")) -> 20260804 | E201: =IF(AT201="","",TEXT(INDEX(入力シート!$Q$5:$Q$204,AT201),"00000000")) -> 00000090 | F201: =IF(AT201="","",14) -> 14 | G201: =IF(AT201="","",1) -> 1 | H201: =IF(AT201="","",1) -> 1 | I201: =IF(AT201="","",3) -> 3 | J201: =IF(AT201="","",1) -> 1 | K201: =IF(AT201="","",INDEX(入力シート!$B$5:$B$204,AT201)) -> 50 | L201: =IF(AT201="","","") | M201: =IF(AT201="","","") | N201: =IF(AT201="","",COUNTIF(入力シート!$Q$5:$Q$204,INDEX(入力シート!$Q$5:$Q$204,AT201))+1) -> 3 | O201: =IF(AT201="","",99) -> 99 | P201: =IF(AT201="","","") | Q201: =IF(AT201="","","") | R201: =IF(AT201="","","消費税") -> 消費税 | S201: =IF(AT201="","",0) -> 0 | T201: =IF(AT201="","","") | U201: =IF(AT201="","",0) -> 0 | V201: =IF(AT201="","",0) -> 0 | W201: =IF(AT201="","","") | X201: =IF(AT201="","",0) -> 0 | Y201: =IF(AT201="","",0) -> 0 | Z201: =IF(AT201="","",ROUNDDOWN(SUMIF(入力シート!$Q$5:$Q$204,INDEX(入力シート!$Q$5:$Q$204,AT201),入力シート!$P$5:$P$204)*IF(INDEX(入力シート!$L$5:$L$204,AT201)=13,0.1,IF(INDEX(入力シート!$L$5:$L$204,AT201)=30,0.08,0)),0)) -> 412000 | AA201: =IF(AT201="","","") | AB201: =IF(AT201="","",0) -> 0 | AC201: =IF(AT201="","",0) -> 0 | AD201: =IF(AT201="","",0) -> 0 | AE201: =IF(AT201="","","") | AF201: =IF(AT201="","",0) -> 0 | AG201: =IF(AT201="","",0) -> 0 | AH201: =IF(AT201="","","") | AI201: =IF(AT201="","","") | AJ201: =IF(AT201="","","") | AK201: =IF(AT201="","",2) -> 2 | AL201: =IF(AT201="","","") | AM201: =IF(AT201="","","") | AN201: =IF(AT201="","",INDEX(入力シート!$C$5:$C$204,AT201)) -> 株式会社オリエンタルフーズ | AO201: =IF(AT201="","","") | AP201: =IF(AT201="","","") | AQ201: =IF(AT201="","","") | AT201: =IFERROR(MATCH(1,入力シート!$T$5:$T$204,0),"") -> 1
A202: =IF(AT202="","",1) | B202: =IF(AT202="","",1) | C202: =IF(AT202="","",0) | D202: =IF(AT202="","",TEXT(INDEX(入力シート!$A$5:$A$204,AT202),"YYYYMMDD")) | E202: =IF(AT202="","",TEXT(INDEX(入力シート!$Q$5:$Q$204,AT202),"00000000")) | F202: =IF(AT202="","",14) | G202: =IF(AT202="","",1) | H202: =IF(AT202="","",1) | I202: =IF(AT202="","",3) | J202: =IF(AT202="","",1) | K202: =IF(AT202="","",INDEX(入力シート!$B$5:$B$204,AT202)) | L202: =IF(AT202="","","") | M202: =IF(AT202="","","") | N202: =IF(AT202="","",COUNTIF(入力シート!$Q$5:$Q$204,INDEX(入力シート!$Q$5:$Q$204,AT202))+1) | O202: =IF(AT202="","",99) | P202: =IF(AT202="","","") | Q202: =IF(AT202="","","") | R202: =IF(AT202="","","消費税") | S202: =IF(AT202="","",0) | T202: =IF(AT202="","","") | U202: =IF(AT202="","",0) | V202: =IF(AT202="","",0) | W202: =IF(AT202="","","") | X202: =IF(AT202="","",0) | Y202: =IF(AT202="","",0) | Z202: =IF(AT202="","",ROUNDDOWN(SUMIF(入力シート!$Q$5:$Q$204,INDEX(入力シート!$Q$5:$Q$204,AT202),入力シート!$P$5:$P$204)*IF(INDEX(入力シート!$L$5:$L$204,AT202)=13,0.1,IF(INDEX(入力シート!$L$5:$L$204,AT202)=30,0.08,0)),0)) | AA202: =IF(AT202="","","") | AB202: =IF(AT202="","",0) | AC202: =IF(AT202="","",0) | AD202: =IF(AT202="","",0) | AE202: =IF(AT202="","","") | AF202: =IF(AT202="","",0) | AG202: =IF(AT202="","",0) | AH202: =IF(AT202="","","") | AI202: =IF(AT202="","","") | AJ202: =IF(AT202="","","") | AK202: =IF(AT202="","",2) | AL202: =IF(AT202="","","") | AM202: =IF(AT202="","","") | AN202: =IF(AT202="","",INDEX(入力シート!$C$5:$C$204,AT202)) | AO202: =IF(AT202="","","") | AP202: =IF(AT202="","","") | AQ202: =IF(AT202="","","") | AT202: =IFERROR(MATCH(2,入力シート!$T$5:$T$204,0),"")
A203: =IF(AT203="","",1) | B203: =IF(AT203="","",1) | C203: =IF(AT203="","",0) | D203: =IF(AT203="","",TEXT(INDEX(入力シート!$A$5:$A$204,AT203),"YYYYMMDD")) | E203: =IF(AT203="","",TEXT(INDEX(入力シート!$Q$5:$Q$204,AT203),"00000000")) | F203: =IF(AT203="","",14) | G203: =IF(AT203="","",1) | H203: =IF(AT203="","",1) | I203: =IF(AT203="","",3) | J203: =IF(AT203="","",1) | K203: =IF(AT203="","",INDEX(入力シート!$B$5:$B$204,AT203)) | L203: =IF(AT203="","","") | M203: =IF(AT203="","","") | N203: =IF(AT203="","",COUNTIF(入力シート!$Q$5:$Q$204,INDEX(入力シート!$Q$5:$Q$204,AT203))+1) | O203: =IF(AT203="","",99) | P203: =IF(AT203="","","") | Q203: =IF(AT203="","","") | R203: =IF(AT203="","","消費税") | S203: =IF(AT203="","",0) | T203: =IF(AT203="","","") | U203: =IF(AT203="","",0) | V203: =IF(AT203="","",0) | W203: =IF(AT203="","","") | X203: =IF(AT203="","",0) | Y203: =IF(AT203="","",0) | Z203: =IF(AT203="","",ROUNDDOWN(SUMIF(入力シート!$Q$5:$Q$204,INDEX(入力シート!$Q$5:$Q$204,AT203),入力シート!$P$5:$P$204)*IF(INDEX(入力シート!$L$5:$L$204,AT203)=13,0.1,IF(INDEX(入力シート!$L$5:$L$204,AT203)=30,0.08,0)),0)) | AA203: =IF(AT203="","","") | AB203: =IF(AT203="","",0) | AC203: =IF(AT203="","",0) | AD203: =IF(AT203="","",0) | AE203: =IF(AT203="","","") | AF203: =IF(AT203="","",0) | AG203: =IF(AT203="","",0) | AH203: =IF(AT203="","","") | AI203: =IF(AT203="","","") | AJ203: =IF(AT203="","","") | AK203: =IF(AT203="","",2) | AL203: =IF(AT203="","","") | AM203: =IF(AT203="","","") | AN203: =IF(AT203="","",INDEX(入力シート!$C$5:$C$204,AT203)) | AO203: =IF(AT203="","","") | AP203: =IF(AT203="","","") | AQ203: =IF(AT203="","","") | AT203: =IFERROR(MATCH(3,入力シート!$T$5:$T$204,0),"")
A204: =IF(AT204="","",1) | B204: =IF(AT204="","",1) | C204: =IF(AT204="","",0) | D204: =IF(AT204="","",TEXT(INDEX(入力シート!$A$5:$A$204,AT204),"YYYYMMDD")) | E204: =IF(AT204="","",TEXT(INDEX(入力シート!$Q$5:$Q$204,AT204),"00000000")) | F204: =IF(AT204="","",14) | G204: =IF(AT204="","",1) | H204: =IF(AT204="","",1) | I204: =IF(AT204="","",3) | J204: =IF(AT204="","",1) | K204: =IF(AT204="","",INDEX(入力シート!$B$5:$B$204,AT204)) | L204: =IF(AT204="","","") | M204: =IF(AT204="","","") | N204: =IF(AT204="","",COUNTIF(入力シート!$Q$5:$Q$204,INDEX(入力シート!$Q$5:$Q$204,AT204))+1) | O204: =IF(AT204="","",99) | P204: =IF(AT204="","","") | Q204: =IF(AT204="","","") | R204: =IF(AT204="","","消費税") | S204: =IF(AT204="","",0) | T204: =IF(AT204="","","") | U204: =IF(AT204="","",0) | V204: =IF(AT204="","",0) | W204: =IF(AT204="","","") | X204: =IF(AT204="","",0) | Y204: =IF(AT204="","",0) | Z204: =IF(AT204="","",ROUNDDOWN(SUMIF(入力シート!$Q$5:$Q$204,INDEX(入力シート!$Q$5:$Q$204,AT204),入力シート!$P$5:$P$204)*IF(INDEX(入力シート!$L$5:$L$204,AT204)=13,0.1,IF(INDEX(入力シート!$L$5:$L$204,AT204)=30,0.08,0)),0)) | AA204: =IF(AT204="","","") | AB204: =IF(AT204="","",0) | AC204: =IF(AT204="","",0) | AD204: =IF(AT204="","",0) | AE204: =IF(AT204="","","") | AF204: =IF(AT204="","",0) | AG204: =IF(AT204="","",0) | AH204: =IF(AT204="","","") | AI204: =IF(AT204="","","") | AJ204: =IF(AT204="","","") | AK204: =IF(AT204="","",2) | AL204: =IF(AT204="","","") | AM204: =IF(AT204="","","") | AN204: =IF(AT204="","",INDEX(入力シート!$C$5:$C$204,AT204)) | AO204: =IF(AT204="","","") | AP204: =IF(AT204="","","") | AQ204: =IF(AT204="","","") | AT204: =IFERROR(MATCH(4,入力シート!$T$5:$T$204,0),"")
A205: =IF(AT205="","",1) | B205: =IF(AT205="","",1) | C205: =IF(AT205="","",0) | D205: =IF(AT205="","",TEXT(INDEX(入力シート!$A$5:$A$204,AT205),"YYYYMMDD")) | E205: =IF(AT205="","",TEXT(INDEX(入力シート!$Q$5:$Q$204,AT205),"00000000")) | F205: =IF(AT205="","",14) | G205: =IF(AT205="","",1) | H205: =IF(AT205="","",1) | I205: =IF(AT205="","",3) | J205: =IF(AT205="","",1) | K205: =IF(AT205="","",INDEX(入力シート!$B$5:$B$204,AT205)) | L205: =IF(AT205="","","") | M205: =IF(AT205="","","") | N205: =IF(AT205="","",COUNTIF(入力シート!$Q$5:$Q$204,INDEX(入力シート!$Q$5:$Q$204,AT205))+1) | O205: =IF(AT205="","",99) | P205: =IF(AT205="","","") | Q205: =IF(AT205="","","") | R205: =IF(AT205="","","消費税") | S205: =IF(AT205="","",0) | T205: =IF(AT205="","","") | U205: =IF(AT205="","",0) | V205: =IF(AT205="","",0) | W205: =IF(AT205="","","") | X205: =IF(AT205="","",0) | Y205: =IF(AT205="","",0) | Z205: =IF(AT205="","",ROUNDDOWN(SUMIF(入力シート!$Q$5:$Q$204,INDEX(入力シート!$Q$5:$Q$204,AT205),入力シート!$P$5:$P$204)*IF(INDEX(入力シート!$L$5:$L$204,AT205)=13,0.1,IF(INDEX(入力シート!$L$5:$L$204,AT205)=30,0.08,0)),0)) | AA205: =IF(AT205="","","") | AB205: =IF(AT205="","",0) | AC205: =IF(AT205="","",0) | AD205: =IF(AT205="","",0) | AE205: =IF(AT205="","","") | AF205: =IF(AT205="","",0) | AG205: =IF(AT205="","",0) | AH205: =IF(AT205="","","") | AI205: =IF(AT205="","","") | AJ205: =IF(AT205="","","") | AK205: =IF(AT205="","",2) | AL205: =IF(AT205="","","") | AM205: =IF(AT205="","","") | AN205: =IF(AT205="","",INDEX(入力シート!$C$5:$C$204,AT205)) | AO205: =IF(AT205="","","") | AP205: =IF(AT205="","","") | AQ205: =IF(AT205="","","") | AT205: =IFERROR(MATCH(5,入力シート!$T$5:$T$204,0),"")
A206: =IF(AT206="","",1) | B206: =IF(AT206="","",1) | C206: =IF(AT206="","",0) | D206: =IF(AT206="","",TEXT(INDEX(入力シート!$A$5:$A$204,AT206),"YYYYMMDD")) | E206: =IF(AT206="","",TEXT(INDEX(入力シート!$Q$5:$Q$204,AT206),"00000000")) | F206: =IF(AT206="","",14) | G206: =IF(AT206="","",1) | H206: =IF(AT206="","",1) | I206: =IF(AT206="","",3) | J206: =IF(AT206="","",1) | K206: =IF(AT206="","",INDEX(入力シート!$B$5:$B$204,AT206)) | L206: =IF(AT206="","","") | M206: =IF(AT206="","","") | N206: =IF(AT206="","",COUNTIF(入力シート!$Q$5:$Q$204,INDEX(入力シート!$Q$5:$Q$204,AT206))+1) | O206: =IF(AT206="","",99) | P206: =IF(AT206="","","") | Q206: =IF(AT206="","","") | R206: =IF(AT206="","","消費税") | S206: =IF(AT206="","",0) | T206: =IF(AT206="","","") | U206: =IF(AT206="","",0) | V206: =IF(AT206="","",0) | W206: =IF(AT206="","","") | X206: =IF(AT206="","",0) | Y206: =IF(AT206="","",0) | Z206: =IF(AT206="","",ROUNDDOWN(SUMIF(入力シート!$Q$5:$Q$204,INDEX(入力シート!$Q$5:$Q$204,AT206),入力シート!$P$5:$P$204)*IF(INDEX(入力シート!$L$5:$L$204,AT206)=13,0.1,IF(INDEX(入力シート!$L$5:$L$204,AT206)=30,0.08,0)),0)) | AA206: =IF(AT206="","","") | AB206: =IF(AT206="","",0) | AC206: =IF(AT206="","",0) | AD206: =IF(AT206="","",0) | AE206: =IF(AT206="","","") | AF206: =IF(AT206="","",0) | AG206: =IF(AT206="","",0) | AH206: =IF(AT206="","","") | AI206: =IF(AT206="","","") | AJ206: =IF(AT206="","","") | AK206: =IF(AT206="","",2) | AL206: =IF(AT206="","","") | AM206: =IF(AT206="","","") | AN206: =IF(AT206="","",INDEX(入力シート!$C$5:$C$204,AT206)) | AO206: =IF(AT206="","","") | AP206: =IF(AT206="","","") | AQ206: =IF(AT206="","","") | AT206: =IFERROR(MATCH(6,入力シート!$T$5:$T$204,0),"")
A207: =IF(AT207="","",1) | B207: =IF(AT207="","",1) | C207: =IF(AT207="","",0) | D207: =IF(AT207="","",TEXT(INDEX(入力シート!$A$5:$A$204,AT207),"YYYYMMDD")) | E207: =IF(AT207="","",TEXT(INDEX(入力シート!$Q$5:$Q$204,AT207),"00000000")) | F207: =IF(AT207="","",14) | G207: =IF(AT207="","",1) | H207: =IF(AT207="","",1) | I207: =IF(AT207="","",3) | J207: =IF(AT207="","",1) | K207: =IF(AT207="","",INDEX(入力シート!$B$5:$B$204,AT207)) | L207: =IF(AT207="","","") | M207: =IF(AT207="","","") | N207: =IF(AT207="","",COUNTIF(入力シート!$Q$5:$Q$204,INDEX(入力シート!$Q$5:$Q$204,AT207))+1) | O207: =IF(AT207="","",99) | P207: =IF(AT207="","","") | Q207: =IF(AT207="","","") | R207: =IF(AT207="","","消費税") | S207: =IF(AT207="","",0) | T207: =IF(AT207="","","") | U207: =IF(AT207="","",0) | V207: =IF(AT207="","",0) | W207: =IF(AT207="","","") | X207: =IF(AT207="","",0) | Y207: =IF(AT207="","",0) | Z207: =IF(AT207="","",ROUNDDOWN(SUMIF(入力シート!$Q$5:$Q$204,INDEX(入力シート!$Q$5:$Q$204,AT207),入力シート!$P$5:$P$204)*IF(INDEX(入力シート!$L$5:$L$204,AT207)=13,0.1,IF(INDEX(入力シート!$L$5:$L$204,AT207)=30,0.08,0)),0)) | AA207: =IF(AT207="","","") | AB207: =IF(AT207="","",0) | AC207: =IF(AT207="","",0) | AD207: =IF(AT207="","",0) | AE207: =IF(AT207="","","") | AF207: =IF(AT207="","",0) | AG207: =IF(AT207="","",0) | AH207: =IF(AT207="","","") | AI207: =IF(AT207="","","") | AJ207: =IF(AT207="","","") | AK207: =IF(AT207="","",2) | AL207: =IF(AT207="","","") | AM207: =IF(AT207="","","") | AN207: =IF(AT207="","",INDEX(入力シート!$C$5:$C$204,AT207)) | AO207: =IF(AT207="","","") | AP207: =IF(AT207="","","") | AQ207: =IF(AT207="","","") | AT207: =IFERROR(MATCH(7,入力シート!$T$5:$T$204,0),"")
A208: =IF(AT208="","",1) | B208: =IF(AT208="","",1) | C208: =IF(AT208="","",0) | D208: =IF(AT208="","",TEXT(INDEX(入力シート!$A$5:$A$204,AT208),"YYYYMMDD")) | E208: =IF(AT208="","",TEXT(INDEX(入力シート!$Q$5:$Q$204,AT208),"00000000")) | F208: =IF(AT208="","",14) | G208: =IF(AT208="","",1) | H208: =IF(AT208="","",1) | I208: =IF(AT208="","",3) | J208: =IF(AT208="","",1) | K208: =IF(AT208="","",INDEX(入力シート!$B$5:$B$204,AT208)) | L208: =IF(AT208="","","") | M208: =IF(AT208="","","") | N208: =IF(AT208="","",COUNTIF(入力シート!$Q$5:$Q$204,INDEX(入力シート!$Q$5:$Q$204,AT208))+1) | O208: =IF(AT208="","",99) | P208: =IF(AT208="","","") | Q208: =IF(AT208="","","") | R208: =IF(AT208="","","消費税") | S208: =IF(AT208="","",0) | T208: =IF(AT208="","","") | U208: =IF(AT208="","",0) | V208: =IF(AT208="","",0) | W208: =IF(AT208="","","") | X208: =IF(AT208="","",0) | Y208: =IF(AT208="","",0) | Z208: =IF(AT208="","",ROUNDDOWN(SUMIF(入力シート!$Q$5:$Q$204,INDEX(入力シート!$Q$5:$Q$204,AT208),入力シート!$P$5:$P$204)*IF(INDEX(入力シート!$L$5:$L$204,AT208)=13,0.1,IF(INDEX(入力シート!$L$5:$L$204,AT208)=30,0.08,0)),0)) | AA208: =IF(AT208="","","") | AB208: =IF(AT208="","",0) | AC208: =IF(AT208="","",0) | AD208: =IF(AT208="","",0) | AE208: =IF(AT208="","","") | AF208: =IF(AT208="","",0) | AG208: =IF(AT208="","",0) | AH208: =IF(AT208="","","") | AI208: =IF(AT208="","","") | AJ208: =IF(AT208="","","") | AK208: =IF(AT208="","",2) | AL208: =IF(AT208="","","") | AM208: =IF(AT208="","","") | AN208: =IF(AT208="","",INDEX(入力シート!$C$5:$C$204,AT208)) | AO208: =IF(AT208="","","") | AP208: =IF(AT208="","","") | AQ208: =IF(AT208="","","") | AT208: =IFERROR(MATCH(8,入力シート!$T$5:$T$204,0),"")
A209: =IF(AT209="","",1) | B209: =IF(AT209="","",1) | C209: =IF(AT209="","",0) | D209: =IF(AT209="","",TEXT(INDEX(入力シート!$A$5:$A$204,AT209),"YYYYMMDD")) | E209: =IF(AT209="","",TEXT(INDEX(入力シート!$Q$5:$Q$204,AT209),"00000000")) | F209: =IF(AT209="","",14) | G209: =IF(AT209="","",1) | H209: =IF(AT209="","",1) | I209: =IF(AT209="","",3) | J209: =IF(AT209="","",1) | K209: =IF(AT209="","",INDEX(入力シート!$B$5:$B$204,AT209)) | L209: =IF(AT209="","","") | M209: =IF(AT209="","","") | N209: =IF(AT209="","",COUNTIF(入力シート!$Q$5:$Q$204,INDEX(入力シート!$Q$5:$Q$204,AT209))+1) | O209: =IF(AT209="","",99) | P209: =IF(AT209="","","") | Q209: =IF(AT209="","","") | R209: =IF(AT209="","","消費税") | S209: =IF(AT209="","",0) | T209: =IF(AT209="","","") | U209: =IF(AT209="","",0) | V209: =IF(AT209="","",0) | W209: =IF(AT209="","","") | X209: =IF(AT209="","",0) | Y209: =IF(AT209="","",0) | Z209: =IF(AT209="","",ROUNDDOWN(SUMIF(入力シート!$Q$5:$Q$204,INDEX(入力シート!$Q$5:$Q$204,AT209),入力シート!$P$5:$P$204)*IF(INDEX(入力シート!$L$5:$L$204,AT209)=13,0.1,IF(INDEX(入力シート!$L$5:$L$204,AT209)=30,0.08,0)),0)) | AA209: =IF(AT209="","","") | AB209: =IF(AT209="","",0) | AC209: =IF(AT209="","",0) | AD209: =IF(AT209="","",0) | AE209: =IF(AT209="","","") | AF209: =IF(AT209="","",0) | AG209: =IF(AT209="","",0) | AH209: =IF(AT209="","","") | AI209: =IF(AT209="","","") | AJ209: =IF(AT209="","","") | AK209: =IF(AT209="","",2) | AL209: =IF(AT209="","","") | AM209: =IF(AT209="","","") | AN209: =IF(AT209="","",INDEX(入力シート!$C$5:$C$204,AT209)) | AO209: =IF(AT209="","","") | AP209: =IF(AT209="","","") | AQ209: =IF(AT209="","","") | AT209: =IFERROR(MATCH(9,入力シート!$T$5:$T$204,0),"")
A210: =IF(AT210="","",1) | B210: =IF(AT210="","",1) | C210: =IF(AT210="","",0) | D210: =IF(AT210="","",TEXT(INDEX(入力シート!$A$5:$A$204,AT210),"YYYYMMDD")) | E210: =IF(AT210="","",TEXT(INDEX(入力シート!$Q$5:$Q$204,AT210),"00000000")) | F210: =IF(AT210="","",14) | G210: =IF(AT210="","",1) | H210: =IF(AT210="","",1) | I210: =IF(AT210="","",3) | J210: =IF(AT210="","",1) | K210: =IF(AT210="","",INDEX(入力シート!$B$5:$B$204,AT210)) | L210: =IF(AT210="","","") | M210: =IF(AT210="","","") | N210: =IF(AT210="","",COUNTIF(入力シート!$Q$5:$Q$204,INDEX(入力シート!$Q$5:$Q$204,AT210))+1) | O210: =IF(AT210="","",99) | P210: =IF(AT210="","","") | Q210: =IF(AT210="","","") | R210: =IF(AT210="","","消費税") | S210: =IF(AT210="","",0) | T210: =IF(AT210="","","") | U210: =IF(AT210="","",0) | V210: =IF(AT210="","",0) | W210: =IF(AT210="","","") | X210: =IF(AT210="","",0) | Y210: =IF(AT210="","",0) | Z210: =IF(AT210="","",ROUNDDOWN(SUMIF(入力シート!$Q$5:$Q$204,INDEX(入力シート!$Q$5:$Q$204,AT210),入力シート!$P$5:$P$204)*IF(INDEX(入力シート!$L$5:$L$204,AT210)=13,0.1,IF(INDEX(入力シート!$L$5:$L$204,AT210)=30,0.08,0)),0)) | AA210: =IF(AT210="","","") | AB210: =IF(AT210="","",0) | AC210: =IF(AT210="","",0) | AD210: =IF(AT210="","",0) | AE210: =IF(AT210="","","") | AF210: =IF(AT210="","",0) | AG210: =IF(AT210="","",0) | AH210: =IF(AT210="","","") | AI210: =IF(AT210="","","") | AJ210: =IF(AT210="","","") | AK210: =IF(AT210="","",2) | AL210: =IF(AT210="","","") | AM210: =IF(AT210="","","") | AN210: =IF(AT210="","",INDEX(入力シート!$C$5:$C$204,AT210)) | AO210: =IF(AT210="","","") | AP210: =IF(AT210="","","") | AQ210: =IF(AT210="","","") | AT210: =IFERROR(MATCH(10,入力シート!$T$5:$T$204,0),"")
A211: =IF(AT211="","",1) | B211: =IF(AT211="","",1) | C211: =IF(AT211="","",0) | D211: =IF(AT211="","",TEXT(INDEX(入力シート!$A$5:$A$204,AT211),"YYYYMMDD")) | E211: =IF(AT211="","",TEXT(INDEX(入力シート!$Q$5:$Q$204,AT211),"00000000")) | F211: =IF(AT211="","",14) | G211: =IF(AT211="","",1) | H211: =IF(AT211="","",1) | I211: =IF(AT211="","",3) | J211: =IF(AT211="","",1) | K211: =IF(AT211="","",INDEX(入力シート!$B$5:$B$204,AT211)) | L211: =IF(AT211="","","") | M211: =IF(AT211="","","") | N211: =IF(AT211="","",COUNTIF(入力シート!$Q$5:$Q$204,INDEX(入力シート!$Q$5:$Q$204,AT211))+1) | O211: =IF(AT211="","",99) | P211: =IF(AT211="","","") | Q211: =IF(AT211="","","") | R211: =IF(AT211="","","消費税") | S211: =IF(AT211="","",0) | T211: =IF(AT211="","","") | U211: =IF(AT211="","",0) | V211: =IF(AT211="","",0) | W211: =IF(AT211="","","") | X211: =IF(AT211="","",0) | Y211: =IF(AT211="","",0) | Z211: =IF(AT211="","",ROUNDDOWN(SUMIF(入力シート!$Q$5:$Q$204,INDEX(入力シート!$Q$5:$Q$204,AT211),入力シート!$P$5:$P$204)*IF(INDEX(入力シート!$L$5:$L$204,AT211)=13,0.1,IF(INDEX(入力シート!$L$5:$L$204,AT211)=30,0.08,0)),0)) | AA211: =IF(AT211="","","") | AB211: =IF(AT211="","",0) | AC211: =IF(AT211="","",0) | AD211: =IF(AT211="","",0) | AE211: =IF(AT211="","","") | AF211: =IF(AT211="","",0) | AG211: =IF(AT211="","",0) | AH211: =IF(AT211="","","") | AI211: =IF(AT211="","","") | AJ211: =IF(AT211="","","") | AK211: =IF(AT211="","",2) | AL211: =IF(AT211="","","") | AM211: =IF(AT211="","","") | AN211: =IF(AT211="","",INDEX(入力シート!$C$5:$C$204,AT211)) | AO211: =IF(AT211="","","") | AP211: =IF(AT211="","","") | AQ211: =IF(AT211="","","") | AT211: =IFERROR(MATCH(11,入力シート!$T$5:$T$204,0),"")
A212: =IF(AT212="","",1) | B212: =IF(AT212="","",1) | C212: =IF(AT212="","",0) | D212: =IF(AT212="","",TEXT(INDEX(入力シート!$A$5:$A$204,AT212),"YYYYMMDD")) | E212: =IF(AT212="","",TEXT(INDEX(入力シート!$Q$5:$Q$204,AT212),"00000000")) | F212: =IF(AT212="","",14) | G212: =IF(AT212="","",1) | H212: =IF(AT212="","",1) | I212: =IF(AT212="","",3) | J212: =IF(AT212="","",1) | K212: =IF(AT212="","",INDEX(入力シート!$B$5:$B$204,AT212)) | L212: =IF(AT212="","","") | M212: =IF(AT212="","","") | N212: =IF(AT212="","",COUNTIF(入力シート!$Q$5:$Q$204,INDEX(入力シート!$Q$5:$Q$204,AT212))+1) | O212: =IF(AT212="","",99) | P212: =IF(AT212="","","") | Q212: =IF(AT212="","","") | R212: =IF(AT212="","","消費税") | S212: =IF(AT212="","",0) | T212: =IF(AT212="","","") | U212: =IF(AT212="","",0) | V212: =IF(AT212="","",0) | W212: =IF(AT212="","","") | X212: =IF(AT212="","",0) | Y212: =IF(AT212="","",0) | Z212: =IF(AT212="","",ROUNDDOWN(SUMIF(入力シート!$Q$5:$Q$204,INDEX(入力シート!$Q$5:$Q$204,AT212),入力シート!$P$5:$P$204)*IF(INDEX(入力シート!$L$5:$L$204,AT212)=13,0.1,IF(INDEX(入力シート!$L$5:$L$204,AT212)=30,0.08,0)),0)) | AA212: =IF(AT212="","","") | AB212: =IF(AT212="","",0) | AC212: =IF(AT212="","",0) | AD212: =IF(AT212="","",0) | AE212: =IF(AT212="","","") | AF212: =IF(AT212="","",0) | AG212: =IF(AT212="","",0) | AH212: =IF(AT212="","","") | AI212: =IF(AT212="","","") | AJ212: =IF(AT212="","","") | AK212: =IF(AT212="","",2) | AL212: =IF(AT212="","","") | AM212: =IF(AT212="","","") | AN212: =IF(AT212="","",INDEX(入力シート!$C$5:$C$204,AT212)) | AO212: =IF(AT212="","","") | AP212: =IF(AT212="","","") | AQ212: =IF(AT212="","","") | AT212: =IFERROR(MATCH(12,入力シート!$T$5:$T$204,0),"")
A213: =IF(AT213="","",1) | B213: =IF(AT213="","",1) | C213: =IF(AT213="","",0) | D213: =IF(AT213="","",TEXT(INDEX(入力シート!$A$5:$A$204,AT213),"YYYYMMDD")) | E213: =IF(AT213="","",TEXT(INDEX(入力シート!$Q$5:$Q$204,AT213),"00000000")) | F213: =IF(AT213="","",14) | G213: =IF(AT213="","",1) | H213: =IF(AT213="","",1) | I213: =IF(AT213="","",3) | J213: =IF(AT213="","",1) | K213: =IF(AT213="","",INDEX(入力シート!$B$5:$B$204,AT213)) | L213: =IF(AT213="","","") | M213: =IF(AT213="","","") | N213: =IF(AT213="","",COUNTIF(入力シート!$Q$5:$Q$204,INDEX(入力シート!$Q$5:$Q$204,AT213))+1) | O213: =IF(AT213="","",99) | P213: =IF(AT213="","","") | Q213: =IF(AT213="","","") | R213: =IF(AT213="","","消費税") | S213: =IF(AT213="","",0) | T213: =IF(AT213="","","") | U213: =IF(AT213="","",0) | V213: =IF(AT213="","",0) | W213: =IF(AT213="","","") | X213: =IF(AT213="","",0) | Y213: =IF(AT213="","",0) | Z213: =IF(AT213="","",ROUNDDOWN(SUMIF(入力シート!$Q$5:$Q$204,INDEX(入力シート!$Q$5:$Q$204,AT213),入力シート!$P$5:$P$204)*IF(INDEX(入力シート!$L$5:$L$204,AT213)=13,0.1,IF(INDEX(入力シート!$L$5:$L$204,AT213)=30,0.08,0)),0)) | AA213: =IF(AT213="","","") | AB213: =IF(AT213="","",0) | AC213: =IF(AT213="","",0) | AD213: =IF(AT213="","",0) | AE213: =IF(AT213="","","") | AF213: =IF(AT213="","",0) | AG213: =IF(AT213="","",0) | AH213: =IF(AT213="","","") | AI213: =IF(AT213="","","") | AJ213: =IF(AT213="","","") | AK213: =IF(AT213="","",2) | AL213: =IF(AT213="","","") | AM213: =IF(AT213="","","") | AN213: =IF(AT213="","",INDEX(入力シート!$C$5:$C$204,AT213)) | AO213: =IF(AT213="","","") | AP213: =IF(AT213="","","") | AQ213: =IF(AT213="","","") | AT213: =IFERROR(MATCH(13,入力シート!$T$5:$T$204,0),"")
A214: =IF(AT214="","",1) | B214: =IF(AT214="","",1) | C214: =IF(AT214="","",0) | D214: =IF(AT214="","",TEXT(INDEX(入力シート!$A$5:$A$204,AT214),"YYYYMMDD")) | E214: =IF(AT214="","",TEXT(INDEX(入力シート!$Q$5:$Q$204,AT214),"00000000")) | F214: =IF(AT214="","",14) | G214: =IF(AT214="","",1) | H214: =IF(AT214="","",1) | I214: =IF(AT214="","",3) | J214: =IF(AT214="","",1) | K214: =IF(AT214="","",INDEX(入力シート!$B$5:$B$204,AT214)) | L214: =IF(AT214="","","") | M214: =IF(AT214="","","") | N214: =IF(AT214="","",COUNTIF(入力シート!$Q$5:$Q$204,INDEX(入力シート!$Q$5:$Q$204,AT214))+1) | O214: =IF(AT214="","",99) | P214: =IF(AT214="","","") | Q214: =IF(AT214="","","") | R214: =IF(AT214="","","消費税") | S214: =IF(AT214="","",0) | T214: =IF(AT214="","","") | U214: =IF(AT214="","",0) | V214: =IF(AT214="","",0) | W214: =IF(AT214="","","") | X214: =IF(AT214="","",0) | Y214: =IF(AT214="","",0) | Z214: =IF(AT214="","",ROUNDDOWN(SUMIF(入力シート!$Q$5:$Q$204,INDEX(入力シート!$Q$5:$Q$204,AT214),入力シート!$P$5:$P$204)*IF(INDEX(入力シート!$L$5:$L$204,AT214)=13,0.1,IF(INDEX(入力シート!$L$5:$L$204,AT214)=30,0.08,0)),0)) | AA214: =IF(AT214="","","") | AB214: =IF(AT214="","",0) | AC214: =IF(AT214="","",0) | AD214: =IF(AT214="","",0) | AE214: =IF(AT214="","","") | AF214: =IF(AT214="","",0) | AG214: =IF(AT214="","",0) | AH214: =IF(AT214="","","") | AI214: =IF(AT214="","","") | AJ214: =IF(AT214="","","") | AK214: =IF(AT214="","",2) | AL214: =IF(AT214="","","") | AM214: =IF(AT214="","","") | AN214: =IF(AT214="","",INDEX(入力シート!$C$5:$C$204,AT214)) | AO214: =IF(AT214="","","") | AP214: =IF(AT214="","","") | AQ214: =IF(AT214="","","") | AT214: =IFERROR(MATCH(14,入力シート!$T$5:$T$204,0),"")
A215: =IF(AT215="","",1) | B215: =IF(AT215="","",1) | C215: =IF(AT215="","",0) | D215: =IF(AT215="","",TEXT(INDEX(入力シート!$A$5:$A$204,AT215),"YYYYMMDD")) | E215: =IF(AT215="","",TEXT(INDEX(入力シート!$Q$5:$Q$204,AT215),"00000000")) | F215: =IF(AT215="","",14) | G215: =IF(AT215="","",1) | H215: =IF(AT215="","",1) | I215: =IF(AT215="","",3) | J215: =IF(AT215="","",1) | K215: =IF(AT215="","",INDEX(入力シート!$B$5:$B$204,AT215)) | L215: =IF(AT215="","","") | M215: =IF(AT215="","","") | N215: =IF(AT215="","",COUNTIF(入力シート!$Q$5:$Q$204,INDEX(入力シート!$Q$5:$Q$204,AT215))+1) | O215: =IF(AT215="","",99) | P215: =IF(AT215="","","") | Q215: =IF(AT215="","","") | R215: =IF(AT215="","","消費税") | S215: =IF(AT215="","",0) | T215: =IF(AT215="","","") | U215: =IF(AT215="","",0) | V215: =IF(AT215="","",0) | W215: =IF(AT215="","","") | X215: =IF(AT215="","",0) | Y215: =IF(AT215="","",0) | Z215: =IF(AT215="","",ROUNDDOWN(SUMIF(入力シート!$Q$5:$Q$204,INDEX(入力シート!$Q$5:$Q$204,AT215),入力シート!$P$5:$P$204)*IF(INDEX(入力シート!$L$5:$L$204,AT215)=13,0.1,IF(INDEX(入力シート!$L$5:$L$204,AT215)=30,0.08,0)),0)) | AA215: =IF(AT215="","","") | AB215: =IF(AT215="","",0) | AC215: =IF(AT215="","",0) | AD215: =IF(AT215="","",0) | AE215: =IF(AT215="","","") | AF215: =IF(AT215="","",0) | AG215: =IF(AT215="","",0) | AH215: =IF(AT215="","","") | AI215: =IF(AT215="","","") | AJ215: =IF(AT215="","","") | AK215: =IF(AT215="","",2) | AL215: =IF(AT215="","","") | AM215: =IF(AT215="","","") | AN215: =IF(AT215="","",INDEX(入力シート!$C$5:$C$204,AT215)) | AO215: =IF(AT215="","","") | AP215: =IF(AT215="","","") | AQ215: =IF(AT215="","","") | AT215: =IFERROR(MATCH(15,入力シート!$T$5:$T$204,0),"")
A216: =IF(AT216="","",1) | B216: =IF(AT216="","",1) | C216: =IF(AT216="","",0) | D216: =IF(AT216="","",TEXT(INDEX(入力シート!$A$5:$A$204,AT216),"YYYYMMDD")) | E216: =IF(AT216="","",TEXT(INDEX(入力シート!$Q$5:$Q$204,AT216),"00000000")) | F216: =IF(AT216="","",14) | G216: =IF(AT216="","",1) | H216: =IF(AT216="","",1) | I216: =IF(AT216="","",3) | J216: =IF(AT216="","",1) | K216: =IF(AT216="","",INDEX(入力シート!$B$5:$B$204,AT216)) | L216: =IF(AT216="","","") | M216: =IF(AT216="","","") | N216: =IF(AT216="","",COUNTIF(入力シート!$Q$5:$Q$204,INDEX(入力シート!$Q$5:$Q$204,AT216))+1) | O216: =IF(AT216="","",99) | P216: =IF(AT216="","","") | Q216: =IF(AT216="","","") | R216: =IF(AT216="","","消費税") | S216: =IF(AT216="","",0) | T216: =IF(AT216="","","") | U216: =IF(AT216="","",0) | V216: =IF(AT216="","",0) | W216: =IF(AT216="","","") | X216: =IF(AT216="","",0) | Y216: =IF(AT216="","",0) | Z216: =IF(AT216="","",ROUNDDOWN(SUMIF(入力シート!$Q$5:$Q$204,INDEX(入力シート!$Q$5:$Q$204,AT216),入力シート!$P$5:$P$204)*IF(INDEX(入力シート!$L$5:$L$204,AT216)=13,0.1,IF(INDEX(入力シート!$L$5:$L$204,AT216)=30,0.08,0)),0)) | AA216: =IF(AT216="","","") | AB216: =IF(AT216="","",0) | AC216: =IF(AT216="","",0) | AD216: =IF(AT216="","",0) | AE216: =IF(AT216="","","") | AF216: =IF(AT216="","",0) | AG216: =IF(AT216="","",0) | AH216: =IF(AT216="","","") | AI216: =IF(AT216="","","") | AJ216: =IF(AT216="","","") | AK216: =IF(AT216="","",2) | AL216: =IF(AT216="","","") | AM216: =IF(AT216="","","") | AN216: =IF(AT216="","",INDEX(入力シート!$C$5:$C$204,AT216)) | AO216: =IF(AT216="","","") | AP216: =IF(AT216="","","") | AQ216: =IF(AT216="","","") | AT216: =IFERROR(MATCH(16,入力シート!$T$5:$T$204,0),"")
A217: =IF(AT217="","",1) | B217: =IF(AT217="","",1) | C217: =IF(AT217="","",0) | D217: =IF(AT217="","",TEXT(INDEX(入力シート!$A$5:$A$204,AT217),"YYYYMMDD")) | E217: =IF(AT217="","",TEXT(INDEX(入力シート!$Q$5:$Q$204,AT217),"00000000")) | F217: =IF(AT217="","",14) | G217: =IF(AT217="","",1) | H217: =IF(AT217="","",1) | I217: =IF(AT217="","",3) | J217: =IF(AT217="","",1) | K217: =IF(AT217="","",INDEX(入力シート!$B$5:$B$204,AT217)) | L217: =IF(AT217="","","") | M217: =IF(AT217="","","") | N217: =IF(AT217="","",COUNTIF(入力シート!$Q$5:$Q$204,INDEX(入力シート!$Q$5:$Q$204,AT217))+1) | O217: =IF(AT217="","",99) | P217: =IF(AT217="","","") | Q217: =IF(AT217="","","") | R217: =IF(AT217="","","消費税") | S217: =IF(AT217="","",0) | T217: =IF(AT217="","","") | U217: =IF(AT217="","",0) | V217: =IF(AT217="","",0) | W217: =IF(AT217="","","") | X217: =IF(AT217="","",0) | Y217: =IF(AT217="","",0) | Z217: =IF(AT217="","",ROUNDDOWN(SUMIF(入力シート!$Q$5:$Q$204,INDEX(入力シート!$Q$5:$Q$204,AT217),入力シート!$P$5:$P$204)*IF(INDEX(入力シート!$L$5:$L$204,AT217)=13,0.1,IF(INDEX(入力シート!$L$5:$L$204,AT217)=30,0.08,0)),0)) | AA217: =IF(AT217="","","") | AB217: =IF(AT217="","",0) | AC217: =IF(AT217="","",0) | AD217: =IF(AT217="","",0) | AE217: =IF(AT217="","","") | AF217: =IF(AT217="","",0) | AG217: =IF(AT217="","",0) | AH217: =IF(AT217="","","") | AI217: =IF(AT217="","","") | AJ217: =IF(AT217="","","") | AK217: =IF(AT217="","",2) | AL217: =IF(AT217="","","") | AM217: =IF(AT217="","","") | AN217: =IF(AT217="","",INDEX(入力シート!$C$5:$C$204,AT217)) | AO217: =IF(AT217="","","") | AP217: =IF(AT217="","","") | AQ217: =IF(AT217="","","") | AT217: =IFERROR(MATCH(17,入力シート!$T$5:$T$204,0),"")
A218: =IF(AT218="","",1) | B218: =IF(AT218="","",1) | C218: =IF(AT218="","",0) | D218: =IF(AT218="","",TEXT(INDEX(入力シート!$A$5:$A$204,AT218),"YYYYMMDD")) | E218: =IF(AT218="","",TEXT(INDEX(入力シート!$Q$5:$Q$204,AT218),"00000000")) | F218: =IF(AT218="","",14) | G218: =IF(AT218="","",1) | H218: =IF(AT218="","",1) | I218: =IF(AT218="","",3) | J218: =IF(AT218="","",1) | K218: =IF(AT218="","",INDEX(入力シート!$B$5:$B$204,AT218)) | L218: =IF(AT218="","","") | M218: =IF(AT218="","","") | N218: =IF(AT218="","",COUNTIF(入力シート!$Q$5:$Q$204,INDEX(入力シート!$Q$5:$Q$204,AT218))+1) | O218: =IF(AT218="","",99) | P218: =IF(AT218="","","") | Q218: =IF(AT218="","","") | R218: =IF(AT218="","","消費税") | S218: =IF(AT218="","",0) | T218: =IF(AT218="","","") | U218: =IF(AT218="","",0) | V218: =IF(AT218="","",0) | W218: =IF(AT218="","","") | X218: =IF(AT218="","",0) | Y218: =IF(AT218="","",0) | Z218: =IF(AT218="","",ROUNDDOWN(SUMIF(入力シート!$Q$5:$Q$204,INDEX(入力シート!$Q$5:$Q$204,AT218),入力シート!$P$5:$P$204)*IF(INDEX(入力シート!$L$5:$L$204,AT218)=13,0.1,IF(INDEX(入力シート!$L$5:$L$204,AT218)=30,0.08,0)),0)) | AA218: =IF(AT218="","","") | AB218: =IF(AT218="","",0) | AC218: =IF(AT218="","",0) | AD218: =IF(AT218="","",0) | AE218: =IF(AT218="","","") | AF218: =IF(AT218="","",0) | AG218: =IF(AT218="","",0) | AH218: =IF(AT218="","","") | AI218: =IF(AT218="","","") | AJ218: =IF(AT218="","","") | AK218: =IF(AT218="","",2) | AL218: =IF(AT218="","","") | AM218: =IF(AT218="","","") | AN218: =IF(AT218="","",INDEX(入力シート!$C$5:$C$204,AT218)) | AO218: =IF(AT218="","","") | AP218: =IF(AT218="","","") | AQ218: =IF(AT218="","","") | AT218: =IFERROR(MATCH(18,入力シート!$T$5:$T$204,0),"")
A219: =IF(AT219="","",1) | B219: =IF(AT219="","",1) | C219: =IF(AT219="","",0) | D219: =IF(AT219="","",TEXT(INDEX(入力シート!$A$5:$A$204,AT219),"YYYYMMDD")) | E219: =IF(AT219="","",TEXT(INDEX(入力シート!$Q$5:$Q$204,AT219),"00000000")) | F219: =IF(AT219="","",14) | G219: =IF(AT219="","",1) | H219: =IF(AT219="","",1) | I219: =IF(AT219="","",3) | J219: =IF(AT219="","",1) | K219: =IF(AT219="","",INDEX(入力シート!$B$5:$B$204,AT219)) | L219: =IF(AT219="","","") | M219: =IF(AT219="","","") | N219: =IF(AT219="","",COUNTIF(入力シート!$Q$5:$Q$204,INDEX(入力シート!$Q$5:$Q$204,AT219))+1) | O219: =IF(AT219="","",99) | P219: =IF(AT219="","","") | Q219: =IF(AT219="","","") | R219: =IF(AT219="","","消費税") | S219: =IF(AT219="","",0) | T219: =IF(AT219="","","") | U219: =IF(AT219="","",0) | V219: =IF(AT219="","",0) | W219: =IF(AT219="","","") | X219: =IF(AT219="","",0) | Y219: =IF(AT219="","",0) | Z219: =IF(AT219="","",ROUNDDOWN(SUMIF(入力シート!$Q$5:$Q$204,INDEX(入力シート!$Q$5:$Q$204,AT219),入力シート!$P$5:$P$204)*IF(INDEX(入力シート!$L$5:$L$204,AT219)=13,0.1,IF(INDEX(入力シート!$L$5:$L$204,AT219)=30,0.08,0)),0)) | AA219: =IF(AT219="","","") | AB219: =IF(AT219="","",0) | AC219: =IF(AT219="","",0) | AD219: =IF(AT219="","",0) | AE219: =IF(AT219="","","") | AF219: =IF(AT219="","",0) | AG219: =IF(AT219="","",0) | AH219: =IF(AT219="","","") | AI219: =IF(AT219="","","") | AJ219: =IF(AT219="","","") | AK219: =IF(AT219="","",2) | AL219: =IF(AT219="","","") | AM219: =IF(AT219="","","") | AN219: =IF(AT219="","",INDEX(入力シート!$C$5:$C$204,AT219)) | AO219: =IF(AT219="","","") | AP219: =IF(AT219="","","") | AQ219: =IF(AT219="","","") | AT219: =IFERROR(MATCH(19,入力シート!$T$5:$T$204,0),"")
A220: =IF(AT220="","",1) | B220: =IF(AT220="","",1) | C220: =IF(AT220="","",0) | D220: =IF(AT220="","",TEXT(INDEX(入力シート!$A$5:$A$204,AT220),"YYYYMMDD")) | E220: =IF(AT220="","",TEXT(INDEX(入力シート!$Q$5:$Q$204,AT220),"00000000")) | F220: =IF(AT220="","",14) | G220: =IF(AT220="","",1) | H220: =IF(AT220="","",1) | I220: =IF(AT220="","",3) | J220: =IF(AT220="","",1) | K220: =IF(AT220="","",INDEX(入力シート!$B$5:$B$204,AT220)) | L220: =IF(AT220="","","") | M220: =IF(AT220="","","") | N220: =IF(AT220="","",COUNTIF(入力シート!$Q$5:$Q$204,INDEX(入力シート!$Q$5:$Q$204,AT220))+1) | O220: =IF(AT220="","",99) | P220: =IF(AT220="","","") | Q220: =IF(AT220="","","") | R220: =IF(AT220="","","消費税") | S220: =IF(AT220="","",0) | T220: =IF(AT220="","","") | U220: =IF(AT220="","",0) | V220: =IF(AT220="","",0) | W220: =IF(AT220="","","") | X220: =IF(AT220="","",0) | Y220: =IF(AT220="","",0) | Z220: =IF(AT220="","",ROUNDDOWN(SUMIF(入力シート!$Q$5:$Q$204,INDEX(入力シート!$Q$5:$Q$204,AT220),入力シート!$P$5:$P$204)*IF(INDEX(入力シート!$L$5:$L$204,AT220)=13,0.1,IF(INDEX(入力シート!$L$5:$L$204,AT220)=30,0.08,0)),0)) | AA220: =IF(AT220="","","") | AB220: =IF(AT220="","",0) | AC220: =IF(AT220="","",0) | AD220: =IF(AT220="","",0) | AE220: =IF(AT220="","","") | AF220: =IF(AT220="","",0) | AG220: =IF(AT220="","",0) | AH220: =IF(AT220="","","") | AI220: =IF(AT220="","","") | AJ220: =IF(AT220="","","") | AK220: =IF(AT220="","",2) | AL220: =IF(AT220="","","") | AM220: =IF(AT220="","","") | AN220: =IF(AT220="","",INDEX(入力シート!$C$5:$C$204,AT220)) | AO220: =IF(AT220="","","") | AP220: =IF(AT220="","","") | AQ220: =IF(AT220="","","") | AT220: =IFERROR(MATCH(20,入力シート!$T$5:$T$204,0),"")
A221: =IF(AT221="","",1) | B221: =IF(AT221="","",1) | C221: =IF(AT221="","",0) | D221: =IF(AT221="","",TEXT(INDEX(入力シート!$A$5:$A$204,AT221),"YYYYMMDD")) | E221: =IF(AT221="","",TEXT(INDEX(入力シート!$Q$5:$Q$204,AT221),"00000000")) | F221: =IF(AT221="","",14) | G221: =IF(AT221="","",1) | H221: =IF(AT221="","",1) | I221: =IF(AT221="","",3) | J221: =IF(AT221="","",1) | K221: =IF(AT221="","",INDEX(入力シート!$B$5:$B$204,AT221)) | L221: =IF(AT221="","","") | M221: =IF(AT221="","","") | N221: =IF(AT221="","",COUNTIF(入力シート!$Q$5:$Q$204,INDEX(入力シート!$Q$5:$Q$204,AT221))+1) | O221: =IF(AT221="","",99) | P221: =IF(AT221="","","") | Q221: =IF(AT221="","","") | R221: =IF(AT221="","","消費税") | S221: =IF(AT221="","",0) | T221: =IF(AT221="","","") | U221: =IF(AT221="","",0) | V221: =IF(AT221="","",0) | W221: =IF(AT221="","","") | X221: =IF(AT221="","",0) | Y221: =IF(AT221="","",0) | Z221: =IF(AT221="","",ROUNDDOWN(SUMIF(入力シート!$Q$5:$Q$204,INDEX(入力シート!$Q$5:$Q$204,AT221),入力シート!$P$5:$P$204)*IF(INDEX(入力シート!$L$5:$L$204,AT221)=13,0.1,IF(INDEX(入力シート!$L$5:$L$204,AT221)=30,0.08,0)),0)) | AA221: =IF(AT221="","","") | AB221: =IF(AT221="","",0) | AC221: =IF(AT221="","",0) | AD221: =IF(AT221="","",0) | AE221: =IF(AT221="","","") | AF221: =IF(AT221="","",0) | AG221: =IF(AT221="","",0) | AH221: =IF(AT221="","","") | AI221: =IF(AT221="","","") | AJ221: =IF(AT221="","","") | AK221: =IF(AT221="","",2) | AL221: =IF(AT221="","","") | AM221: =IF(AT221="","","") | AN221: =IF(AT221="","",INDEX(入力シート!$C$5:$C$204,AT221)) | AO221: =IF(AT221="","","") | AP221: =IF(AT221="","","") | AQ221: =IF(AT221="","","") | AT221: =IFERROR(MATCH(21,入力シート!$T$5:$T$204,0),"")
A222: =IF(AT222="","",1) | B222: =IF(AT222="","",1) | C222: =IF(AT222="","",0) | D222: =IF(AT222="","",TEXT(INDEX(入力シート!$A$5:$A$204,AT222),"YYYYMMDD")) | E222: =IF(AT222="","",TEXT(INDEX(入力シート!$Q$5:$Q$204,AT222),"00000000")) | F222: =IF(AT222="","",14) | G222: =IF(AT222="","",1) | H222: =IF(AT222="","",1) | I222: =IF(AT222="","",3) | J222: =IF(AT222="","",1) | K222: =IF(AT222="","",INDEX(入力シート!$B$5:$B$204,AT222)) | L222: =IF(AT222="","","") | M222: =IF(AT222="","","") | N222: =IF(AT222="","",COUNTIF(入力シート!$Q$5:$Q$204,INDEX(入力シート!$Q$5:$Q$204,AT222))+1) | O222: =IF(AT222="","",99) | P222: =IF(AT222="","","") | Q222: =IF(AT222="","","") | R222: =IF(AT222="","","消費税") | S222: =IF(AT222="","",0) | T222: =IF(AT222="","","") | U222: =IF(AT222="","",0) | V222: =IF(AT222="","",0) | W222: =IF(AT222="","","") | X222: =IF(AT222="","",0) | Y222: =IF(AT222="","",0) | Z222: =IF(AT222="","",ROUNDDOWN(SUMIF(入力シート!$Q$5:$Q$204,INDEX(入力シート!$Q$5:$Q$204,AT222),入力シート!$P$5:$P$204)*IF(INDEX(入力シート!$L$5:$L$204,AT222)=13,0.1,IF(INDEX(入力シート!$L$5:$L$204,AT222)=30,0.08,0)),0)) | AA222: =IF(AT222="","","") | AB222: =IF(AT222="","",0) | AC222: =IF(AT222="","",0) | AD222: =IF(AT222="","",0) | AE222: =IF(AT222="","","") | AF222: =IF(AT222="","",0) | AG222: =IF(AT222="","",0) | AH222: =IF(AT222="","","") | AI222: =IF(AT222="","","") | AJ222: =IF(AT222="","","") | AK222: =IF(AT222="","",2) | AL222: =IF(AT222="","","") | AM222: =IF(AT222="","","") | AN222: =IF(AT222="","",INDEX(入力シート!$C$5:$C$204,AT222)) | AO222: =IF(AT222="","","") | AP222: =IF(AT222="","","") | AQ222: =IF(AT222="","","") | AT222: =IFERROR(MATCH(22,入力シート!$T$5:$T$204,0),"")
A223: =IF(AT223="","",1) | B223: =IF(AT223="","",1) | C223: =IF(AT223="","",0) | D223: =IF(AT223="","",TEXT(INDEX(入力シート!$A$5:$A$204,AT223),"YYYYMMDD")) | E223: =IF(AT223="","",TEXT(INDEX(入力シート!$Q$5:$Q$204,AT223),"00000000")) | F223: =IF(AT223="","",14) | G223: =IF(AT223="","",1) | H223: =IF(AT223="","",1) | I223: =IF(AT223="","",3) | J223: =IF(AT223="","",1) | K223: =IF(AT223="","",INDEX(入力シート!$B$5:$B$204,AT223)) | L223: =IF(AT223="","","") | M223: =IF(AT223="","","") | N223: =IF(AT223="","",COUNTIF(入力シート!$Q$5:$Q$204,INDEX(入力シート!$Q$5:$Q$204,AT223))+1) | O223: =IF(AT223="","",99) | P223: =IF(AT223="","","") | Q223: =IF(AT223="","","") | R223: =IF(AT223="","","消費税") | S223: =IF(AT223="","",0) | T223: =IF(AT223="","","") | U223: =IF(AT223="","",0) | V223: =IF(AT223="","",0) | W223: =IF(AT223="","","") | X223: =IF(AT223="","",0) | Y223: =IF(AT223="","",0) | Z223: =IF(AT223="","",ROUNDDOWN(SUMIF(入力シート!$Q$5:$Q$204,INDEX(入力シート!$Q$5:$Q$204,AT223),入力シート!$P$5:$P$204)*IF(INDEX(入力シート!$L$5:$L$204,AT223)=13,0.1,IF(INDEX(入力シート!$L$5:$L$204,AT223)=30,0.08,0)),0)) | AA223: =IF(AT223="","","") | AB223: =IF(AT223="","",0) | AC223: =IF(AT223="","",0) | AD223: =IF(AT223="","",0) | AE223: =IF(AT223="","","") | AF223: =IF(AT223="","",0) | AG223: =IF(AT223="","",0) | AH223: =IF(AT223="","","") | AI223: =IF(AT223="","","") | AJ223: =IF(AT223="","","") | AK223: =IF(AT223="","",2) | AL223: =IF(AT223="","","") | AM223: =IF(AT223="","","") | AN223: =IF(AT223="","",INDEX(入力シート!$C$5:$C$204,AT223)) | AO223: =IF(AT223="","","") | AP223: =IF(AT223="","","") | AQ223: =IF(AT223="","","") | AT223: =IFERROR(MATCH(23,入力シート!$T$5:$T$204,0),"")
A224: =IF(AT224="","",1) | B224: =IF(AT224="","",1) | C224: =IF(AT224="","",0) | D224: =IF(AT224="","",TEXT(INDEX(入力シート!$A$5:$A$204,AT224),"YYYYMMDD")) | E224: =IF(AT224="","",TEXT(INDEX(入力シート!$Q$5:$Q$204,AT224),"00000000")) | F224: =IF(AT224="","",14) | G224: =IF(AT224="","",1) | H224: =IF(AT224="","",1) | I224: =IF(AT224="","",3) | J224: =IF(AT224="","",1) | K224: =IF(AT224="","",INDEX(入力シート!$B$5:$B$204,AT224)) | L224: =IF(AT224="","","") | M224: =IF(AT224="","","") | N224: =IF(AT224="","",COUNTIF(入力シート!$Q$5:$Q$204,INDEX(入力シート!$Q$5:$Q$204,AT224))+1) | O224: =IF(AT224="","",99) | P224: =IF(AT224="","","") | Q224: =IF(AT224="","","") | R224: =IF(AT224="","","消費税") | S224: =IF(AT224="","",0) | T224: =IF(AT224="","","") | U224: =IF(AT224="","",0) | V224: =IF(AT224="","",0) | W224: =IF(AT224="","","") | X224: =IF(AT224="","",0) | Y224: =IF(AT224="","",0) | Z224: =IF(AT224="","",ROUNDDOWN(SUMIF(入力シート!$Q$5:$Q$204,INDEX(入力シート!$Q$5:$Q$204,AT224),入力シート!$P$5:$P$204)*IF(INDEX(入力シート!$L$5:$L$204,AT224)=13,0.1,IF(INDEX(入力シート!$L$5:$L$204,AT224)=30,0.08,0)),0)) | AA224: =IF(AT224="","","") | AB224: =IF(AT224="","",0) | AC224: =IF(AT224="","",0) | AD224: =IF(AT224="","",0) | AE224: =IF(AT224="","","") | AF224: =IF(AT224="","",0) | AG224: =IF(AT224="","",0) | AH224: =IF(AT224="","","") | AI224: =IF(AT224="","","") | AJ224: =IF(AT224="","","") | AK224: =IF(AT224="","",2) | AL224: =IF(AT224="","","") | AM224: =IF(AT224="","","") | AN224: =IF(AT224="","",INDEX(入力シート!$C$5:$C$204,AT224)) | AO224: =IF(AT224="","","") | AP224: =IF(AT224="","","") | AQ224: =IF(AT224="","","") | AT224: =IFERROR(MATCH(24,入力シート!$T$5:$T$204,0),"")
A225: =IF(AT225="","",1) | B225: =IF(AT225="","",1) | C225: =IF(AT225="","",0) | D225: =IF(AT225="","",TEXT(INDEX(入力シート!$A$5:$A$204,AT225),"YYYYMMDD")) | E225: =IF(AT225="","",TEXT(INDEX(入力シート!$Q$5:$Q$204,AT225),"00000000")) | F225: =IF(AT225="","",14) | G225: =IF(AT225="","",1) | H225: =IF(AT225="","",1) | I225: =IF(AT225="","",3) | J225: =IF(AT225="","",1) | K225: =IF(AT225="","",INDEX(入力シート!$B$5:$B$204,AT225)) | L225: =IF(AT225="","","") | M225: =IF(AT225="","","") | N225: =IF(AT225="","",COUNTIF(入力シート!$Q$5:$Q$204,INDEX(入力シート!$Q$5:$Q$204,AT225))+1) | O225: =IF(AT225="","",99) | P225: =IF(AT225="","","") | Q225: =IF(AT225="","","") | R225: =IF(AT225="","","消費税") | S225: =IF(AT225="","",0) | T225: =IF(AT225="","","") | U225: =IF(AT225="","",0) | V225: =IF(AT225="","",0) | W225: =IF(AT225="","","") | X225: =IF(AT225="","",0) | Y225: =IF(AT225="","",0) | Z225: =IF(AT225="","",ROUNDDOWN(SUMIF(入力シート!$Q$5:$Q$204,INDEX(入力シート!$Q$5:$Q$204,AT225),入力シート!$P$5:$P$204)*IF(INDEX(入力シート!$L$5:$L$204,AT225)=13,0.1,IF(INDEX(入力シート!$L$5:$L$204,AT225)=30,0.08,0)),0)) | AA225: =IF(AT225="","","") | AB225: =IF(AT225="","",0) | AC225: =IF(AT225="","",0) | AD225: =IF(AT225="","",0) | AE225: =IF(AT225="","","") | AF225: =IF(AT225="","",0) | AG225: =IF(AT225="","",0) | AH225: =IF(AT225="","","") | AI225: =IF(AT225="","","") | AJ225: =IF(AT225="","","") | AK225: =IF(AT225="","",2) | AL225: =IF(AT225="","","") | AM225: =IF(AT225="","","") | AN225: =IF(AT225="","",INDEX(入力シート!$C$5:$C$204,AT225)) | AO225: =IF(AT225="","","") | AP225: =IF(AT225="","","") | AQ225: =IF(AT225="","","") | AT225: =IFERROR(MATCH(25,入力シート!$T$5:$T$204,0),"")
A226: =IF(AT226="","",1) | B226: =IF(AT226="","",1) | C226: =IF(AT226="","",0) | D226: =IF(AT226="","",TEXT(INDEX(入力シート!$A$5:$A$204,AT226),"YYYYMMDD")) | E226: =IF(AT226="","",TEXT(INDEX(入力シート!$Q$5:$Q$204,AT226),"00000000")) | F226: =IF(AT226="","",14) | G226: =IF(AT226="","",1) | H226: =IF(AT226="","",1) | I226: =IF(AT226="","",3) | J226: =IF(AT226="","",1) | K226: =IF(AT226="","",INDEX(入力シート!$B$5:$B$204,AT226)) | L226: =IF(AT226="","","") | M226: =IF(AT226="","","") | N226: =IF(AT226="","",COUNTIF(入力シート!$Q$5:$Q$204,INDEX(入力シート!$Q$5:$Q$204,AT226))+1) | O226: =IF(AT226="","",99) | P226: =IF(AT226="","","") | Q226: =IF(AT226="","","") | R226: =IF(AT226="","","消費税") | S226: =IF(AT226="","",0) | T226: =IF(AT226="","","") | U226: =IF(AT226="","",0) | V226: =IF(AT226="","",0) | W226: =IF(AT226="","","") | X226: =IF(AT226="","",0) | Y226: =IF(AT226="","",0) | Z226: =IF(AT226="","",ROUNDDOWN(SUMIF(入力シート!$Q$5:$Q$204,INDEX(入力シート!$Q$5:$Q$204,AT226),入力シート!$P$5:$P$204)*IF(INDEX(入力シート!$L$5:$L$204,AT226)=13,0.1,IF(INDEX(入力シート!$L$5:$L$204,AT226)=30,0.08,0)),0)) | AA226: =IF(AT226="","","") | AB226: =IF(AT226="","",0) | AC226: =IF(AT226="","",0) | AD226: =IF(AT226="","",0) | AE226: =IF(AT226="","","") | AF226: =IF(AT226="","",0) | AG226: =IF(AT226="","",0) | AH226: =IF(AT226="","","") | AI226: =IF(AT226="","","") | AJ226: =IF(AT226="","","") | AK226: =IF(AT226="","",2) | AL226: =IF(AT226="","","") | AM226: =IF(AT226="","","") | AN226: =IF(AT226="","",INDEX(入力シート!$C$5:$C$204,AT226)) | AO226: =IF(AT226="","","") | AP226: =IF(AT226="","","") | AQ226: =IF(AT226="","","") | AT226: =IFERROR(MATCH(26,入力シート!$T$5:$T$204,0),"")
A227: =IF(AT227="","",1) | B227: =IF(AT227="","",1) | C227: =IF(AT227="","",0) | D227: =IF(AT227="","",TEXT(INDEX(入力シート!$A$5:$A$204,AT227),"YYYYMMDD")) | E227: =IF(AT227="","",TEXT(INDEX(入力シート!$Q$5:$Q$204,AT227),"00000000")) | F227: =IF(AT227="","",14) | G227: =IF(AT227="","",1) | H227: =IF(AT227="","",1) | I227: =IF(AT227="","",3) | J227: =IF(AT227="","",1) | K227: =IF(AT227="","",INDEX(入力シート!$B$5:$B$204,AT227)) | L227: =IF(AT227="","","") | M227: =IF(AT227="","","") | N227: =IF(AT227="","",COUNTIF(入力シート!$Q$5:$Q$204,INDEX(入力シート!$Q$5:$Q$204,AT227))+1) | O227: =IF(AT227="","",99) | P227: =IF(AT227="","","") | Q227: =IF(AT227="","","") | R227: =IF(AT227="","","消費税") | S227: =IF(AT227="","",0) | T227: =IF(AT227="","","") | U227: =IF(AT227="","",0) | V227: =IF(AT227="","",0) | W227: =IF(AT227="","","") | X227: =IF(AT227="","",0) | Y227: =IF(AT227="","",0) | Z227: =IF(AT227="","",ROUNDDOWN(SUMIF(入力シート!$Q$5:$Q$204,INDEX(入力シート!$Q$5:$Q$204,AT227),入力シート!$P$5:$P$204)*IF(INDEX(入力シート!$L$5:$L$204,AT227)=13,0.1,IF(INDEX(入力シート!$L$5:$L$204,AT227)=30,0.08,0)),0)) | AA227: =IF(AT227="","","") | AB227: =IF(AT227="","",0) | AC227: =IF(AT227="","",0) | AD227: =IF(AT227="","",0) | AE227: =IF(AT227="","","") | AF227: =IF(AT227="","",0) | AG227: =IF(AT227="","",0) | AH227: =IF(AT227="","","") | AI227: =IF(AT227="","","") | AJ227: =IF(AT227="","","") | AK227: =IF(AT227="","",2) | AL227: =IF(AT227="","","") | AM227: =IF(AT227="","","") | AN227: =IF(AT227="","",INDEX(入力シート!$C$5:$C$204,AT227)) | AO227: =IF(AT227="","","") | AP227: =IF(AT227="","","") | AQ227: =IF(AT227="","","") | AT227: =IFERROR(MATCH(27,入力シート!$T$5:$T$204,0),"")
A228: =IF(AT228="","",1) | B228: =IF(AT228="","",1) | C228: =IF(AT228="","",0) | D228: =IF(AT228="","",TEXT(INDEX(入力シート!$A$5:$A$204,AT228),"YYYYMMDD")) | E228: =IF(AT228="","",TEXT(INDEX(入力シート!$Q$5:$Q$204,AT228),"00000000")) | F228: =IF(AT228="","",14) | G228: =IF(AT228="","",1) | H228: =IF(AT228="","",1) | I228: =IF(AT228="","",3) | J228: =IF(AT228="","",1) | K228: =IF(AT228="","",INDEX(入力シート!$B$5:$B$204,AT228)) | L228: =IF(AT228="","","") | M228: =IF(AT228="","","") | N228: =IF(AT228="","",COUNTIF(入力シート!$Q$5:$Q$204,INDEX(入力シート!$Q$5:$Q$204,AT228))+1) | O228: =IF(AT228="","",99) | P228: =IF(AT228="","","") | Q228: =IF(AT228="","","") | R228: =IF(AT228="","","消費税") | S228: =IF(AT228="","",0) | T228: =IF(AT228="","","") | U228: =IF(AT228="","",0) | V228: =IF(AT228="","",0) | W228: =IF(AT228="","","") | X228: =IF(AT228="","",0) | Y228: =IF(AT228="","",0) | Z228: =IF(AT228="","",ROUNDDOWN(SUMIF(入力シート!$Q$5:$Q$204,INDEX(入力シート!$Q$5:$Q$204,AT228),入力シート!$P$5:$P$204)*IF(INDEX(入力シート!$L$5:$L$204,AT228)=13,0.1,IF(INDEX(入力シート!$L$5:$L$204,AT228)=30,0.08,0)),0)) | AA228: =IF(AT228="","","") | AB228: =IF(AT228="","",0) | AC228: =IF(AT228="","",0) | AD228: =IF(AT228="","",0) | AE228: =IF(AT228="","","") | AF228: =IF(AT228="","",0) | AG228: =IF(AT228="","",0) | AH228: =IF(AT228="","","") | AI228: =IF(AT228="","","") | AJ228: =IF(AT228="","","") | AK228: =IF(AT228="","",2) | AL228: =IF(AT228="","","") | AM228: =IF(AT228="","","") | AN228: =IF(AT228="","",INDEX(入力シート!$C$5:$C$204,AT228)) | AO228: =IF(AT228="","","") | AP228: =IF(AT228="","","") | AQ228: =IF(AT228="","","") | AT228: =IFERROR(MATCH(28,入力シート!$T$5:$T$204,0),"")
A229: =IF(AT229="","",1) | B229: =IF(AT229="","",1) | C229: =IF(AT229="","",0) | D229: =IF(AT229="","",TEXT(INDEX(入力シート!$A$5:$A$204,AT229),"YYYYMMDD")) | E229: =IF(AT229="","",TEXT(INDEX(入力シート!$Q$5:$Q$204,AT229),"00000000")) | F229: =IF(AT229="","",14) | G229: =IF(AT229="","",1) | H229: =IF(AT229="","",1) | I229: =IF(AT229="","",3) | J229: =IF(AT229="","",1) | K229: =IF(AT229="","",INDEX(入力シート!$B$5:$B$204,AT229)) | L229: =IF(AT229="","","") | M229: =IF(AT229="","","") | N229: =IF(AT229="","",COUNTIF(入力シート!$Q$5:$Q$204,INDEX(入力シート!$Q$5:$Q$204,AT229))+1) | O229: =IF(AT229="","",99) | P229: =IF(AT229="","","") | Q229: =IF(AT229="","","") | R229: =IF(AT229="","","消費税") | S229: =IF(AT229="","",0) | T229: =IF(AT229="","","") | U229: =IF(AT229="","",0) | V229: =IF(AT229="","",0) | W229: =IF(AT229="","","") | X229: =IF(AT229="","",0) | Y229: =IF(AT229="","",0) | Z229: =IF(AT229="","",ROUNDDOWN(SUMIF(入力シート!$Q$5:$Q$204,INDEX(入力シート!$Q$5:$Q$204,AT229),入力シート!$P$5:$P$204)*IF(INDEX(入力シート!$L$5:$L$204,AT229)=13,0.1,IF(INDEX(入力シート!$L$5:$L$204,AT229)=30,0.08,0)),0)) | AA229: =IF(AT229="","","") | AB229: =IF(AT229="","",0) | AC229: =IF(AT229="","",0) | AD229: =IF(AT229="","",0) | AE229: =IF(AT229="","","") | AF229: =IF(AT229="","",0) | AG229: =IF(AT229="","",0) | AH229: =IF(AT229="","","") | AI229: =IF(AT229="","","") | AJ229: =IF(AT229="","","") | AK229: =IF(AT229="","",2) | AL229: =IF(AT229="","","") | AM229: =IF(AT229="","","") | AN229: =IF(AT229="","",INDEX(入力シート!$C$5:$C$204,AT229)) | AO229: =IF(AT229="","","") | AP229: =IF(AT229="","","") | AQ229: =IF(AT229="","","") | AT229: =IFERROR(MATCH(29,入力シート!$T$5:$T$204,0),"")
A230: =IF(AT230="","",1) | B230: =IF(AT230="","",1) | C230: =IF(AT230="","",0) | D230: =IF(AT230="","",TEXT(INDEX(入力シート!$A$5:$A$204,AT230),"YYYYMMDD")) | E230: =IF(AT230="","",TEXT(INDEX(入力シート!$Q$5:$Q$204,AT230),"00000000")) | F230: =IF(AT230="","",14) | G230: =IF(AT230="","",1) | H230: =IF(AT230="","",1) | I230: =IF(AT230="","",3) | J230: =IF(AT230="","",1) | K230: =IF(AT230="","",INDEX(入力シート!$B$5:$B$204,AT230)) | L230: =IF(AT230="","","") | M230: =IF(AT230="","","") | N230: =IF(AT230="","",COUNTIF(入力シート!$Q$5:$Q$204,INDEX(入力シート!$Q$5:$Q$204,AT230))+1) | O230: =IF(AT230="","",99) | P230: =IF(AT230="","","") | Q230: =IF(AT230="","","") | R230: =IF(AT230="","","消費税") | S230: =IF(AT230="","",0) | T230: =IF(AT230="","","") | U230: =IF(AT230="","",0) | V230: =IF(AT230="","",0) | W230: =IF(AT230="","","") | X230: =IF(AT230="","",0) | Y230: =IF(AT230="","",0) | Z230: =IF(AT230="","",ROUNDDOWN(SUMIF(入力シート!$Q$5:$Q$204,INDEX(入力シート!$Q$5:$Q$204,AT230),入力シート!$P$5:$P$204)*IF(INDEX(入力シート!$L$5:$L$204,AT230)=13,0.1,IF(INDEX(入力シート!$L$5:$L$204,AT230)=30,0.08,0)),0)) | AA230: =IF(AT230="","","") | AB230: =IF(AT230="","",0) | AC230: =IF(AT230="","",0) | AD230: =IF(AT230="","",0) | AE230: =IF(AT230="","","") | AF230: =IF(AT230="","",0) | AG230: =IF(AT230="","",0) | AH230: =IF(AT230="","","") | AI230: =IF(AT230="","","") | AJ230: =IF(AT230="","","") | AK230: =IF(AT230="","",2) | AL230: =IF(AT230="","","") | AM230: =IF(AT230="","","") | AN230: =IF(AT230="","",INDEX(入力シート!$C$5:$C$204,AT230)) | AO230: =IF(AT230="","","") | AP230: =IF(AT230="","","") | AQ230: =IF(AT230="","","") | AT230: =IFERROR(MATCH(30,入力シート!$T$5:$T$204,0),"")
A231: =IF(AT231="","",1) | B231: =IF(AT231="","",1) | C231: =IF(AT231="","",0) | D231: =IF(AT231="","",TEXT(INDEX(入力シート!$A$5:$A$204,AT231),"YYYYMMDD")) | E231: =IF(AT231="","",TEXT(INDEX(入力シート!$Q$5:$Q$204,AT231),"00000000")) | F231: =IF(AT231="","",14) | G231: =IF(AT231="","",1) | H231: =IF(AT231="","",1) | I231: =IF(AT231="","",3) | J231: =IF(AT231="","",1) | K231: =IF(AT231="","",INDEX(入力シート!$B$5:$B$204,AT231)) | L231: =IF(AT231="","","") | M231: =IF(AT231="","","") | N231: =IF(AT231="","",COUNTIF(入力シート!$Q$5:$Q$204,INDEX(入力シート!$Q$5:$Q$204,AT231))+1) | O231: =IF(AT231="","",99) | P231: =IF(AT231="","","") | Q231: =IF(AT231="","","") | R231: =IF(AT231="","","消費税") | S231: =IF(AT231="","",0) | T231: =IF(AT231="","","") | U231: =IF(AT231="","",0) | V231: =IF(AT231="","",0) | W231: =IF(AT231="","","") | X231: =IF(AT231="","",0) | Y231: =IF(AT231="","",0) | Z231: =IF(AT231="","",ROUNDDOWN(SUMIF(入力シート!$Q$5:$Q$204,INDEX(入力シート!$Q$5:$Q$204,AT231),入力シート!$P$5:$P$204)*IF(INDEX(入力シート!$L$5:$L$204,AT231)=13,0.1,IF(INDEX(入力シート!$L$5:$L$204,AT231)=30,0.08,0)),0)) | AA231: =IF(AT231="","","") | AB231: =IF(AT231="","",0) | AC231: =IF(AT231="","",0) | AD231: =IF(AT231="","",0) | AE231: =IF(AT231="","","") | AF231: =IF(AT231="","",0) | AG231: =IF(AT231="","",0) | AH231: =IF(AT231="","","") | AI231: =IF(AT231="","","") | AJ231: =IF(AT231="","","") | AK231: =IF(AT231="","",2) | AL231: =IF(AT231="","","") | AM231: =IF(AT231="","","") | AN231: =IF(AT231="","",INDEX(入力シート!$C$5:$C$204,AT231)) | AO231: =IF(AT231="","","") | AP231: =IF(AT231="","","") | AQ231: =IF(AT231="","","") | AT231: =IFERROR(MATCH(31,入力シート!$T$5:$T$204,0),"")
A232: =IF(AT232="","",1) | B232: =IF(AT232="","",1) | C232: =IF(AT232="","",0) | D232: =IF(AT232="","",TEXT(INDEX(入力シート!$A$5:$A$204,AT232),"YYYYMMDD")) | E232: =IF(AT232="","",TEXT(INDEX(入力シート!$Q$5:$Q$204,AT232),"00000000")) | F232: =IF(AT232="","",14) | G232: =IF(AT232="","",1) | H232: =IF(AT232="","",1) | I232: =IF(AT232="","",3) | J232: =IF(AT232="","",1) | K232: =IF(AT232="","",INDEX(入力シート!$B$5:$B$204,AT232)) | L232: =IF(AT232="","","") | M232: =IF(AT232="","","") | N232: =IF(AT232="","",COUNTIF(入力シート!$Q$5:$Q$204,INDEX(入力シート!$Q$5:$Q$204,AT232))+1) | O232: =IF(AT232="","",99) | P232: =IF(AT232="","","") | Q232: =IF(AT232="","","") | R232: =IF(AT232="","","消費税") | S232: =IF(AT232="","",0) | T232: =IF(AT232="","","") | U232: =IF(AT232="","",0) | V232: =IF(AT232="","",0) | W232: =IF(AT232="","","") | X232: =IF(AT232="","",0) | Y232: =IF(AT232="","",0) | Z232: =IF(AT232="","",ROUNDDOWN(SUMIF(入力シート!$Q$5:$Q$204,INDEX(入力シート!$Q$5:$Q$204,AT232),入力シート!$P$5:$P$204)*IF(INDEX(入力シート!$L$5:$L$204,AT232)=13,0.1,IF(INDEX(入力シート!$L$5:$L$204,AT232)=30,0.08,0)),0)) | AA232: =IF(AT232="","","") | AB232: =IF(AT232="","",0) | AC232: =IF(AT232="","",0) | AD232: =IF(AT232="","",0) | AE232: =IF(AT232="","","") | AF232: =IF(AT232="","",0) | AG232: =IF(AT232="","",0) | AH232: =IF(AT232="","","") | AI232: =IF(AT232="","","") | AJ232: =IF(AT232="","","") | AK232: =IF(AT232="","",2) | AL232: =IF(AT232="","","") | AM232: =IF(AT232="","","") | AN232: =IF(AT232="","",INDEX(入力シート!$C$5:$C$204,AT232)) | AO232: =IF(AT232="","","") | AP232: =IF(AT232="","","") | AQ232: =IF(AT232="","","") | AT232: =IFERROR(MATCH(32,入力シート!$T$5:$T$204,0),"")
A233: =IF(AT233="","",1) | B233: =IF(AT233="","",1) | C233: =IF(AT233="","",0) | D233: =IF(AT233="","",TEXT(INDEX(入力シート!$A$5:$A$204,AT233),"YYYYMMDD")) | E233: =IF(AT233="","",TEXT(INDEX(入力シート!$Q$5:$Q$204,AT233),"00000000")) | F233: =IF(AT233="","",14) | G233: =IF(AT233="","",1) | H233: =IF(AT233="","",1) | I233: =IF(AT233="","",3) | J233: =IF(AT233="","",1) | K233: =IF(AT233="","",INDEX(入力シート!$B$5:$B$204,AT233)) | L233: =IF(AT233="","","") | M233: =IF(AT233="","","") | N233: =IF(AT233="","",COUNTIF(入力シート!$Q$5:$Q$204,INDEX(入力シート!$Q$5:$Q$204,AT233))+1) | O233: =IF(AT233="","",99) | P233: =IF(AT233="","","") | Q233: =IF(AT233="","","") | R233: =IF(AT233="","","消費税") | S233: =IF(AT233="","",0) | T233: =IF(AT233="","","") | U233: =IF(AT233="","",0) | V233: =IF(AT233="","",0) | W233: =IF(AT233="","","") | X233: =IF(AT233="","",0) | Y233: =IF(AT233="","",0) | Z233: =IF(AT233="","",ROUNDDOWN(SUMIF(入力シート!$Q$5:$Q$204,INDEX(入力シート!$Q$5:$Q$204,AT233),入力シート!$P$5:$P$204)*IF(INDEX(入力シート!$L$5:$L$204,AT233)=13,0.1,IF(INDEX(入力シート!$L$5:$L$204,AT233)=30,0.08,0)),0)) | AA233: =IF(AT233="","","") | AB233: =IF(AT233="","",0) | AC233: =IF(AT233="","",0) | AD233: =IF(AT233="","",0) | AE233: =IF(AT233="","","") | AF233: =IF(AT233="","",0) | AG233: =IF(AT233="","",0) | AH233: =IF(AT233="","","") | AI233: =IF(AT233="","","") | AJ233: =IF(AT233="","","") | AK233: =IF(AT233="","",2) | AL233: =IF(AT233="","","") | AM233: =IF(AT233="","","") | AN233: =IF(AT233="","",INDEX(入力シート!$C$5:$C$204,AT233)) | AO233: =IF(AT233="","","") | AP233: =IF(AT233="","","") | AQ233: =IF(AT233="","","") | AT233: =IFERROR(MATCH(33,入力シート!$T$5:$T$204,0),"")
A234: =IF(AT234="","",1) | B234: =IF(AT234="","",1) | C234: =IF(AT234="","",0) | D234: =IF(AT234="","",TEXT(INDEX(入力シート!$A$5:$A$204,AT234),"YYYYMMDD")) | E234: =IF(AT234="","",TEXT(INDEX(入力シート!$Q$5:$Q$204,AT234),"00000000")) | F234: =IF(AT234="","",14) | G234: =IF(AT234="","",1) | H234: =IF(AT234="","",1) | I234: =IF(AT234="","",3) | J234: =IF(AT234="","",1) | K234: =IF(AT234="","",INDEX(入力シート!$B$5:$B$204,AT234)) | L234: =IF(AT234="","","") | M234: =IF(AT234="","","") | N234: =IF(AT234="","",COUNTIF(入力シート!$Q$5:$Q$204,INDEX(入力シート!$Q$5:$Q$204,AT234))+1) | O234: =IF(AT234="","",99) | P234: =IF(AT234="","","") | Q234: =IF(AT234="","","") | R234: =IF(AT234="","","消費税") | S234: =IF(AT234="","",0) | T234: =IF(AT234="","","") | U234: =IF(AT234="","",0) | V234: =IF(AT234="","",0) | W234: =IF(AT234="","","") | X234: =IF(AT234="","",0) | Y234: =IF(AT234="","",0) | Z234: =IF(AT234="","",ROUNDDOWN(SUMIF(入力シート!$Q$5:$Q$204,INDEX(入力シート!$Q$5:$Q$204,AT234),入力シート!$P$5:$P$204)*IF(INDEX(入力シート!$L$5:$L$204,AT234)=13,0.1,IF(INDEX(入力シート!$L$5:$L$204,AT234)=30,0.08,0)),0)) | AA234: =IF(AT234="","","") | AB234: =IF(AT234="","",0) | AC234: =IF(AT234="","",0) | AD234: =IF(AT234="","",0) | AE234: =IF(AT234="","","") | AF234: =IF(AT234="","",0) | AG234: =IF(AT234="","",0) | AH234: =IF(AT234="","","") | AI234: =IF(AT234="","","") | AJ234: =IF(AT234="","","") | AK234: =IF(AT234="","",2) | AL234: =IF(AT234="","","") | AM234: =IF(AT234="","","") | AN234: =IF(AT234="","",INDEX(入力シート!$C$5:$C$204,AT234)) | AO234: =IF(AT234="","","") | AP234: =IF(AT234="","","") | AQ234: =IF(AT234="","","") | AT234: =IFERROR(MATCH(34,入力シート!$T$5:$T$204,0),"")
A235: =IF(AT235="","",1) | B235: =IF(AT235="","",1) | C235: =IF(AT235="","",0) | D235: =IF(AT235="","",TEXT(INDEX(入力シート!$A$5:$A$204,AT235),"YYYYMMDD")) | E235: =IF(AT235="","",TEXT(INDEX(入力シート!$Q$5:$Q$204,AT235),"00000000")) | F235: =IF(AT235="","",14) | G235: =IF(AT235="","",1) | H235: =IF(AT235="","",1) | I235: =IF(AT235="","",3) | J235: =IF(AT235="","",1) | K235: =IF(AT235="","",INDEX(入力シート!$B$5:$B$204,AT235)) | L235: =IF(AT235="","","") | M235: =IF(AT235="","","") | N235: =IF(AT235="","",COUNTIF(入力シート!$Q$5:$Q$204,INDEX(入力シート!$Q$5:$Q$204,AT235))+1) | O235: =IF(AT235="","",99) | P235: =IF(AT235="","","") | Q235: =IF(AT235="","","") | R235: =IF(AT235="","","消費税") | S235: =IF(AT235="","",0) | T235: =IF(AT235="","","") | U235: =IF(AT235="","",0) | V235: =IF(AT235="","",0) | W235: =IF(AT235="","","") | X235: =IF(AT235="","",0) | Y235: =IF(AT235="","",0) | Z235: =IF(AT235="","",ROUNDDOWN(SUMIF(入力シート!$Q$5:$Q$204,INDEX(入力シート!$Q$5:$Q$204,AT235),入力シート!$P$5:$P$204)*IF(INDEX(入力シート!$L$5:$L$204,AT235)=13,0.1,IF(INDEX(入力シート!$L$5:$L$204,AT235)=30,0.08,0)),0)) | AA235: =IF(AT235="","","") | AB235: =IF(AT235="","",0) | AC235: =IF(AT235="","",0) | AD235: =IF(AT235="","",0) | AE235: =IF(AT235="","","") | AF235: =IF(AT235="","",0) | AG235: =IF(AT235="","",0) | AH235: =IF(AT235="","","") | AI235: =IF(AT235="","","") | AJ235: =IF(AT235="","","") | AK235: =IF(AT235="","",2) | AL235: =IF(AT235="","","") | AM235: =IF(AT235="","","") | AN235: =IF(AT235="","",INDEX(入力シート!$C$5:$C$204,AT235)) | AO235: =IF(AT235="","","") | AP235: =IF(AT235="","","") | AQ235: =IF(AT235="","","") | AT235: =IFERROR(MATCH(35,入力シート!$T$5:$T$204,0),"")
A236: =IF(AT236="","",1) | B236: =IF(AT236="","",1) | C236: =IF(AT236="","",0) | D236: =IF(AT236="","",TEXT(INDEX(入力シート!$A$5:$A$204,AT236),"YYYYMMDD")) | E236: =IF(AT236="","",TEXT(INDEX(入力シート!$Q$5:$Q$204,AT236),"00000000")) | F236: =IF(AT236="","",14) | G236: =IF(AT236="","",1) | H236: =IF(AT236="","",1) | I236: =IF(AT236="","",3) | J236: =IF(AT236="","",1) | K236: =IF(AT236="","",INDEX(入力シート!$B$5:$B$204,AT236)) | L236: =IF(AT236="","","") | M236: =IF(AT236="","","") | N236: =IF(AT236="","",COUNTIF(入力シート!$Q$5:$Q$204,INDEX(入力シート!$Q$5:$Q$204,AT236))+1) | O236: =IF(AT236="","",99) | P236: =IF(AT236="","","") | Q236: =IF(AT236="","","") | R236: =IF(AT236="","","消費税") | S236: =IF(AT236="","",0) | T236: =IF(AT236="","","") | U236: =IF(AT236="","",0) | V236: =IF(AT236="","",0) | W236: =IF(AT236="","","") | X236: =IF(AT236="","",0) | Y236: =IF(AT236="","",0) | Z236: =IF(AT236="","",ROUNDDOWN(SUMIF(入力シート!$Q$5:$Q$204,INDEX(入力シート!$Q$5:$Q$204,AT236),入力シート!$P$5:$P$204)*IF(INDEX(入力シート!$L$5:$L$204,AT236)=13,0.1,IF(INDEX(入力シート!$L$5:$L$204,AT236)=30,0.08,0)),0)) | AA236: =IF(AT236="","","") | AB236: =IF(AT236="","",0) | AC236: =IF(AT236="","",0) | AD236: =IF(AT236="","",0) | AE236: =IF(AT236="","","") | AF236: =IF(AT236="","",0) | AG236: =IF(AT236="","",0) | AH236: =IF(AT236="","","") | AI236: =IF(AT236="","","") | AJ236: =IF(AT236="","","") | AK236: =IF(AT236="","",2) | AL236: =IF(AT236="","","") | AM236: =IF(AT236="","","") | AN236: =IF(AT236="","",INDEX(入力シート!$C$5:$C$204,AT236)) | AO236: =IF(AT236="","","") | AP236: =IF(AT236="","","") | AQ236: =IF(AT236="","","") | AT236: =IFERROR(MATCH(36,入力シート!$T$5:$T$204,0),"")
A237: =IF(AT237="","",1) | B237: =IF(AT237="","",1) | C237: =IF(AT237="","",0) | D237: =IF(AT237="","",TEXT(INDEX(入力シート!$A$5:$A$204,AT237),"YYYYMMDD")) | E237: =IF(AT237="","",TEXT(INDEX(入力シート!$Q$5:$Q$204,AT237),"00000000")) | F237: =IF(AT237="","",14) | G237: =IF(AT237="","",1) | H237: =IF(AT237="","",1) | I237: =IF(AT237="","",3) | J237: =IF(AT237="","",1) | K237: =IF(AT237="","",INDEX(入力シート!$B$5:$B$204,AT237)) | L237: =IF(AT237="","","") | M237: =IF(AT237="","","") | N237: =IF(AT237="","",COUNTIF(入力シート!$Q$5:$Q$204,INDEX(入力シート!$Q$5:$Q$204,AT237))+1) | O237: =IF(AT237="","",99) | P237: =IF(AT237="","","") | Q237: =IF(AT237="","","") | R237: =IF(AT237="","","消費税") | S237: =IF(AT237="","",0) | T237: =IF(AT237="","","") | U237: =IF(AT237="","",0) | V237: =IF(AT237="","",0) | W237: =IF(AT237="","","") | X237: =IF(AT237="","",0) | Y237: =IF(AT237="","",0) | Z237: =IF(AT237="","",ROUNDDOWN(SUMIF(入力シート!$Q$5:$Q$204,INDEX(入力シート!$Q$5:$Q$204,AT237),入力シート!$P$5:$P$204)*IF(INDEX(入力シート!$L$5:$L$204,AT237)=13,0.1,IF(INDEX(入力シート!$L$5:$L$204,AT237)=30,0.08,0)),0)) | AA237: =IF(AT237="","","") | AB237: =IF(AT237="","",0) | AC237: =IF(AT237="","",0) | AD237: =IF(AT237="","",0) | AE237: =IF(AT237="","","") | AF237: =IF(AT237="","",0) | AG237: =IF(AT237="","",0) | AH237: =IF(AT237="","","") | AI237: =IF(AT237="","","") | AJ237: =IF(AT237="","","") | AK237: =IF(AT237="","",2) | AL237: =IF(AT237="","","") | AM237: =IF(AT237="","","") | AN237: =IF(AT237="","",INDEX(入力シート!$C$5:$C$204,AT237)) | AO237: =IF(AT237="","","") | AP237: =IF(AT237="","","") | AQ237: =IF(AT237="","","") | AT237: =IFERROR(MATCH(37,入力シート!$T$5:$T$204,0),"")
A238: =IF(AT238="","",1) | B238: =IF(AT238="","",1) | C238: =IF(AT238="","",0) | D238: =IF(AT238="","",TEXT(INDEX(入力シート!$A$5:$A$204,AT238),"YYYYMMDD")) | E238: =IF(AT238="","",TEXT(INDEX(入力シート!$Q$5:$Q$204,AT238),"00000000")) | F238: =IF(AT238="","",14) | G238: =IF(AT238="","",1) | H238: =IF(AT238="","",1) | I238: =IF(AT238="","",3) | J238: =IF(AT238="","",1) | K238: =IF(AT238="","",INDEX(入力シート!$B$5:$B$204,AT238)) | L238: =IF(AT238="","","") | M238: =IF(AT238="","","") | N238: =IF(AT238="","",COUNTIF(入力シート!$Q$5:$Q$204,INDEX(入力シート!$Q$5:$Q$204,AT238))+1) | O238: =IF(AT238="","",99) | P238: =IF(AT238="","","") | Q238: =IF(AT238="","","") | R238: =IF(AT238="","","消費税") | S238: =IF(AT238="","",0) | T238: =IF(AT238="","","") | U238: =IF(AT238="","",0) | V238: =IF(AT238="","",0) | W238: =IF(AT238="","","") | X238: =IF(AT238="","",0) | Y238: =IF(AT238="","",0) | Z238: =IF(AT238="","",ROUNDDOWN(SUMIF(入力シート!$Q$5:$Q$204,INDEX(入力シート!$Q$5:$Q$204,AT238),入力シート!$P$5:$P$204)*IF(INDEX(入力シート!$L$5:$L$204,AT238)=13,0.1,IF(INDEX(入力シート!$L$5:$L$204,AT238)=30,0.08,0)),0)) | AA238: =IF(AT238="","","") | AB238: =IF(AT238="","",0) | AC238: =IF(AT238="","",0) | AD238: =IF(AT238="","",0) | AE238: =IF(AT238="","","") | AF238: =IF(AT238="","",0) | AG238: =IF(AT238="","",0) | AH238: =IF(AT238="","","") | AI238: =IF(AT238="","","") | AJ238: =IF(AT238="","","") | AK238: =IF(AT238="","",2) | AL238: =IF(AT238="","","") | AM238: =IF(AT238="","","") | AN238: =IF(AT238="","",INDEX(入力シート!$C$5:$C$204,AT238)) | AO238: =IF(AT238="","","") | AP238: =IF(AT238="","","") | AQ238: =IF(AT238="","","") | AT238: =IFERROR(MATCH(38,入力シート!$T$5:$T$204,0),"")
A239: =IF(AT239="","",1) | B239: =IF(AT239="","",1) | C239: =IF(AT239="","",0) | D239: =IF(AT239="","",TEXT(INDEX(入力シート!$A$5:$A$204,AT239),"YYYYMMDD")) | E239: =IF(AT239="","",TEXT(INDEX(入力シート!$Q$5:$Q$204,AT239),"00000000")) | F239: =IF(AT239="","",14) | G239: =IF(AT239="","",1) | H239: =IF(AT239="","",1) | I239: =IF(AT239="","",3) | J239: =IF(AT239="","",1) | K239: =IF(AT239="","",INDEX(入力シート!$B$5:$B$204,AT239)) | L239: =IF(AT239="","","") | M239: =IF(AT239="","","") | N239: =IF(AT239="","",COUNTIF(入力シート!$Q$5:$Q$204,INDEX(入力シート!$Q$5:$Q$204,AT239))+1) | O239: =IF(AT239="","",99) | P239: =IF(AT239="","","") | Q239: =IF(AT239="","","") | R239: =IF(AT239="","","消費税") | S239: =IF(AT239="","",0) | T239: =IF(AT239="","","") | U239: =IF(AT239="","",0) | V239: =IF(AT239="","",0) | W239: =IF(AT239="","","") | X239: =IF(AT239="","",0) | Y239: =IF(AT239="","",0) | Z239: =IF(AT239="","",ROUNDDOWN(SUMIF(入力シート!$Q$5:$Q$204,INDEX(入力シート!$Q$5:$Q$204,AT239),入力シート!$P$5:$P$204)*IF(INDEX(入力シート!$L$5:$L$204,AT239)=13,0.1,IF(INDEX(入力シート!$L$5:$L$204,AT239)=30,0.08,0)),0)) | AA239: =IF(AT239="","","") | AB239: =IF(AT239="","",0) | AC239: =IF(AT239="","",0) | AD239: =IF(AT239="","",0) | AE239: =IF(AT239="","","") | AF239: =IF(AT239="","",0) | AG239: =IF(AT239="","",0) | AH239: =IF(AT239="","","") | AI239: =IF(AT239="","","") | AJ239: =IF(AT239="","","") | AK239: =IF(AT239="","",2) | AL239: =IF(AT239="","","") | AM239: =IF(AT239="","","") | AN239: =IF(AT239="","",INDEX(入力シート!$C$5:$C$204,AT239)) | AO239: =IF(AT239="","","") | AP239: =IF(AT239="","","") | AQ239: =IF(AT239="","","") | AT239: =IFERROR(MATCH(39,入力シート!$T$5:$T$204,0),"")
A240: =IF(AT240="","",1) | B240: =IF(AT240="","",1) | C240: =IF(AT240="","",0) | D240: =IF(AT240="","",TEXT(INDEX(入力シート!$A$5:$A$204,AT240),"YYYYMMDD")) | E240: =IF(AT240="","",TEXT(INDEX(入力シート!$Q$5:$Q$204,AT240),"00000000")) | F240: =IF(AT240="","",14) | G240: =IF(AT240="","",1) | H240: =IF(AT240="","",1) | I240: =IF(AT240="","",3) | J240: =IF(AT240="","",1) | K240: =IF(AT240="","",INDEX(入力シート!$B$5:$B$204,AT240)) | L240: =IF(AT240="","","") | M240: =IF(AT240="","","") | N240: =IF(AT240="","",COUNTIF(入力シート!$Q$5:$Q$204,INDEX(入力シート!$Q$5:$Q$204,AT240))+1) | O240: =IF(AT240="","",99) | P240: =IF(AT240="","","") | Q240: =IF(AT240="","","") | R240: =IF(AT240="","","消費税") | S240: =IF(AT240="","",0) | T240: =IF(AT240="","","") | U240: =IF(AT240="","",0) | V240: =IF(AT240="","",0) | W240: =IF(AT240="","","") | X240: =IF(AT240="","",0) | Y240: =IF(AT240="","",0) | Z240: =IF(AT240="","",ROUNDDOWN(SUMIF(入力シート!$Q$5:$Q$204,INDEX(入力シート!$Q$5:$Q$204,AT240),入力シート!$P$5:$P$204)*IF(INDEX(入力シート!$L$5:$L$204,AT240)=13,0.1,IF(INDEX(入力シート!$L$5:$L$204,AT240)=30,0.08,0)),0)) | AA240: =IF(AT240="","","") | AB240: =IF(AT240="","",0) | AC240: =IF(AT240="","",0) | AD240: =IF(AT240="","",0) | AE240: =IF(AT240="","","") | AF240: =IF(AT240="","",0) | AG240: =IF(AT240="","",0) | AH240: =IF(AT240="","","") | AI240: =IF(AT240="","","") | AJ240: =IF(AT240="","","") | AK240: =IF(AT240="","",2) | AL240: =IF(AT240="","","") | AM240: =IF(AT240="","","") | AN240: =IF(AT240="","",INDEX(入力シート!$C$5:$C$204,AT240)) | AO240: =IF(AT240="","","") | AP240: =IF(AT240="","","") | AQ240: =IF(AT240="","","") | AT240: =IFERROR(MATCH(40,入力シート!$T$5:$T$204,0),"")
A241: =IF(AT241="","",1) | B241: =IF(AT241="","",1) | C241: =IF(AT241="","",0) | D241: =IF(AT241="","",TEXT(INDEX(入力シート!$A$5:$A$204,AT241),"YYYYMMDD")) | E241: =IF(AT241="","",TEXT(INDEX(入力シート!$Q$5:$Q$204,AT241),"00000000")) | F241: =IF(AT241="","",14) | G241: =IF(AT241="","",1) | H241: =IF(AT241="","",1) | I241: =IF(AT241="","",3) | J241: =IF(AT241="","",1) | K241: =IF(AT241="","",INDEX(入力シート!$B$5:$B$204,AT241)) | L241: =IF(AT241="","","") | M241: =IF(AT241="","","") | N241: =IF(AT241="","",COUNTIF(入力シート!$Q$5:$Q$204,INDEX(入力シート!$Q$5:$Q$204,AT241))+1) | O241: =IF(AT241="","",99) | P241: =IF(AT241="","","") | Q241: =IF(AT241="","","") | R241: =IF(AT241="","","消費税") | S241: =IF(AT241="","",0) | T241: =IF(AT241="","","") | U241: =IF(AT241="","",0) | V241: =IF(AT241="","",0) | W241: =IF(AT241="","","") | X241: =IF(AT241="","",0) | Y241: =IF(AT241="","",0) | Z241: =IF(AT241="","",ROUNDDOWN(SUMIF(入力シート!$Q$5:$Q$204,INDEX(入力シート!$Q$5:$Q$204,AT241),入力シート!$P$5:$P$204)*IF(INDEX(入力シート!$L$5:$L$204,AT241)=13,0.1,IF(INDEX(入力シート!$L$5:$L$204,AT241)=30,0.08,0)),0)) | AA241: =IF(AT241="","","") | AB241: =IF(AT241="","",0) | AC241: =IF(AT241="","",0) | AD241: =IF(AT241="","",0) | AE241: =IF(AT241="","","") | AF241: =IF(AT241="","",0) | AG241: =IF(AT241="","",0) | AH241: =IF(AT241="","","") | AI241: =IF(AT241="","","") | AJ241: =IF(AT241="","","") | AK241: =IF(AT241="","",2) | AL241: =IF(AT241="","","") | AM241: =IF(AT241="","","") | AN241: =IF(AT241="","",INDEX(入力シート!$C$5:$C$204,AT241)) | AO241: =IF(AT241="","","") | AP241: =IF(AT241="","","") | AQ241: =IF(AT241="","","") | AT241: =IFERROR(MATCH(41,入力シート!$T$5:$T$204,0),"")
A242: =IF(AT242="","",1) | B242: =IF(AT242="","",1) | C242: =IF(AT242="","",0) | D242: =IF(AT242="","",TEXT(INDEX(入力シート!$A$5:$A$204,AT242),"YYYYMMDD")) | E242: =IF(AT242="","",TEXT(INDEX(入力シート!$Q$5:$Q$204,AT242),"00000000")) | F242: =IF(AT242="","",14) | G242: =IF(AT242="","",1) | H242: =IF(AT242="","",1) | I242: =IF(AT242="","",3) | J242: =IF(AT242="","",1) | K242: =IF(AT242="","",INDEX(入力シート!$B$5:$B$204,AT242)) | L242: =IF(AT242="","","") | M242: =IF(AT242="","","") | N242: =IF(AT242="","",COUNTIF(入力シート!$Q$5:$Q$204,INDEX(入力シート!$Q$5:$Q$204,AT242))+1) | O242: =IF(AT242="","",99) | P242: =IF(AT242="","","") | Q242: =IF(AT242="","","") | R242: =IF(AT242="","","消費税") | S242: =IF(AT242="","",0) | T242: =IF(AT242="","","") | U242: =IF(AT242="","",0) | V242: =IF(AT242="","",0) | W242: =IF(AT242="","","") | X242: =IF(AT242="","",0) | Y242: =IF(AT242="","",0) | Z242: =IF(AT242="","",ROUNDDOWN(SUMIF(入力シート!$Q$5:$Q$204,INDEX(入力シート!$Q$5:$Q$204,AT242),入力シート!$P$5:$P$204)*IF(INDEX(入力シート!$L$5:$L$204,AT242)=13,0.1,IF(INDEX(入力シート!$L$5:$L$204,AT242)=30,0.08,0)),0)) | AA242: =IF(AT242="","","") | AB242: =IF(AT242="","",0) | AC242: =IF(AT242="","",0) | AD242: =IF(AT242="","",0) | AE242: =IF(AT242="","","") | AF242: =IF(AT242="","",0) | AG242: =IF(AT242="","",0) | AH242: =IF(AT242="","","") | AI242: =IF(AT242="","","") | AJ242: =IF(AT242="","","") | AK242: =IF(AT242="","",2) | AL242: =IF(AT242="","","") | AM242: =IF(AT242="","","") | AN242: =IF(AT242="","",INDEX(入力シート!$C$5:$C$204,AT242)) | AO242: =IF(AT242="","","") | AP242: =IF(AT242="","","") | AQ242: =IF(AT242="","","") | AT242: =IFERROR(MATCH(42,入力シート!$T$5:$T$204,0),"")
A243: =IF(AT243="","",1) | B243: =IF(AT243="","",1) | C243: =IF(AT243="","",0) | D243: =IF(AT243="","",TEXT(INDEX(入力シート!$A$5:$A$204,AT243),"YYYYMMDD")) | E243: =IF(AT243="","",TEXT(INDEX(入力シート!$Q$5:$Q$204,AT243),"00000000")) | F243: =IF(AT243="","",14) | G243: =IF(AT243="","",1) | H243: =IF(AT243="","",1) | I243: =IF(AT243="","",3) | J243: =IF(AT243="","",1) | K243: =IF(AT243="","",INDEX(入力シート!$B$5:$B$204,AT243)) | L243: =IF(AT243="","","") | M243: =IF(AT243="","","") | N243: =IF(AT243="","",COUNTIF(入力シート!$Q$5:$Q$204,INDEX(入力シート!$Q$5:$Q$204,AT243))+1) | O243: =IF(AT243="","",99) | P243: =IF(AT243="","","") | Q243: =IF(AT243="","","") | R243: =IF(AT243="","","消費税") | S243: =IF(AT243="","",0) | T243: =IF(AT243="","","") | U243: =IF(AT243="","",0) | V243: =IF(AT243="","",0) | W243: =IF(AT243="","","") | X243: =IF(AT243="","",0) | Y243: =IF(AT243="","",0) | Z243: =IF(AT243="","",ROUNDDOWN(SUMIF(入力シート!$Q$5:$Q$204,INDEX(入力シート!$Q$5:$Q$204,AT243),入力シート!$P$5:$P$204)*IF(INDEX(入力シート!$L$5:$L$204,AT243)=13,0.1,IF(INDEX(入力シート!$L$5:$L$204,AT243)=30,0.08,0)),0)) | AA243: =IF(AT243="","","") | AB243: =IF(AT243="","",0) | AC243: =IF(AT243="","",0) | AD243: =IF(AT243="","",0) | AE243: =IF(AT243="","","") | AF243: =IF(AT243="","",0) | AG243: =IF(AT243="","",0) | AH243: =IF(AT243="","","") | AI243: =IF(AT243="","","") | AJ243: =IF(AT243="","","") | AK243: =IF(AT243="","",2) | AL243: =IF(AT243="","","") | AM243: =IF(AT243="","","") | AN243: =IF(AT243="","",INDEX(入力シート!$C$5:$C$204,AT243)) | AO243: =IF(AT243="","","") | AP243: =IF(AT243="","","") | AQ243: =IF(AT243="","","") | AT243: =IFERROR(MATCH(43,入力シート!$T$5:$T$204,0),"")
A244: =IF(AT244="","",1) | B244: =IF(AT244="","",1) | C244: =IF(AT244="","",0) | D244: =IF(AT244="","",TEXT(INDEX(入力シート!$A$5:$A$204,AT244),"YYYYMMDD")) | E244: =IF(AT244="","",TEXT(INDEX(入力シート!$Q$5:$Q$204,AT244),"00000000")) | F244: =IF(AT244="","",14) | G244: =IF(AT244="","",1) | H244: =IF(AT244="","",1) | I244: =IF(AT244="","",3) | J244: =IF(AT244="","",1) | K244: =IF(AT244="","",INDEX(入力シート!$B$5:$B$204,AT244)) | L244: =IF(AT244="","","") | M244: =IF(AT244="","","") | N244: =IF(AT244="","",COUNTIF(入力シート!$Q$5:$Q$204,INDEX(入力シート!$Q$5:$Q$204,AT244))+1) | O244: =IF(AT244="","",99) | P244: =IF(AT244="","","") | Q244: =IF(AT244="","","") | R244: =IF(AT244="","","消費税") | S244: =IF(AT244="","",0) | T244: =IF(AT244="","","") | U244: =IF(AT244="","",0) | V244: =IF(AT244="","",0) | W244: =IF(AT244="","","") | X244: =IF(AT244="","",0) | Y244: =IF(AT244="","",0) | Z244: =IF(AT244="","",ROUNDDOWN(SUMIF(入力シート!$Q$5:$Q$204,INDEX(入力シート!$Q$5:$Q$204,AT244),入力シート!$P$5:$P$204)*IF(INDEX(入力シート!$L$5:$L$204,AT244)=13,0.1,IF(INDEX(入力シート!$L$5:$L$204,AT244)=30,0.08,0)),0)) | AA244: =IF(AT244="","","") | AB244: =IF(AT244="","",0) | AC244: =IF(AT244="","",0) | AD244: =IF(AT244="","",0) | AE244: =IF(AT244="","","") | AF244: =IF(AT244="","",0) | AG244: =IF(AT244="","",0) | AH244: =IF(AT244="","","") | AI244: =IF(AT244="","","") | AJ244: =IF(AT244="","","") | AK244: =IF(AT244="","",2) | AL244: =IF(AT244="","","") | AM244: =IF(AT244="","","") | AN244: =IF(AT244="","",INDEX(入力シート!$C$5:$C$204,AT244)) | AO244: =IF(AT244="","","") | AP244: =IF(AT244="","","") | AQ244: =IF(AT244="","","") | AT244: =IFERROR(MATCH(44,入力シート!$T$5:$T$204,0),"")
A245: =IF(AT245="","",1) | B245: =IF(AT245="","",1) | C245: =IF(AT245="","",0) | D245: =IF(AT245="","",TEXT(INDEX(入力シート!$A$5:$A$204,AT245),"YYYYMMDD")) | E245: =IF(AT245="","",TEXT(INDEX(入力シート!$Q$5:$Q$204,AT245),"00000000")) | F245: =IF(AT245="","",14) | G245: =IF(AT245="","",1) | H245: =IF(AT245="","",1) | I245: =IF(AT245="","",3) | J245: =IF(AT245="","",1) | K245: =IF(AT245="","",INDEX(入力シート!$B$5:$B$204,AT245)) | L245: =IF(AT245="","","") | M245: =IF(AT245="","","") | N245: =IF(AT245="","",COUNTIF(入力シート!$Q$5:$Q$204,INDEX(入力シート!$Q$5:$Q$204,AT245))+1) | O245: =IF(AT245="","",99) | P245: =IF(AT245="","","") | Q245: =IF(AT245="","","") | R245: =IF(AT245="","","消費税") | S245: =IF(AT245="","",0) | T245: =IF(AT245="","","") | U245: =IF(AT245="","",0) | V245: =IF(AT245="","",0) | W245: =IF(AT245="","","") | X245: =IF(AT245="","",0) | Y245: =IF(AT245="","",0) | Z245: =IF(AT245="","",ROUNDDOWN(SUMIF(入力シート!$Q$5:$Q$204,INDEX(入力シート!$Q$5:$Q$204,AT245),入力シート!$P$5:$P$204)*IF(INDEX(入力シート!$L$5:$L$204,AT245)=13,0.1,IF(INDEX(入力シート!$L$5:$L$204,AT245)=30,0.08,0)),0)) | AA245: =IF(AT245="","","") | AB245: =IF(AT245="","",0) | AC245: =IF(AT245="","",0) | AD245: =IF(AT245="","",0) | AE245: =IF(AT245="","","") | AF245: =IF(AT245="","",0) | AG245: =IF(AT245="","",0) | AH245: =IF(AT245="","","") | AI245: =IF(AT245="","","") | AJ245: =IF(AT245="","","") | AK245: =IF(AT245="","",2) | AL245: =IF(AT245="","","") | AM245: =IF(AT245="","","") | AN245: =IF(AT245="","",INDEX(入力シート!$C$5:$C$204,AT245)) | AO245: =IF(AT245="","","") | AP245: =IF(AT245="","","") | AQ245: =IF(AT245="","","") | AT245: =IFERROR(MATCH(45,入力シート!$T$5:$T$204,0),"")
A246: =IF(AT246="","",1) | B246: =IF(AT246="","",1) | C246: =IF(AT246="","",0) | D246: =IF(AT246="","",TEXT(INDEX(入力シート!$A$5:$A$204,AT246),"YYYYMMDD")) | E246: =IF(AT246="","",TEXT(INDEX(入力シート!$Q$5:$Q$204,AT246),"00000000")) | F246: =IF(AT246="","",14) | G246: =IF(AT246="","",1) | H246: =IF(AT246="","",1) | I246: =IF(AT246="","",3) | J246: =IF(AT246="","",1) | K246: =IF(AT246="","",INDEX(入力シート!$B$5:$B$204,AT246)) | L246: =IF(AT246="","","") | M246: =IF(AT246="","","") | N246: =IF(AT246="","",COUNTIF(入力シート!$Q$5:$Q$204,INDEX(入力シート!$Q$5:$Q$204,AT246))+1) | O246: =IF(AT246="","",99) | P246: =IF(AT246="","","") | Q246: =IF(AT246="","","") | R246: =IF(AT246="","","消費税") | S246: =IF(AT246="","",0) | T246: =IF(AT246="","","") | U246: =IF(AT246="","",0) | V246: =IF(AT246="","",0) | W246: =IF(AT246="","","") | X246: =IF(AT246="","",0) | Y246: =IF(AT246="","",0) | Z246: =IF(AT246="","",ROUNDDOWN(SUMIF(入力シート!$Q$5:$Q$204,INDEX(入力シート!$Q$5:$Q$204,AT246),入力シート!$P$5:$P$204)*IF(INDEX(入力シート!$L$5:$L$204,AT246)=13,0.1,IF(INDEX(入力シート!$L$5:$L$204,AT246)=30,0.08,0)),0)) | AA246: =IF(AT246="","","") | AB246: =IF(AT246="","",0) | AC246: =IF(AT246="","",0) | AD246: =IF(AT246="","",0) | AE246: =IF(AT246="","","") | AF246: =IF(AT246="","",0) | AG246: =IF(AT246="","",0) | AH246: =IF(AT246="","","") | AI246: =IF(AT246="","","") | AJ246: =IF(AT246="","","") | AK246: =IF(AT246="","",2) | AL246: =IF(AT246="","","") | AM246: =IF(AT246="","","") | AN246: =IF(AT246="","",INDEX(入力シート!$C$5:$C$204,AT246)) | AO246: =IF(AT246="","","") | AP246: =IF(AT246="","","") | AQ246: =IF(AT246="","","") | AT246: =IFERROR(MATCH(46,入力シート!$T$5:$T$204,0),"")
A247: =IF(AT247="","",1) | B247: =IF(AT247="","",1) | C247: =IF(AT247="","",0) | D247: =IF(AT247="","",TEXT(INDEX(入力シート!$A$5:$A$204,AT247),"YYYYMMDD")) | E247: =IF(AT247="","",TEXT(INDEX(入力シート!$Q$5:$Q$204,AT247),"00000000")) | F247: =IF(AT247="","",14) | G247: =IF(AT247="","",1) | H247: =IF(AT247="","",1) | I247: =IF(AT247="","",3) | J247: =IF(AT247="","",1) | K247: =IF(AT247="","",INDEX(入力シート!$B$5:$B$204,AT247)) | L247: =IF(AT247="","","") | M247: =IF(AT247="","","") | N247: =IF(AT247="","",COUNTIF(入力シート!$Q$5:$Q$204,INDEX(入力シート!$Q$5:$Q$204,AT247))+1) | O247: =IF(AT247="","",99) | P247: =IF(AT247="","","") | Q247: =IF(AT247="","","") | R247: =IF(AT247="","","消費税") | S247: =IF(AT247="","",0) | T247: =IF(AT247="","","") | U247: =IF(AT247="","",0) | V247: =IF(AT247="","",0) | W247: =IF(AT247="","","") | X247: =IF(AT247="","",0) | Y247: =IF(AT247="","",0) | Z247: =IF(AT247="","",ROUNDDOWN(SUMIF(入力シート!$Q$5:$Q$204,INDEX(入力シート!$Q$5:$Q$204,AT247),入力シート!$P$5:$P$204)*IF(INDEX(入力シート!$L$5:$L$204,AT247)=13,0.1,IF(INDEX(入力シート!$L$5:$L$204,AT247)=30,0.08,0)),0)) | AA247: =IF(AT247="","","") | AB247: =IF(AT247="","",0) | AC247: =IF(AT247="","",0) | AD247: =IF(AT247="","",0) | AE247: =IF(AT247="","","") | AF247: =IF(AT247="","",0) | AG247: =IF(AT247="","",0) | AH247: =IF(AT247="","","") | AI247: =IF(AT247="","","") | AJ247: =IF(AT247="","","") | AK247: =IF(AT247="","",2) | AL247: =IF(AT247="","","") | AM247: =IF(AT247="","","") | AN247: =IF(AT247="","",INDEX(入力シート!$C$5:$C$204,AT247)) | AO247: =IF(AT247="","","") | AP247: =IF(AT247="","","") | AQ247: =IF(AT247="","","") | AT247: =IFERROR(MATCH(47,入力シート!$T$5:$T$204,0),"")
A248: =IF(AT248="","",1) | B248: =IF(AT248="","",1) | C248: =IF(AT248="","",0) | D248: =IF(AT248="","",TEXT(INDEX(入力シート!$A$5:$A$204,AT248),"YYYYMMDD")) | E248: =IF(AT248="","",TEXT(INDEX(入力シート!$Q$5:$Q$204,AT248),"00000000")) | F248: =IF(AT248="","",14) | G248: =IF(AT248="","",1) | H248: =IF(AT248="","",1) | I248: =IF(AT248="","",3) | J248: =IF(AT248="","",1) | K248: =IF(AT248="","",INDEX(入力シート!$B$5:$B$204,AT248)) | L248: =IF(AT248="","","") | M248: =IF(AT248="","","") | N248: =IF(AT248="","",COUNTIF(入力シート!$Q$5:$Q$204,INDEX(入力シート!$Q$5:$Q$204,AT248))+1) | O248: =IF(AT248="","",99) | P248: =IF(AT248="","","") | Q248: =IF(AT248="","","") | R248: =IF(AT248="","","消費税") | S248: =IF(AT248="","",0) | T248: =IF(AT248="","","") | U248: =IF(AT248="","",0) | V248: =IF(AT248="","",0) | W248: =IF(AT248="","","") | X248: =IF(AT248="","",0) | Y248: =IF(AT248="","",0) | Z248: =IF(AT248="","",ROUNDDOWN(SUMIF(入力シート!$Q$5:$Q$204,INDEX(入力シート!$Q$5:$Q$204,AT248),入力シート!$P$5:$P$204)*IF(INDEX(入力シート!$L$5:$L$204,AT248)=13,0.1,IF(INDEX(入力シート!$L$5:$L$204,AT248)=30,0.08,0)),0)) | AA248: =IF(AT248="","","") | AB248: =IF(AT248="","",0) | AC248: =IF(AT248="","",0) | AD248: =IF(AT248="","",0) | AE248: =IF(AT248="","","") | AF248: =IF(AT248="","",0) | AG248: =IF(AT248="","",0) | AH248: =IF(AT248="","","") | AI248: =IF(AT248="","","") | AJ248: =IF(AT248="","","") | AK248: =IF(AT248="","",2) | AL248: =IF(AT248="","","") | AM248: =IF(AT248="","","") | AN248: =IF(AT248="","",INDEX(入力シート!$C$5:$C$204,AT248)) | AO248: =IF(AT248="","","") | AP248: =IF(AT248="","","") | AQ248: =IF(AT248="","","") | AT248: =IFERROR(MATCH(48,入力シート!$T$5:$T$204,0),"")
A249: =IF(AT249="","",1) | B249: =IF(AT249="","",1) | C249: =IF(AT249="","",0) | D249: =IF(AT249="","",TEXT(INDEX(入力シート!$A$5:$A$204,AT249),"YYYYMMDD")) | E249: =IF(AT249="","",TEXT(INDEX(入力シート!$Q$5:$Q$204,AT249),"00000000")) | F249: =IF(AT249="","",14) | G249: =IF(AT249="","",1) | H249: =IF(AT249="","",1) | I249: =IF(AT249="","",3) | J249: =IF(AT249="","",1) | K249: =IF(AT249="","",INDEX(入力シート!$B$5:$B$204,AT249)) | L249: =IF(AT249="","","") | M249: =IF(AT249="","","") | N249: =IF(AT249="","",COUNTIF(入力シート!$Q$5:$Q$204,INDEX(入力シート!$Q$5:$Q$204,AT249))+1) | O249: =IF(AT249="","",99) | P249: =IF(AT249="","","") | Q249: =IF(AT249="","","") | R249: =IF(AT249="","","消費税") | S249: =IF(AT249="","",0) | T249: =IF(AT249="","","") | U249: =IF(AT249="","",0) | V249: =IF(AT249="","",0) | W249: =IF(AT249="","","") | X249: =IF(AT249="","",0) | Y249: =IF(AT249="","",0) | Z249: =IF(AT249="","",ROUNDDOWN(SUMIF(入力シート!$Q$5:$Q$204,INDEX(入力シート!$Q$5:$Q$204,AT249),入力シート!$P$5:$P$204)*IF(INDEX(入力シート!$L$5:$L$204,AT249)=13,0.1,IF(INDEX(入力シート!$L$5:$L$204,AT249)=30,0.08,0)),0)) | AA249: =IF(AT249="","","") | AB249: =IF(AT249="","",0) | AC249: =IF(AT249="","",0) | AD249: =IF(AT249="","",0) | AE249: =IF(AT249="","","") | AF249: =IF(AT249="","",0) | AG249: =IF(AT249="","",0) | AH249: =IF(AT249="","","") | AI249: =IF(AT249="","","") | AJ249: =IF(AT249="","","") | AK249: =IF(AT249="","",2) | AL249: =IF(AT249="","","") | AM249: =IF(AT249="","","") | AN249: =IF(AT249="","",INDEX(入力シート!$C$5:$C$204,AT249)) | AO249: =IF(AT249="","","") | AP249: =IF(AT249="","","") | AQ249: =IF(AT249="","","") | AT249: =IFERROR(MATCH(49,入力シート!$T$5:$T$204,0),"")
A250: =IF(AT250="","",1) | B250: =IF(AT250="","",1) | C250: =IF(AT250="","",0) | D250: =IF(AT250="","",TEXT(INDEX(入力シート!$A$5:$A$204,AT250),"YYYYMMDD")) | E250: =IF(AT250="","",TEXT(INDEX(入力シート!$Q$5:$Q$204,AT250),"00000000")) | F250: =IF(AT250="","",14) | G250: =IF(AT250="","",1) | H250: =IF(AT250="","",1) | I250: =IF(AT250="","",3) | J250: =IF(AT250="","",1) | K250: =IF(AT250="","",INDEX(入力シート!$B$5:$B$204,AT250)) | L250: =IF(AT250="","","") | M250: =IF(AT250="","","") | N250: =IF(AT250="","",COUNTIF(入力シート!$Q$5:$Q$204,INDEX(入力シート!$Q$5:$Q$204,AT250))+1) | O250: =IF(AT250="","",99) | P250: =IF(AT250="","","") | Q250: =IF(AT250="","","") | R250: =IF(AT250="","","消費税") | S250: =IF(AT250="","",0) | T250: =IF(AT250="","","") | U250: =IF(AT250="","",0) | V250: =IF(AT250="","",0) | W250: =IF(AT250="","","") | X250: =IF(AT250="","",0) | Y250: =IF(AT250="","",0) | Z250: =IF(AT250="","",ROUNDDOWN(SUMIF(入力シート!$Q$5:$Q$204,INDEX(入力シート!$Q$5:$Q$204,AT250),入力シート!$P$5:$P$204)*IF(INDEX(入力シート!$L$5:$L$204,AT250)=13,0.1,IF(INDEX(入力シート!$L$5:$L$204,AT250)=30,0.08,0)),0)) | AA250: =IF(AT250="","","") | AB250: =IF(AT250="","",0) | AC250: =IF(AT250="","",0) | AD250: =IF(AT250="","",0) | AE250: =IF(AT250="","","") | AF250: =IF(AT250="","",0) | AG250: =IF(AT250="","",0) | AH250: =IF(AT250="","","") | AI250: =IF(AT250="","","") | AJ250: =IF(AT250="","","") | AK250: =IF(AT250="","",2) | AL250: =IF(AT250="","","") | AM250: =IF(AT250="","","") | AN250: =IF(AT250="","",INDEX(入力シート!$C$5:$C$204,AT250)) | AO250: =IF(AT250="","","") | AP250: =IF(AT250="","","") | AQ250: =IF(AT250="","","") | AT250: =IFERROR(MATCH(50,入力シート!$T$5:$T$204,0),"")
A251: =IF(AT251="","",1) | B251: =IF(AT251="","",1) | C251: =IF(AT251="","",0) | D251: =IF(AT251="","",TEXT(INDEX(入力シート!$A$5:$A$204,AT251),"YYYYMMDD")) | E251: =IF(AT251="","",TEXT(INDEX(入力シート!$Q$5:$Q$204,AT251),"00000000")) | F251: =IF(AT251="","",14) | G251: =IF(AT251="","",1) | H251: =IF(AT251="","",1) | I251: =IF(AT251="","",3) | J251: =IF(AT251="","",1) | K251: =IF(AT251="","",INDEX(入力シート!$B$5:$B$204,AT251)) | L251: =IF(AT251="","","") | M251: =IF(AT251="","","") | N251: =IF(AT251="","",COUNTIF(入力シート!$Q$5:$Q$204,INDEX(入力シート!$Q$5:$Q$204,AT251))+1) | O251: =IF(AT251="","",99) | P251: =IF(AT251="","","") | Q251: =IF(AT251="","","") | R251: =IF(AT251="","","消費税") | S251: =IF(AT251="","",0) | T251: =IF(AT251="","","") | U251: =IF(AT251="","",0) | V251: =IF(AT251="","",0) | W251: =IF(AT251="","","") | X251: =IF(AT251="","",0) | Y251: =IF(AT251="","",0) | Z251: =IF(AT251="","",ROUNDDOWN(SUMIF(入力シート!$Q$5:$Q$204,INDEX(入力シート!$Q$5:$Q$204,AT251),入力シート!$P$5:$P$204)*IF(INDEX(入力シート!$L$5:$L$204,AT251)=13,0.1,IF(INDEX(入力シート!$L$5:$L$204,AT251)=30,0.08,0)),0)) | AA251: =IF(AT251="","","") | AB251: =IF(AT251="","",0) | AC251: =IF(AT251="","",0) | AD251: =IF(AT251="","",0) | AE251: =IF(AT251="","","") | AF251: =IF(AT251="","",0) | AG251: =IF(AT251="","",0) | AH251: =IF(AT251="","","") | AI251: =IF(AT251="","","") | AJ251: =IF(AT251="","","") | AK251: =IF(AT251="","",2) | AL251: =IF(AT251="","","") | AM251: =IF(AT251="","","") | AN251: =IF(AT251="","",INDEX(入力シート!$C$5:$C$204,AT251)) | AO251: =IF(AT251="","","") | AP251: =IF(AT251="","","") | AQ251: =IF(AT251="","","") | AT251: =IFERROR(MATCH(51,入力シート!$T$5:$T$204,0),"")
A252: =IF(AT252="","",1) | B252: =IF(AT252="","",1) | C252: =IF(AT252="","",0) | D252: =IF(AT252="","",TEXT(INDEX(入力シート!$A$5:$A$204,AT252),"YYYYMMDD")) | E252: =IF(AT252="","",TEXT(INDEX(入力シート!$Q$5:$Q$204,AT252),"00000000")) | F252: =IF(AT252="","",14) | G252: =IF(AT252="","",1) | H252: =IF(AT252="","",1) | I252: =IF(AT252="","",3) | J252: =IF(AT252="","",1) | K252: =IF(AT252="","",INDEX(入力シート!$B$5:$B$204,AT252)) | L252: =IF(AT252="","","") | M252: =IF(AT252="","","") | N252: =IF(AT252="","",COUNTIF(入力シート!$Q$5:$Q$204,INDEX(入力シート!$Q$5:$Q$204,AT252))+1) | O252: =IF(AT252="","",99) | P252: =IF(AT252="","","") | Q252: =IF(AT252="","","") | R252: =IF(AT252="","","消費税") | S252: =IF(AT252="","",0) | T252: =IF(AT252="","","") | U252: =IF(AT252="","",0) | V252: =IF(AT252="","",0) | W252: =IF(AT252="","","") | X252: =IF(AT252="","",0) | Y252: =IF(AT252="","",0) | Z252: =IF(AT252="","",ROUNDDOWN(SUMIF(入力シート!$Q$5:$Q$204,INDEX(入力シート!$Q$5:$Q$204,AT252),入力シート!$P$5:$P$204)*IF(INDEX(入力シート!$L$5:$L$204,AT252)=13,0.1,IF(INDEX(入力シート!$L$5:$L$204,AT252)=30,0.08,0)),0)) | AA252: =IF(AT252="","","") | AB252: =IF(AT252="","",0) | AC252: =IF(AT252="","",0) | AD252: =IF(AT252="","",0) | AE252: =IF(AT252="","","") | AF252: =IF(AT252="","",0) | AG252: =IF(AT252="","",0) | AH252: =IF(AT252="","","") | AI252: =IF(AT252="","","") | AJ252: =IF(AT252="","","") | AK252: =IF(AT252="","",2) | AL252: =IF(AT252="","","") | AM252: =IF(AT252="","","") | AN252: =IF(AT252="","",INDEX(入力シート!$C$5:$C$204,AT252)) | AO252: =IF(AT252="","","") | AP252: =IF(AT252="","","") | AQ252: =IF(AT252="","","") | AT252: =IFERROR(MATCH(52,入力シート!$T$5:$T$204,0),"")
A253: =IF(AT253="","",1) | B253: =IF(AT253="","",1) | C253: =IF(AT253="","",0) | D253: =IF(AT253="","",TEXT(INDEX(入力シート!$A$5:$A$204,AT253),"YYYYMMDD")) | E253: =IF(AT253="","",TEXT(INDEX(入力シート!$Q$5:$Q$204,AT253),"00000000")) | F253: =IF(AT253="","",14) | G253: =IF(AT253="","",1) | H253: =IF(AT253="","",1) | I253: =IF(AT253="","",3) | J253: =IF(AT253="","",1) | K253: =IF(AT253="","",INDEX(入力シート!$B$5:$B$204,AT253)) | L253: =IF(AT253="","","") | M253: =IF(AT253="","","") | N253: =IF(AT253="","",COUNTIF(入力シート!$Q$5:$Q$204,INDEX(入力シート!$Q$5:$Q$204,AT253))+1) | O253: =IF(AT253="","",99) | P253: =IF(AT253="","","") | Q253: =IF(AT253="","","") | R253: =IF(AT253="","","消費税") | S253: =IF(AT253="","",0) | T253: =IF(AT253="","","") | U253: =IF(AT253="","",0) | V253: =IF(AT253="","",0) | W253: =IF(AT253="","","") | X253: =IF(AT253="","",0) | Y253: =IF(AT253="","",0) | Z253: =IF(AT253="","",ROUNDDOWN(SUMIF(入力シート!$Q$5:$Q$204,INDEX(入力シート!$Q$5:$Q$204,AT253),入力シート!$P$5:$P$204)*IF(INDEX(入力シート!$L$5:$L$204,AT253)=13,0.1,IF(INDEX(入力シート!$L$5:$L$204,AT253)=30,0.08,0)),0)) | AA253: =IF(AT253="","","") | AB253: =IF(AT253="","",0) | AC253: =IF(AT253="","",0) | AD253: =IF(AT253="","",0) | AE253: =IF(AT253="","","") | AF253: =IF(AT253="","",0) | AG253: =IF(AT253="","",0) | AH253: =IF(AT253="","","") | AI253: =IF(AT253="","","") | AJ253: =IF(AT253="","","") | AK253: =IF(AT253="","",2) | AL253: =IF(AT253="","","") | AM253: =IF(AT253="","","") | AN253: =IF(AT253="","",INDEX(入力シート!$C$5:$C$204,AT253)) | AO253: =IF(AT253="","","") | AP253: =IF(AT253="","","") | AQ253: =IF(AT253="","","") | AT253: =IFERROR(MATCH(53,入力シート!$T$5:$T$204,0),"")
A254: =IF(AT254="","",1) | B254: =IF(AT254="","",1) | C254: =IF(AT254="","",0) | D254: =IF(AT254="","",TEXT(INDEX(入力シート!$A$5:$A$204,AT254),"YYYYMMDD")) | E254: =IF(AT254="","",TEXT(INDEX(入力シート!$Q$5:$Q$204,AT254),"00000000")) | F254: =IF(AT254="","",14) | G254: =IF(AT254="","",1) | H254: =IF(AT254="","",1) | I254: =IF(AT254="","",3) | J254: =IF(AT254="","",1) | K254: =IF(AT254="","",INDEX(入力シート!$B$5:$B$204,AT254)) | L254: =IF(AT254="","","") | M254: =IF(AT254="","","") | N254: =IF(AT254="","",COUNTIF(入力シート!$Q$5:$Q$204,INDEX(入力シート!$Q$5:$Q$204,AT254))+1) | O254: =IF(AT254="","",99) | P254: =IF(AT254="","","") | Q254: =IF(AT254="","","") | R254: =IF(AT254="","","消費税") | S254: =IF(AT254="","",0) | T254: =IF(AT254="","","") | U254: =IF(AT254="","",0) | V254: =IF(AT254="","",0) | W254: =IF(AT254="","","") | X254: =IF(AT254="","",0) | Y254: =IF(AT254="","",0) | Z254: =IF(AT254="","",ROUNDDOWN(SUMIF(入力シート!$Q$5:$Q$204,INDEX(入力シート!$Q$5:$Q$204,AT254),入力シート!$P$5:$P$204)*IF(INDEX(入力シート!$L$5:$L$204,AT254)=13,0.1,IF(INDEX(入力シート!$L$5:$L$204,AT254)=30,0.08,0)),0)) | AA254: =IF(AT254="","","") | AB254: =IF(AT254="","",0) | AC254: =IF(AT254="","",0) | AD254: =IF(AT254="","",0) | AE254: =IF(AT254="","","") | AF254: =IF(AT254="","",0) | AG254: =IF(AT254="","",0) | AH254: =IF(AT254="","","") | AI254: =IF(AT254="","","") | AJ254: =IF(AT254="","","") | AK254: =IF(AT254="","",2) | AL254: =IF(AT254="","","") | AM254: =IF(AT254="","","") | AN254: =IF(AT254="","",INDEX(入力シート!$C$5:$C$204,AT254)) | AO254: =IF(AT254="","","") | AP254: =IF(AT254="","","") | AQ254: =IF(AT254="","","") | AT254: =IFERROR(MATCH(54,入力シート!$T$5:$T$204,0),"")
A255: =IF(AT255="","",1) | B255: =IF(AT255="","",1) | C255: =IF(AT255="","",0) | D255: =IF(AT255="","",TEXT(INDEX(入力シート!$A$5:$A$204,AT255),"YYYYMMDD")) | E255: =IF(AT255="","",TEXT(INDEX(入力シート!$Q$5:$Q$204,AT255),"00000000")) | F255: =IF(AT255="","",14) | G255: =IF(AT255="","",1) | H255: =IF(AT255="","",1) | I255: =IF(AT255="","",3) | J255: =IF(AT255="","",1) | K255: =IF(AT255="","",INDEX(入力シート!$B$5:$B$204,AT255)) | L255: =IF(AT255="","","") | M255: =IF(AT255="","","") | N255: =IF(AT255="","",COUNTIF(入力シート!$Q$5:$Q$204,INDEX(入力シート!$Q$5:$Q$204,AT255))+1) | O255: =IF(AT255="","",99) | P255: =IF(AT255="","","") | Q255: =IF(AT255="","","") | R255: =IF(AT255="","","消費税") | S255: =IF(AT255="","",0) | T255: =IF(AT255="","","") | U255: =IF(AT255="","",0) | V255: =IF(AT255="","",0) | W255: =IF(AT255="","","") | X255: =IF(AT255="","",0) | Y255: =IF(AT255="","",0) | Z255: =IF(AT255="","",ROUNDDOWN(SUMIF(入力シート!$Q$5:$Q$204,INDEX(入力シート!$Q$5:$Q$204,AT255),入力シート!$P$5:$P$204)*IF(INDEX(入力シート!$L$5:$L$204,AT255)=13,0.1,IF(INDEX(入力シート!$L$5:$L$204,AT255)=30,0.08,0)),0)) | AA255: =IF(AT255="","","") | AB255: =IF(AT255="","",0) | AC255: =IF(AT255="","",0) | AD255: =IF(AT255="","",0) | AE255: =IF(AT255="","","") | AF255: =IF(AT255="","",0) | AG255: =IF(AT255="","",0) | AH255: =IF(AT255="","","") | AI255: =IF(AT255="","","") | AJ255: =IF(AT255="","","") | AK255: =IF(AT255="","",2) | AL255: =IF(AT255="","","") | AM255: =IF(AT255="","","") | AN255: =IF(AT255="","",INDEX(入力シート!$C$5:$C$204,AT255)) | AO255: =IF(AT255="","","") | AP255: =IF(AT255="","","") | AQ255: =IF(AT255="","","") | AT255: =IFERROR(MATCH(55,入力シート!$T$5:$T$204,0),"")
A256: =IF(AT256="","",1) | B256: =IF(AT256="","",1) | C256: =IF(AT256="","",0) | D256: =IF(AT256="","",TEXT(INDEX(入力シート!$A$5:$A$204,AT256),"YYYYMMDD")) | E256: =IF(AT256="","",TEXT(INDEX(入力シート!$Q$5:$Q$204,AT256),"00000000")) | F256: =IF(AT256="","",14) | G256: =IF(AT256="","",1) | H256: =IF(AT256="","",1) | I256: =IF(AT256="","",3) | J256: =IF(AT256="","",1) | K256: =IF(AT256="","",INDEX(入力シート!$B$5:$B$204,AT256)) | L256: =IF(AT256="","","") | M256: =IF(AT256="","","") | N256: =IF(AT256="","",COUNTIF(入力シート!$Q$5:$Q$204,INDEX(入力シート!$Q$5:$Q$204,AT256))+1) | O256: =IF(AT256="","",99) | P256: =IF(AT256="","","") | Q256: =IF(AT256="","","") | R256: =IF(AT256="","","消費税") | S256: =IF(AT256="","",0) | T256: =IF(AT256="","","") | U256: =IF(AT256="","",0) | V256: =IF(AT256="","",0) | W256: =IF(AT256="","","") | X256: =IF(AT256="","",0) | Y256: =IF(AT256="","",0) | Z256: =IF(AT256="","",ROUNDDOWN(SUMIF(入力シート!$Q$5:$Q$204,INDEX(入力シート!$Q$5:$Q$204,AT256),入力シート!$P$5:$P$204)*IF(INDEX(入力シート!$L$5:$L$204,AT256)=13,0.1,IF(INDEX(入力シート!$L$5:$L$204,AT256)=30,0.08,0)),0)) | AA256: =IF(AT256="","","") | AB256: =IF(AT256="","",0) | AC256: =IF(AT256="","",0) | AD256: =IF(AT256="","",0) | AE256: =IF(AT256="","","") | AF256: =IF(AT256="","",0) | AG256: =IF(AT256="","",0) | AH256: =IF(AT256="","","") | AI256: =IF(AT256="","","") | AJ256: =IF(AT256="","","") | AK256: =IF(AT256="","",2) | AL256: =IF(AT256="","","") | AM256: =IF(AT256="","","") | AN256: =IF(AT256="","",INDEX(入力シート!$C$5:$C$204,AT256)) | AO256: =IF(AT256="","","") | AP256: =IF(AT256="","","") | AQ256: =IF(AT256="","","") | AT256: =IFERROR(MATCH(56,入力シート!$T$5:$T$204,0),"")
A257: =IF(AT257="","",1) | B257: =IF(AT257="","",1) | C257: =IF(AT257="","",0) | D257: =IF(AT257="","",TEXT(INDEX(入力シート!$A$5:$A$204,AT257),"YYYYMMDD")) | E257: =IF(AT257="","",TEXT(INDEX(入力シート!$Q$5:$Q$204,AT257),"00000000")) | F257: =IF(AT257="","",14) | G257: =IF(AT257="","",1) | H257: =IF(AT257="","",1) | I257: =IF(AT257="","",3) | J257: =IF(AT257="","",1) | K257: =IF(AT257="","",INDEX(入力シート!$B$5:$B$204,AT257)) | L257: =IF(AT257="","","") | M257: =IF(AT257="","","") | N257: =IF(AT257="","",COUNTIF(入力シート!$Q$5:$Q$204,INDEX(入力シート!$Q$5:$Q$204,AT257))+1) | O257: =IF(AT257="","",99) | P257: =IF(AT257="","","") | Q257: =IF(AT257="","","") | R257: =IF(AT257="","","消費税") | S257: =IF(AT257="","",0) | T257: =IF(AT257="","","") | U257: =IF(AT257="","",0) | V257: =IF(AT257="","",0) | W257: =IF(AT257="","","") | X257: =IF(AT257="","",0) | Y257: =IF(AT257="","",0) | Z257: =IF(AT257="","",ROUNDDOWN(SUMIF(入力シート!$Q$5:$Q$204,INDEX(入力シート!$Q$5:$Q$204,AT257),入力シート!$P$5:$P$204)*IF(INDEX(入力シート!$L$5:$L$204,AT257)=13,0.1,IF(INDEX(入力シート!$L$5:$L$204,AT257)=30,0.08,0)),0)) | AA257: =IF(AT257="","","") | AB257: =IF(AT257="","",0) | AC257: =IF(AT257="","",0) | AD257: =IF(AT257="","",0) | AE257: =IF(AT257="","","") | AF257: =IF(AT257="","",0) | AG257: =IF(AT257="","",0) | AH257: =IF(AT257="","","") | AI257: =IF(AT257="","","") | AJ257: =IF(AT257="","","") | AK257: =IF(AT257="","",2) | AL257: =IF(AT257="","","") | AM257: =IF(AT257="","","") | AN257: =IF(AT257="","",INDEX(入力シート!$C$5:$C$204,AT257)) | AO257: =IF(AT257="","","") | AP257: =IF(AT257="","","") | AQ257: =IF(AT257="","","") | AT257: =IFERROR(MATCH(57,入力シート!$T$5:$T$204,0),"")
A258: =IF(AT258="","",1) | B258: =IF(AT258="","",1) | C258: =IF(AT258="","",0) | D258: =IF(AT258="","",TEXT(INDEX(入力シート!$A$5:$A$204,AT258),"YYYYMMDD")) | E258: =IF(AT258="","",TEXT(INDEX(入力シート!$Q$5:$Q$204,AT258),"00000000")) | F258: =IF(AT258="","",14) | G258: =IF(AT258="","",1) | H258: =IF(AT258="","",1) | I258: =IF(AT258="","",3) | J258: =IF(AT258="","",1) | K258: =IF(AT258="","",INDEX(入力シート!$B$5:$B$204,AT258)) | L258: =IF(AT258="","","") | M258: =IF(AT258="","","") | N258: =IF(AT258="","",COUNTIF(入力シート!$Q$5:$Q$204,INDEX(入力シート!$Q$5:$Q$204,AT258))+1) | O258: =IF(AT258="","",99) | P258: =IF(AT258="","","") | Q258: =IF(AT258="","","") | R258: =IF(AT258="","","消費税") | S258: =IF(AT258="","",0) | T258: =IF(AT258="","","") | U258: =IF(AT258="","",0) | V258: =IF(AT258="","",0) | W258: =IF(AT258="","","") | X258: =IF(AT258="","",0) | Y258: =IF(AT258="","",0) | Z258: =IF(AT258="","",ROUNDDOWN(SUMIF(入力シート!$Q$5:$Q$204,INDEX(入力シート!$Q$5:$Q$204,AT258),入力シート!$P$5:$P$204)*IF(INDEX(入力シート!$L$5:$L$204,AT258)=13,0.1,IF(INDEX(入力シート!$L$5:$L$204,AT258)=30,0.08,0)),0)) | AA258: =IF(AT258="","","") | AB258: =IF(AT258="","",0) | AC258: =IF(AT258="","",0) | AD258: =IF(AT258="","",0) | AE258: =IF(AT258="","","") | AF258: =IF(AT258="","",0) | AG258: =IF(AT258="","",0) | AH258: =IF(AT258="","","") | AI258: =IF(AT258="","","") | AJ258: =IF(AT258="","","") | AK258: =IF(AT258="","",2) | AL258: =IF(AT258="","","") | AM258: =IF(AT258="","","") | AN258: =IF(AT258="","",INDEX(入力シート!$C$5:$C$204,AT258)) | AO258: =IF(AT258="","","") | AP258: =IF(AT258="","","") | AQ258: =IF(AT258="","","") | AT258: =IFERROR(MATCH(58,入力シート!$T$5:$T$204,0),"")
A259: =IF(AT259="","",1) | B259: =IF(AT259="","",1) | C259: =IF(AT259="","",0) | D259: =IF(AT259="","",TEXT(INDEX(入力シート!$A$5:$A$204,AT259),"YYYYMMDD")) | E259: =IF(AT259="","",TEXT(INDEX(入力シート!$Q$5:$Q$204,AT259),"00000000")) | F259: =IF(AT259="","",14) | G259: =IF(AT259="","",1) | H259: =IF(AT259="","",1) | I259: =IF(AT259="","",3) | J259: =IF(AT259="","",1) | K259: =IF(AT259="","",INDEX(入力シート!$B$5:$B$204,AT259)) | L259: =IF(AT259="","","") | M259: =IF(AT259="","","") | N259: =IF(AT259="","",COUNTIF(入力シート!$Q$5:$Q$204,INDEX(入力シート!$Q$5:$Q$204,AT259))+1) | O259: =IF(AT259="","",99) | P259: =IF(AT259="","","") | Q259: =IF(AT259="","","") | R259: =IF(AT259="","","消費税") | S259: =IF(AT259="","",0) | T259: =IF(AT259="","","") | U259: =IF(AT259="","",0) | V259: =IF(AT259="","",0) | W259: =IF(AT259="","","") | X259: =IF(AT259="","",0) | Y259: =IF(AT259="","",0) | Z259: =IF(AT259="","",ROUNDDOWN(SUMIF(入力シート!$Q$5:$Q$204,INDEX(入力シート!$Q$5:$Q$204,AT259),入力シート!$P$5:$P$204)*IF(INDEX(入力シート!$L$5:$L$204,AT259)=13,0.1,IF(INDEX(入力シート!$L$5:$L$204,AT259)=30,0.08,0)),0)) | AA259: =IF(AT259="","","") | AB259: =IF(AT259="","",0) | AC259: =IF(AT259="","",0) | AD259: =IF(AT259="","",0) | AE259: =IF(AT259="","","") | AF259: =IF(AT259="","",0) | AG259: =IF(AT259="","",0) | AH259: =IF(AT259="","","") | AI259: =IF(AT259="","","") | AJ259: =IF(AT259="","","") | AK259: =IF(AT259="","",2) | AL259: =IF(AT259="","","") | AM259: =IF(AT259="","","") | AN259: =IF(AT259="","",INDEX(入力シート!$C$5:$C$204,AT259)) | AO259: =IF(AT259="","","") | AP259: =IF(AT259="","","") | AQ259: =IF(AT259="","","") | AT259: =IFERROR(MATCH(59,入力シート!$T$5:$T$204,0),"")
A260: =IF(AT260="","",1) | B260: =IF(AT260="","",1) | C260: =IF(AT260="","",0) | D260: =IF(AT260="","",TEXT(INDEX(入力シート!$A$5:$A$204,AT260),"YYYYMMDD")) | E260: =IF(AT260="","",TEXT(INDEX(入力シート!$Q$5:$Q$204,AT260),"00000000")) | F260: =IF(AT260="","",14) | G260: =IF(AT260="","",1) | H260: =IF(AT260="","",1) | I260: =IF(AT260="","",3) | J260: =IF(AT260="","",1) | K260: =IF(AT260="","",INDEX(入力シート!$B$5:$B$204,AT260)) | L260: =IF(AT260="","","") | M260: =IF(AT260="","","") | N260: =IF(AT260="","",COUNTIF(入力シート!$Q$5:$Q$204,INDEX(入力シート!$Q$5:$Q$204,AT260))+1) | O260: =IF(AT260="","",99) | P260: =IF(AT260="","","") | Q260: =IF(AT260="","","") | R260: =IF(AT260="","","消費税") | S260: =IF(AT260="","",0) | T260: =IF(AT260="","","") | U260: =IF(AT260="","",0) | V260: =IF(AT260="","",0) | W260: =IF(AT260="","","") | X260: =IF(AT260="","",0) | Y260: =IF(AT260="","",0) | Z260: =IF(AT260="","",ROUNDDOWN(SUMIF(入力シート!$Q$5:$Q$204,INDEX(入力シート!$Q$5:$Q$204,AT260),入力シート!$P$5:$P$204)*IF(INDEX(入力シート!$L$5:$L$204,AT260)=13,0.1,IF(INDEX(入力シート!$L$5:$L$204,AT260)=30,0.08,0)),0)) | AA260: =IF(AT260="","","") | AB260: =IF(AT260="","",0) | AC260: =IF(AT260="","",0) | AD260: =IF(AT260="","",0) | AE260: =IF(AT260="","","") | AF260: =IF(AT260="","",0) | AG260: =IF(AT260="","",0) | AH260: =IF(AT260="","","") | AI260: =IF(AT260="","","") | AJ260: =IF(AT260="","","") | AK260: =IF(AT260="","",2) | AL260: =IF(AT260="","","") | AM260: =IF(AT260="","","") | AN260: =IF(AT260="","",INDEX(入力シート!$C$5:$C$204,AT260)) | AO260: =IF(AT260="","","") | AP260: =IF(AT260="","","") | AQ260: =IF(AT260="","","") | AT260: =IFERROR(MATCH(60,入力シート!$T$5:$T$204,0),"")
A261: =IF(AT261="","",1) | B261: =IF(AT261="","",1) | C261: =IF(AT261="","",0) | D261: =IF(AT261="","",TEXT(INDEX(入力シート!$A$5:$A$204,AT261),"YYYYMMDD")) | E261: =IF(AT261="","",TEXT(INDEX(入力シート!$Q$5:$Q$204,AT261),"00000000")) | F261: =IF(AT261="","",14) | G261: =IF(AT261="","",1) | H261: =IF(AT261="","",1) | I261: =IF(AT261="","",3) | J261: =IF(AT261="","",1) | K261: =IF(AT261="","",INDEX(入力シート!$B$5:$B$204,AT261)) | L261: =IF(AT261="","","") | M261: =IF(AT261="","","") | N261: =IF(AT261="","",COUNTIF(入力シート!$Q$5:$Q$204,INDEX(入力シート!$Q$5:$Q$204,AT261))+1) | O261: =IF(AT261="","",99) | P261: =IF(AT261="","","") | Q261: =IF(AT261="","","") | R261: =IF(AT261="","","消費税") | S261: =IF(AT261="","",0) | T261: =IF(AT261="","","") | U261: =IF(AT261="","",0) | V261: =IF(AT261="","",0) | W261: =IF(AT261="","","") | X261: =IF(AT261="","",0) | Y261: =IF(AT261="","",0) | Z261: =IF(AT261="","",ROUNDDOWN(SUMIF(入力シート!$Q$5:$Q$204,INDEX(入力シート!$Q$5:$Q$204,AT261),入力シート!$P$5:$P$204)*IF(INDEX(入力シート!$L$5:$L$204,AT261)=13,0.1,IF(INDEX(入力シート!$L$5:$L$204,AT261)=30,0.08,0)),0)) | AA261: =IF(AT261="","","") | AB261: =IF(AT261="","",0) | AC261: =IF(AT261="","",0) | AD261: =IF(AT261="","",0) | AE261: =IF(AT261="","","") | AF261: =IF(AT261="","",0) | AG261: =IF(AT261="","",0) | AH261: =IF(AT261="","","") | AI261: =IF(AT261="","","") | AJ261: =IF(AT261="","","") | AK261: =IF(AT261="","",2) | AL261: =IF(AT261="","","") | AM261: =IF(AT261="","","") | AN261: =IF(AT261="","",INDEX(入力シート!$C$5:$C$204,AT261)) | AO261: =IF(AT261="","","") | AP261: =IF(AT261="","","") | AQ261: =IF(AT261="","","") | AT261: =IFERROR(MATCH(61,入力シート!$T$5:$T$204,0),"")
A262: =IF(AT262="","",1) | B262: =IF(AT262="","",1) | C262: =IF(AT262="","",0) | D262: =IF(AT262="","",TEXT(INDEX(入力シート!$A$5:$A$204,AT262),"YYYYMMDD")) | E262: =IF(AT262="","",TEXT(INDEX(入力シート!$Q$5:$Q$204,AT262),"00000000")) | F262: =IF(AT262="","",14) | G262: =IF(AT262="","",1) | H262: =IF(AT262="","",1) | I262: =IF(AT262="","",3) | J262: =IF(AT262="","",1) | K262: =IF(AT262="","",INDEX(入力シート!$B$5:$B$204,AT262)) | L262: =IF(AT262="","","") | M262: =IF(AT262="","","") | N262: =IF(AT262="","",COUNTIF(入力シート!$Q$5:$Q$204,INDEX(入力シート!$Q$5:$Q$204,AT262))+1) | O262: =IF(AT262="","",99) | P262: =IF(AT262="","","") | Q262: =IF(AT262="","","") | R262: =IF(AT262="","","消費税") | S262: =IF(AT262="","",0) | T262: =IF(AT262="","","") | U262: =IF(AT262="","",0) | V262: =IF(AT262="","",0) | W262: =IF(AT262="","","") | X262: =IF(AT262="","",0) | Y262: =IF(AT262="","",0) | Z262: =IF(AT262="","",ROUNDDOWN(SUMIF(入力シート!$Q$5:$Q$204,INDEX(入力シート!$Q$5:$Q$204,AT262),入力シート!$P$5:$P$204)*IF(INDEX(入力シート!$L$5:$L$204,AT262)=13,0.1,IF(INDEX(入力シート!$L$5:$L$204,AT262)=30,0.08,0)),0)) | AA262: =IF(AT262="","","") | AB262: =IF(AT262="","",0) | AC262: =IF(AT262="","",0) | AD262: =IF(AT262="","",0) | AE262: =IF(AT262="","","") | AF262: =IF(AT262="","",0) | AG262: =IF(AT262="","",0) | AH262: =IF(AT262="","","") | AI262: =IF(AT262="","","") | AJ262: =IF(AT262="","","") | AK262: =IF(AT262="","",2) | AL262: =IF(AT262="","","") | AM262: =IF(AT262="","","") | AN262: =IF(AT262="","",INDEX(入力シート!$C$5:$C$204,AT262)) | AO262: =IF(AT262="","","") | AP262: =IF(AT262="","","") | AQ262: =IF(AT262="","","") | AT262: =IFERROR(MATCH(62,入力シート!$T$5:$T$204,0),"")
A263: =IF(AT263="","",1) | B263: =IF(AT263="","",1) | C263: =IF(AT263="","",0) | D263: =IF(AT263="","",TEXT(INDEX(入力シート!$A$5:$A$204,AT263),"YYYYMMDD")) | E263: =IF(AT263="","",TEXT(INDEX(入力シート!$Q$5:$Q$204,AT263),"00000000")) | F263: =IF(AT263="","",14) | G263: =IF(AT263="","",1) | H263: =IF(AT263="","",1) | I263: =IF(AT263="","",3) | J263: =IF(AT263="","",1) | K263: =IF(AT263="","",INDEX(入力シート!$B$5:$B$204,AT263)) | L263: =IF(AT263="","","") | M263: =IF(AT263="","","") | N263: =IF(AT263="","",COUNTIF(入力シート!$Q$5:$Q$204,INDEX(入力シート!$Q$5:$Q$204,AT263))+1) | O263: =IF(AT263="","",99) | P263: =IF(AT263="","","") | Q263: =IF(AT263="","","") | R263: =IF(AT263="","","消費税") | S263: =IF(AT263="","",0) | T263: =IF(AT263="","","") | U263: =IF(AT263="","",0) | V263: =IF(AT263="","",0) | W263: =IF(AT263="","","") | X263: =IF(AT263="","",0) | Y263: =IF(AT263="","",0) | Z263: =IF(AT263="","",ROUNDDOWN(SUMIF(入力シート!$Q$5:$Q$204,INDEX(入力シート!$Q$5:$Q$204,AT263),入力シート!$P$5:$P$204)*IF(INDEX(入力シート!$L$5:$L$204,AT263)=13,0.1,IF(INDEX(入力シート!$L$5:$L$204,AT263)=30,0.08,0)),0)) | AA263: =IF(AT263="","","") | AB263: =IF(AT263="","",0) | AC263: =IF(AT263="","",0) | AD263: =IF(AT263="","",0) | AE263: =IF(AT263="","","") | AF263: =IF(AT263="","",0) | AG263: =IF(AT263="","",0) | AH263: =IF(AT263="","","") | AI263: =IF(AT263="","","") | AJ263: =IF(AT263="","","") | AK263: =IF(AT263="","",2) | AL263: =IF(AT263="","","") | AM263: =IF(AT263="","","") | AN263: =IF(AT263="","",INDEX(入力シート!$C$5:$C$204,AT263)) | AO263: =IF(AT263="","","") | AP263: =IF(AT263="","","") | AQ263: =IF(AT263="","","") | AT263: =IFERROR(MATCH(63,入力シート!$T$5:$T$204,0),"")
A264: =IF(AT264="","",1) | B264: =IF(AT264="","",1) | C264: =IF(AT264="","",0) | D264: =IF(AT264="","",TEXT(INDEX(入力シート!$A$5:$A$204,AT264),"YYYYMMDD")) | E264: =IF(AT264="","",TEXT(INDEX(入力シート!$Q$5:$Q$204,AT264),"00000000")) | F264: =IF(AT264="","",14) | G264: =IF(AT264="","",1) | H264: =IF(AT264="","",1) | I264: =IF(AT264="","",3) | J264: =IF(AT264="","",1) | K264: =IF(AT264="","",INDEX(入力シート!$B$5:$B$204,AT264)) | L264: =IF(AT264="","","") | M264: =IF(AT264="","","") | N264: =IF(AT264="","",COUNTIF(入力シート!$Q$5:$Q$204,INDEX(入力シート!$Q$5:$Q$204,AT264))+1) | O264: =IF(AT264="","",99) | P264: =IF(AT264="","","") | Q264: =IF(AT264="","","") | R264: =IF(AT264="","","消費税") | S264: =IF(AT264="","",0) | T264: =IF(AT264="","","") | U264: =IF(AT264="","",0) | V264: =IF(AT264="","",0) | W264: =IF(AT264="","","") | X264: =IF(AT264="","",0) | Y264: =IF(AT264="","",0) | Z264: =IF(AT264="","",ROUNDDOWN(SUMIF(入力シート!$Q$5:$Q$204,INDEX(入力シート!$Q$5:$Q$204,AT264),入力シート!$P$5:$P$204)*IF(INDEX(入力シート!$L$5:$L$204,AT264)=13,0.1,IF(INDEX(入力シート!$L$5:$L$204,AT264)=30,0.08,0)),0)) | AA264: =IF(AT264="","","") | AB264: =IF(AT264="","",0) | AC264: =IF(AT264="","",0) | AD264: =IF(AT264="","",0) | AE264: =IF(AT264="","","") | AF264: =IF(AT264="","",0) | AG264: =IF(AT264="","",0) | AH264: =IF(AT264="","","") | AI264: =IF(AT264="","","") | AJ264: =IF(AT264="","","") | AK264: =IF(AT264="","",2) | AL264: =IF(AT264="","","") | AM264: =IF(AT264="","","") | AN264: =IF(AT264="","",INDEX(入力シート!$C$5:$C$204,AT264)) | AO264: =IF(AT264="","","") | AP264: =IF(AT264="","","") | AQ264: =IF(AT264="","","") | AT264: =IFERROR(MATCH(64,入力シート!$T$5:$T$204,0),"")
A265: =IF(AT265="","",1) | B265: =IF(AT265="","",1) | C265: =IF(AT265="","",0) | D265: =IF(AT265="","",TEXT(INDEX(入力シート!$A$5:$A$204,AT265),"YYYYMMDD")) | E265: =IF(AT265="","",TEXT(INDEX(入力シート!$Q$5:$Q$204,AT265),"00000000")) | F265: =IF(AT265="","",14) | G265: =IF(AT265="","",1) | H265: =IF(AT265="","",1) | I265: =IF(AT265="","",3) | J265: =IF(AT265="","",1) | K265: =IF(AT265="","",INDEX(入力シート!$B$5:$B$204,AT265)) | L265: =IF(AT265="","","") | M265: =IF(AT265="","","") | N265: =IF(AT265="","",COUNTIF(入力シート!$Q$5:$Q$204,INDEX(入力シート!$Q$5:$Q$204,AT265))+1) | O265: =IF(AT265="","",99) | P265: =IF(AT265="","","") | Q265: =IF(AT265="","","") | R265: =IF(AT265="","","消費税") | S265: =IF(AT265="","",0) | T265: =IF(AT265="","","") | U265: =IF(AT265="","",0) | V265: =IF(AT265="","",0) | W265: =IF(AT265="","","") | X265: =IF(AT265="","",0) | Y265: =IF(AT265="","",0) | Z265: =IF(AT265="","",ROUNDDOWN(SUMIF(入力シート!$Q$5:$Q$204,INDEX(入力シート!$Q$5:$Q$204,AT265),入力シート!$P$5:$P$204)*IF(INDEX(入力シート!$L$5:$L$204,AT265)=13,0.1,IF(INDEX(入力シート!$L$5:$L$204,AT265)=30,0.08,0)),0)) | AA265: =IF(AT265="","","") | AB265: =IF(AT265="","",0) | AC265: =IF(AT265="","",0) | AD265: =IF(AT265="","",0) | AE265: =IF(AT265="","","") | AF265: =IF(AT265="","",0) | AG265: =IF(AT265="","",0) | AH265: =IF(AT265="","","") | AI265: =IF(AT265="","","") | AJ265: =IF(AT265="","","") | AK265: =IF(AT265="","",2) | AL265: =IF(AT265="","","") | AM265: =IF(AT265="","","") | AN265: =IF(AT265="","",INDEX(入力シート!$C$5:$C$204,AT265)) | AO265: =IF(AT265="","","") | AP265: =IF(AT265="","","") | AQ265: =IF(AT265="","","") | AT265: =IFERROR(MATCH(65,入力シート!$T$5:$T$204,0),"")
A266: =IF(AT266="","",1) | B266: =IF(AT266="","",1) | C266: =IF(AT266="","",0) | D266: =IF(AT266="","",TEXT(INDEX(入力シート!$A$5:$A$204,AT266),"YYYYMMDD")) | E266: =IF(AT266="","",TEXT(INDEX(入力シート!$Q$5:$Q$204,AT266),"00000000")) | F266: =IF(AT266="","",14) | G266: =IF(AT266="","",1) | H266: =IF(AT266="","",1) | I266: =IF(AT266="","",3) | J266: =IF(AT266="","",1) | K266: =IF(AT266="","",INDEX(入力シート!$B$5:$B$204,AT266)) | L266: =IF(AT266="","","") | M266: =IF(AT266="","","") | N266: =IF(AT266="","",COUNTIF(入力シート!$Q$5:$Q$204,INDEX(入力シート!$Q$5:$Q$204,AT266))+1) | O266: =IF(AT266="","",99) | P266: =IF(AT266="","","") | Q266: =IF(AT266="","","") | R266: =IF(AT266="","","消費税") | S266: =IF(AT266="","",0) | T266: =IF(AT266="","","") | U266: =IF(AT266="","",0) | V266: =IF(AT266="","",0) | W266: =IF(AT266="","","") | X266: =IF(AT266="","",0) | Y266: =IF(AT266="","",0) | Z266: =IF(AT266="","",ROUNDDOWN(SUMIF(入力シート!$Q$5:$Q$204,INDEX(入力シート!$Q$5:$Q$204,AT266),入力シート!$P$5:$P$204)*IF(INDEX(入力シート!$L$5:$L$204,AT266)=13,0.1,IF(INDEX(入力シート!$L$5:$L$204,AT266)=30,0.08,0)),0)) | AA266: =IF(AT266="","","") | AB266: =IF(AT266="","",0) | AC266: =IF(AT266="","",0) | AD266: =IF(AT266="","",0) | AE266: =IF(AT266="","","") | AF266: =IF(AT266="","",0) | AG266: =IF(AT266="","",0) | AH266: =IF(AT266="","","") | AI266: =IF(AT266="","","") | AJ266: =IF(AT266="","","") | AK266: =IF(AT266="","",2) | AL266: =IF(AT266="","","") | AM266: =IF(AT266="","","") | AN266: =IF(AT266="","",INDEX(入力シート!$C$5:$C$204,AT266)) | AO266: =IF(AT266="","","") | AP266: =IF(AT266="","","") | AQ266: =IF(AT266="","","") | AT266: =IFERROR(MATCH(66,入力シート!$T$5:$T$204,0),"")
A267: =IF(AT267="","",1) | B267: =IF(AT267="","",1) | C267: =IF(AT267="","",0) | D267: =IF(AT267="","",TEXT(INDEX(入力シート!$A$5:$A$204,AT267),"YYYYMMDD")) | E267: =IF(AT267="","",TEXT(INDEX(入力シート!$Q$5:$Q$204,AT267),"00000000")) | F267: =IF(AT267="","",14) | G267: =IF(AT267="","",1) | H267: =IF(AT267="","",1) | I267: =IF(AT267="","",3) | J267: =IF(AT267="","",1) | K267: =IF(AT267="","",INDEX(入力シート!$B$5:$B$204,AT267)) | L267: =IF(AT267="","","") | M267: =IF(AT267="","","") | N267: =IF(AT267="","",COUNTIF(入力シート!$Q$5:$Q$204,INDEX(入力シート!$Q$5:$Q$204,AT267))+1) | O267: =IF(AT267="","",99) | P267: =IF(AT267="","","") | Q267: =IF(AT267="","","") | R267: =IF(AT267="","","消費税") | S267: =IF(AT267="","",0) | T267: =IF(AT267="","","") | U267: =IF(AT267="","",0) | V267: =IF(AT267="","",0) | W267: =IF(AT267="","","") | X267: =IF(AT267="","",0) | Y267: =IF(AT267="","",0) | Z267: =IF(AT267="","",ROUNDDOWN(SUMIF(入力シート!$Q$5:$Q$204,INDEX(入力シート!$Q$5:$Q$204,AT267),入力シート!$P$5:$P$204)*IF(INDEX(入力シート!$L$5:$L$204,AT267)=13,0.1,IF(INDEX(入力シート!$L$5:$L$204,AT267)=30,0.08,0)),0)) | AA267: =IF(AT267="","","") | AB267: =IF(AT267="","",0) | AC267: =IF(AT267="","",0) | AD267: =IF(AT267="","",0) | AE267: =IF(AT267="","","") | AF267: =IF(AT267="","",0) | AG267: =IF(AT267="","",0) | AH267: =IF(AT267="","","") | AI267: =IF(AT267="","","") | AJ267: =IF(AT267="","","") | AK267: =IF(AT267="","",2) | AL267: =IF(AT267="","","") | AM267: =IF(AT267="","","") | AN267: =IF(AT267="","",INDEX(入力シート!$C$5:$C$204,AT267)) | AO267: =IF(AT267="","","") | AP267: =IF(AT267="","","") | AQ267: =IF(AT267="","","") | AT267: =IFERROR(MATCH(67,入力シート!$T$5:$T$204,0),"")
A268: =IF(AT268="","",1) | B268: =IF(AT268="","",1) | C268: =IF(AT268="","",0) | D268: =IF(AT268="","",TEXT(INDEX(入力シート!$A$5:$A$204,AT268),"YYYYMMDD")) | E268: =IF(AT268="","",TEXT(INDEX(入力シート!$Q$5:$Q$204,AT268),"00000000")) | F268: =IF(AT268="","",14) | G268: =IF(AT268="","",1) | H268: =IF(AT268="","",1) | I268: =IF(AT268="","",3) | J268: =IF(AT268="","",1) | K268: =IF(AT268="","",INDEX(入力シート!$B$5:$B$204,AT268)) | L268: =IF(AT268="","","") | M268: =IF(AT268="","","") | N268: =IF(AT268="","",COUNTIF(入力シート!$Q$5:$Q$204,INDEX(入力シート!$Q$5:$Q$204,AT268))+1) | O268: =IF(AT268="","",99) | P268: =IF(AT268="","","") | Q268: =IF(AT268="","","") | R268: =IF(AT268="","","消費税") | S268: =IF(AT268="","",0) | T268: =IF(AT268="","","") | U268: =IF(AT268="","",0) | V268: =IF(AT268="","",0) | W268: =IF(AT268="","","") | X268: =IF(AT268="","",0) | Y268: =IF(AT268="","",0) | Z268: =IF(AT268="","",ROUNDDOWN(SUMIF(入力シート!$Q$5:$Q$204,INDEX(入力シート!$Q$5:$Q$204,AT268),入力シート!$P$5:$P$204)*IF(INDEX(入力シート!$L$5:$L$204,AT268)=13,0.1,IF(INDEX(入力シート!$L$5:$L$204,AT268)=30,0.08,0)),0)) | AA268: =IF(AT268="","","") | AB268: =IF(AT268="","",0) | AC268: =IF(AT268="","",0) | AD268: =IF(AT268="","",0) | AE268: =IF(AT268="","","") | AF268: =IF(AT268="","",0) | AG268: =IF(AT268="","",0) | AH268: =IF(AT268="","","") | AI268: =IF(AT268="","","") | AJ268: =IF(AT268="","","") | AK268: =IF(AT268="","",2) | AL268: =IF(AT268="","","") | AM268: =IF(AT268="","","") | AN268: =IF(AT268="","",INDEX(入力シート!$C$5:$C$204,AT268)) | AO268: =IF(AT268="","","") | AP268: =IF(AT268="","","") | AQ268: =IF(AT268="","","") | AT268: =IFERROR(MATCH(68,入力シート!$T$5:$T$204,0),"")
A269: =IF(AT269="","",1) | B269: =IF(AT269="","",1) | C269: =IF(AT269="","",0) | D269: =IF(AT269="","",TEXT(INDEX(入力シート!$A$5:$A$204,AT269),"YYYYMMDD")) | E269: =IF(AT269="","",TEXT(INDEX(入力シート!$Q$5:$Q$204,AT269),"00000000")) | F269: =IF(AT269="","",14) | G269: =IF(AT269="","",1) | H269: =IF(AT269="","",1) | I269: =IF(AT269="","",3) | J269: =IF(AT269="","",1) | K269: =IF(AT269="","",INDEX(入力シート!$B$5:$B$204,AT269)) | L269: =IF(AT269="","","") | M269: =IF(AT269="","","") | N269: =IF(AT269="","",COUNTIF(入力シート!$Q$5:$Q$204,INDEX(入力シート!$Q$5:$Q$204,AT269))+1) | O269: =IF(AT269="","",99) | P269: =IF(AT269="","","") | Q269: =IF(AT269="","","") | R269: =IF(AT269="","","消費税") | S269: =IF(AT269="","",0) | T269: =IF(AT269="","","") | U269: =IF(AT269="","",0) | V269: =IF(AT269="","",0) | W269: =IF(AT269="","","") | X269: =IF(AT269="","",0) | Y269: =IF(AT269="","",0) | Z269: =IF(AT269="","",ROUNDDOWN(SUMIF(入力シート!$Q$5:$Q$204,INDEX(入力シート!$Q$5:$Q$204,AT269),入力シート!$P$5:$P$204)*IF(INDEX(入力シート!$L$5:$L$204,AT269)=13,0.1,IF(INDEX(入力シート!$L$5:$L$204,AT269)=30,0.08,0)),0)) | AA269: =IF(AT269="","","") | AB269: =IF(AT269="","",0) | AC269: =IF(AT269="","",0) | AD269: =IF(AT269="","",0) | AE269: =IF(AT269="","","") | AF269: =IF(AT269="","",0) | AG269: =IF(AT269="","",0) | AH269: =IF(AT269="","","") | AI269: =IF(AT269="","","") | AJ269: =IF(AT269="","","") | AK269: =IF(AT269="","",2) | AL269: =IF(AT269="","","") | AM269: =IF(AT269="","","") | AN269: =IF(AT269="","",INDEX(入力シート!$C$5:$C$204,AT269)) | AO269: =IF(AT269="","","") | AP269: =IF(AT269="","","") | AQ269: =IF(AT269="","","") | AT269: =IFERROR(MATCH(69,入力シート!$T$5:$T$204,0),"")
A270: =IF(AT270="","",1) | B270: =IF(AT270="","",1) | C270: =IF(AT270="","",0) | D270: =IF(AT270="","",TEXT(INDEX(入力シート!$A$5:$A$204,AT270),"YYYYMMDD")) | E270: =IF(AT270="","",TEXT(INDEX(入力シート!$Q$5:$Q$204,AT270),"00000000")) | F270: =IF(AT270="","",14) | G270: =IF(AT270="","",1) | H270: =IF(AT270="","",1) | I270: =IF(AT270="","",3) | J270: =IF(AT270="","",1) | K270: =IF(AT270="","",INDEX(入力シート!$B$5:$B$204,AT270)) | L270: =IF(AT270="","","") | M270: =IF(AT270="","","") | N270: =IF(AT270="","",COUNTIF(入力シート!$Q$5:$Q$204,INDEX(入力シート!$Q$5:$Q$204,AT270))+1) | O270: =IF(AT270="","",99) | P270: =IF(AT270="","","") | Q270: =IF(AT270="","","") | R270: =IF(AT270="","","消費税") | S270: =IF(AT270="","",0) | T270: =IF(AT270="","","") | U270: =IF(AT270="","",0) | V270: =IF(AT270="","",0) | W270: =IF(AT270="","","") | X270: =IF(AT270="","",0) | Y270: =IF(AT270="","",0) | Z270: =IF(AT270="","",ROUNDDOWN(SUMIF(入力シート!$Q$5:$Q$204,INDEX(入力シート!$Q$5:$Q$204,AT270),入力シート!$P$5:$P$204)*IF(INDEX(入力シート!$L$5:$L$204,AT270)=13,0.1,IF(INDEX(入力シート!$L$5:$L$204,AT270)=30,0.08,0)),0)) | AA270: =IF(AT270="","","") | AB270: =IF(AT270="","",0) | AC270: =IF(AT270="","",0) | AD270: =IF(AT270="","",0) | AE270: =IF(AT270="","","") | AF270: =IF(AT270="","",0) | AG270: =IF(AT270="","",0) | AH270: =IF(AT270="","","") | AI270: =IF(AT270="","","") | AJ270: =IF(AT270="","","") | AK270: =IF(AT270="","",2) | AL270: =IF(AT270="","","") | AM270: =IF(AT270="","","") | AN270: =IF(AT270="","",INDEX(入力シート!$C$5:$C$204,AT270)) | AO270: =IF(AT270="","","") | AP270: =IF(AT270="","","") | AQ270: =IF(AT270="","","") | AT270: =IFERROR(MATCH(70,入力シート!$T$5:$T$204,0),"")
A271: =IF(AT271="","",1) | B271: =IF(AT271="","",1) | C271: =IF(AT271="","",0) | D271: =IF(AT271="","",TEXT(INDEX(入力シート!$A$5:$A$204,AT271),"YYYYMMDD")) | E271: =IF(AT271="","",TEXT(INDEX(入力シート!$Q$5:$Q$204,AT271),"00000000")) | F271: =IF(AT271="","",14) | G271: =IF(AT271="","",1) | H271: =IF(AT271="","",1) | I271: =IF(AT271="","",3) | J271: =IF(AT271="","",1) | K271: =IF(AT271="","",INDEX(入力シート!$B$5:$B$204,AT271)) | L271: =IF(AT271="","","") | M271: =IF(AT271="","","") | N271: =IF(AT271="","",COUNTIF(入力シート!$Q$5:$Q$204,INDEX(入力シート!$Q$5:$Q$204,AT271))+1) | O271: =IF(AT271="","",99) | P271: =IF(AT271="","","") | Q271: =IF(AT271="","","") | R271: =IF(AT271="","","消費税") | S271: =IF(AT271="","",0) | T271: =IF(AT271="","","") | U271: =IF(AT271="","",0) | V271: =IF(AT271="","",0) | W271: =IF(AT271="","","") | X271: =IF(AT271="","",0) | Y271: =IF(AT271="","",0) | Z271: =IF(AT271="","",ROUNDDOWN(SUMIF(入力シート!$Q$5:$Q$204,INDEX(入力シート!$Q$5:$Q$204,AT271),入力シート!$P$5:$P$204)*IF(INDEX(入力シート!$L$5:$L$204,AT271)=13,0.1,IF(INDEX(入力シート!$L$5:$L$204,AT271)=30,0.08,0)),0)) | AA271: =IF(AT271="","","") | AB271: =IF(AT271="","",0) | AC271: =IF(AT271="","",0) | AD271: =IF(AT271="","",0) | AE271: =IF(AT271="","","") | AF271: =IF(AT271="","",0) | AG271: =IF(AT271="","",0) | AH271: =IF(AT271="","","") | AI271: =IF(AT271="","","") | AJ271: =IF(AT271="","","") | AK271: =IF(AT271="","",2) | AL271: =IF(AT271="","","") | AM271: =IF(AT271="","","") | AN271: =IF(AT271="","",INDEX(入力シート!$C$5:$C$204,AT271)) | AO271: =IF(AT271="","","") | AP271: =IF(AT271="","","") | AQ271: =IF(AT271="","","") | AT271: =IFERROR(MATCH(71,入力シート!$T$5:$T$204,0),"")
A272: =IF(AT272="","",1) | B272: =IF(AT272="","",1) | C272: =IF(AT272="","",0) | D272: =IF(AT272="","",TEXT(INDEX(入力シート!$A$5:$A$204,AT272),"YYYYMMDD")) | E272: =IF(AT272="","",TEXT(INDEX(入力シート!$Q$5:$Q$204,AT272),"00000000")) | F272: =IF(AT272="","",14) | G272: =IF(AT272="","",1) | H272: =IF(AT272="","",1) | I272: =IF(AT272="","",3) | J272: =IF(AT272="","",1) | K272: =IF(AT272="","",INDEX(入力シート!$B$5:$B$204,AT272)) | L272: =IF(AT272="","","") | M272: =IF(AT272="","","") | N272: =IF(AT272="","",COUNTIF(入力シート!$Q$5:$Q$204,INDEX(入力シート!$Q$5:$Q$204,AT272))+1) | O272: =IF(AT272="","",99) | P272: =IF(AT272="","","") | Q272: =IF(AT272="","","") | R272: =IF(AT272="","","消費税") | S272: =IF(AT272="","",0) | T272: =IF(AT272="","","") | U272: =IF(AT272="","",0) | V272: =IF(AT272="","",0) | W272: =IF(AT272="","","") | X272: =IF(AT272="","",0) | Y272: =IF(AT272="","",0) | Z272: =IF(AT272="","",ROUNDDOWN(SUMIF(入力シート!$Q$5:$Q$204,INDEX(入力シート!$Q$5:$Q$204,AT272),入力シート!$P$5:$P$204)*IF(INDEX(入力シート!$L$5:$L$204,AT272)=13,0.1,IF(INDEX(入力シート!$L$5:$L$204,AT272)=30,0.08,0)),0)) | AA272: =IF(AT272="","","") | AB272: =IF(AT272="","",0) | AC272: =IF(AT272="","",0) | AD272: =IF(AT272="","",0) | AE272: =IF(AT272="","","") | AF272: =IF(AT272="","",0) | AG272: =IF(AT272="","",0) | AH272: =IF(AT272="","","") | AI272: =IF(AT272="","","") | AJ272: =IF(AT272="","","") | AK272: =IF(AT272="","",2) | AL272: =IF(AT272="","","") | AM272: =IF(AT272="","","") | AN272: =IF(AT272="","",INDEX(入力シート!$C$5:$C$204,AT272)) | AO272: =IF(AT272="","","") | AP272: =IF(AT272="","","") | AQ272: =IF(AT272="","","") | AT272: =IFERROR(MATCH(72,入力シート!$T$5:$T$204,0),"")
A273: =IF(AT273="","",1) | B273: =IF(AT273="","",1) | C273: =IF(AT273="","",0) | D273: =IF(AT273="","",TEXT(INDEX(入力シート!$A$5:$A$204,AT273),"YYYYMMDD")) | E273: =IF(AT273="","",TEXT(INDEX(入力シート!$Q$5:$Q$204,AT273),"00000000")) | F273: =IF(AT273="","",14) | G273: =IF(AT273="","",1) | H273: =IF(AT273="","",1) | I273: =IF(AT273="","",3) | J273: =IF(AT273="","",1) | K273: =IF(AT273="","",INDEX(入力シート!$B$5:$B$204,AT273)) | L273: =IF(AT273="","","") | M273: =IF(AT273="","","") | N273: =IF(AT273="","",COUNTIF(入力シート!$Q$5:$Q$204,INDEX(入力シート!$Q$5:$Q$204,AT273))+1) | O273: =IF(AT273="","",99) | P273: =IF(AT273="","","") | Q273: =IF(AT273="","","") | R273: =IF(AT273="","","消費税") | S273: =IF(AT273="","",0) | T273: =IF(AT273="","","") | U273: =IF(AT273="","",0) | V273: =IF(AT273="","",0) | W273: =IF(AT273="","","") | X273: =IF(AT273="","",0) | Y273: =IF(AT273="","",0) | Z273: =IF(AT273="","",ROUNDDOWN(SUMIF(入力シート!$Q$5:$Q$204,INDEX(入力シート!$Q$5:$Q$204,AT273),入力シート!$P$5:$P$204)*IF(INDEX(入力シート!$L$5:$L$204,AT273)=13,0.1,IF(INDEX(入力シート!$L$5:$L$204,AT273)=30,0.08,0)),0)) | AA273: =IF(AT273="","","") | AB273: =IF(AT273="","",0) | AC273: =IF(AT273="","",0) | AD273: =IF(AT273="","",0) | AE273: =IF(AT273="","","") | AF273: =IF(AT273="","",0) | AG273: =IF(AT273="","",0) | AH273: =IF(AT273="","","") | AI273: =IF(AT273="","","") | AJ273: =IF(AT273="","","") | AK273: =IF(AT273="","",2) | AL273: =IF(AT273="","","") | AM273: =IF(AT273="","","") | AN273: =IF(AT273="","",INDEX(入力シート!$C$5:$C$204,AT273)) | AO273: =IF(AT273="","","") | AP273: =IF(AT273="","","") | AQ273: =IF(AT273="","","") | AT273: =IFERROR(MATCH(73,入力シート!$T$5:$T$204,0),"")
A274: =IF(AT274="","",1) | B274: =IF(AT274="","",1) | C274: =IF(AT274="","",0) | D274: =IF(AT274="","",TEXT(INDEX(入力シート!$A$5:$A$204,AT274),"YYYYMMDD")) | E274: =IF(AT274="","",TEXT(INDEX(入力シート!$Q$5:$Q$204,AT274),"00000000")) | F274: =IF(AT274="","",14) | G274: =IF(AT274="","",1) | H274: =IF(AT274="","",1) | I274: =IF(AT274="","",3) | J274: =IF(AT274="","",1) | K274: =IF(AT274="","",INDEX(入力シート!$B$5:$B$204,AT274)) | L274: =IF(AT274="","","") | M274: =IF(AT274="","","") | N274: =IF(AT274="","",COUNTIF(入力シート!$Q$5:$Q$204,INDEX(入力シート!$Q$5:$Q$204,AT274))+1) | O274: =IF(AT274="","",99) | P274: =IF(AT274="","","") | Q274: =IF(AT274="","","") | R274: =IF(AT274="","","消費税") | S274: =IF(AT274="","",0) | T274: =IF(AT274="","","") | U274: =IF(AT274="","",0) | V274: =IF(AT274="","",0) | W274: =IF(AT274="","","") | X274: =IF(AT274="","",0) | Y274: =IF(AT274="","",0) | Z274: =IF(AT274="","",ROUNDDOWN(SUMIF(入力シート!$Q$5:$Q$204,INDEX(入力シート!$Q$5:$Q$204,AT274),入力シート!$P$5:$P$204)*IF(INDEX(入力シート!$L$5:$L$204,AT274)=13,0.1,IF(INDEX(入力シート!$L$5:$L$204,AT274)=30,0.08,0)),0)) | AA274: =IF(AT274="","","") | AB274: =IF(AT274="","",0) | AC274: =IF(AT274="","",0) | AD274: =IF(AT274="","",0) | AE274: =IF(AT274="","","") | AF274: =IF(AT274="","",0) | AG274: =IF(AT274="","",0) | AH274: =IF(AT274="","","") | AI274: =IF(AT274="","","") | AJ274: =IF(AT274="","","") | AK274: =IF(AT274="","",2) | AL274: =IF(AT274="","","") | AM274: =IF(AT274="","","") | AN274: =IF(AT274="","",INDEX(入力シート!$C$5:$C$204,AT274)) | AO274: =IF(AT274="","","") | AP274: =IF(AT274="","","") | AQ274: =IF(AT274="","","") | AT274: =IFERROR(MATCH(74,入力シート!$T$5:$T$204,0),"")
A275: =IF(AT275="","",1) | B275: =IF(AT275="","",1) | C275: =IF(AT275="","",0) | D275: =IF(AT275="","",TEXT(INDEX(入力シート!$A$5:$A$204,AT275),"YYYYMMDD")) | E275: =IF(AT275="","",TEXT(INDEX(入力シート!$Q$5:$Q$204,AT275),"00000000")) | F275: =IF(AT275="","",14) | G275: =IF(AT275="","",1) | H275: =IF(AT275="","",1) | I275: =IF(AT275="","",3) | J275: =IF(AT275="","",1) | K275: =IF(AT275="","",INDEX(入力シート!$B$5:$B$204,AT275)) | L275: =IF(AT275="","","") | M275: =IF(AT275="","","") | N275: =IF(AT275="","",COUNTIF(入力シート!$Q$5:$Q$204,INDEX(入力シート!$Q$5:$Q$204,AT275))+1) | O275: =IF(AT275="","",99) | P275: =IF(AT275="","","") | Q275: =IF(AT275="","","") | R275: =IF(AT275="","","消費税") | S275: =IF(AT275="","",0) | T275: =IF(AT275="","","") | U275: =IF(AT275="","",0) | V275: =IF(AT275="","",0) | W275: =IF(AT275="","","") | X275: =IF(AT275="","",0) | Y275: =IF(AT275="","",0) | Z275: =IF(AT275="","",ROUNDDOWN(SUMIF(入力シート!$Q$5:$Q$204,INDEX(入力シート!$Q$5:$Q$204,AT275),入力シート!$P$5:$P$204)*IF(INDEX(入力シート!$L$5:$L$204,AT275)=13,0.1,IF(INDEX(入力シート!$L$5:$L$204,AT275)=30,0.08,0)),0)) | AA275: =IF(AT275="","","") | AB275: =IF(AT275="","",0) | AC275: =IF(AT275="","",0) | AD275: =IF(AT275="","",0) | AE275: =IF(AT275="","","") | AF275: =IF(AT275="","",0) | AG275: =IF(AT275="","",0) | AH275: =IF(AT275="","","") | AI275: =IF(AT275="","","") | AJ275: =IF(AT275="","","") | AK275: =IF(AT275="","",2) | AL275: =IF(AT275="","","") | AM275: =IF(AT275="","","") | AN275: =IF(AT275="","",INDEX(入力シート!$C$5:$C$204,AT275)) | AO275: =IF(AT275="","","") | AP275: =IF(AT275="","","") | AQ275: =IF(AT275="","","") | AT275: =IFERROR(MATCH(75,入力シート!$T$5:$T$204,0),"")
A276: =IF(AT276="","",1) | B276: =IF(AT276="","",1) | C276: =IF(AT276="","",0) | D276: =IF(AT276="","",TEXT(INDEX(入力シート!$A$5:$A$204,AT276),"YYYYMMDD")) | E276: =IF(AT276="","",TEXT(INDEX(入力シート!$Q$5:$Q$204,AT276),"00000000")) | F276: =IF(AT276="","",14) | G276: =IF(AT276="","",1) | H276: =IF(AT276="","",1) | I276: =IF(AT276="","",3) | J276: =IF(AT276="","",1) | K276: =IF(AT276="","",INDEX(入力シート!$B$5:$B$204,AT276)) | L276: =IF(AT276="","","") | M276: =IF(AT276="","","") | N276: =IF(AT276="","",COUNTIF(入力シート!$Q$5:$Q$204,INDEX(入力シート!$Q$5:$Q$204,AT276))+1) | O276: =IF(AT276="","",99) | P276: =IF(AT276="","","") | Q276: =IF(AT276="","","") | R276: =IF(AT276="","","消費税") | S276: =IF(AT276="","",0) | T276: =IF(AT276="","","") | U276: =IF(AT276="","",0) | V276: =IF(AT276="","",0) | W276: =IF(AT276="","","") | X276: =IF(AT276="","",0) | Y276: =IF(AT276="","",0) | Z276: =IF(AT276="","",ROUNDDOWN(SUMIF(入力シート!$Q$5:$Q$204,INDEX(入力シート!$Q$5:$Q$204,AT276),入力シート!$P$5:$P$204)*IF(INDEX(入力シート!$L$5:$L$204,AT276)=13,0.1,IF(INDEX(入力シート!$L$5:$L$204,AT276)=30,0.08,0)),0)) | AA276: =IF(AT276="","","") | AB276: =IF(AT276="","",0) | AC276: =IF(AT276="","",0) | AD276: =IF(AT276="","",0) | AE276: =IF(AT276="","","") | AF276: =IF(AT276="","",0) | AG276: =IF(AT276="","",0) | AH276: =IF(AT276="","","") | AI276: =IF(AT276="","","") | AJ276: =IF(AT276="","","") | AK276: =IF(AT276="","",2) | AL276: =IF(AT276="","","") | AM276: =IF(AT276="","","") | AN276: =IF(AT276="","",INDEX(入力シート!$C$5:$C$204,AT276)) | AO276: =IF(AT276="","","") | AP276: =IF(AT276="","","") | AQ276: =IF(AT276="","","") | AT276: =IFERROR(MATCH(76,入力シート!$T$5:$T$204,0),"")
A277: =IF(AT277="","",1) | B277: =IF(AT277="","",1) | C277: =IF(AT277="","",0) | D277: =IF(AT277="","",TEXT(INDEX(入力シート!$A$5:$A$204,AT277),"YYYYMMDD")) | E277: =IF(AT277="","",TEXT(INDEX(入力シート!$Q$5:$Q$204,AT277),"00000000")) | F277: =IF(AT277="","",14) | G277: =IF(AT277="","",1) | H277: =IF(AT277="","",1) | I277: =IF(AT277="","",3) | J277: =IF(AT277="","",1) | K277: =IF(AT277="","",INDEX(入力シート!$B$5:$B$204,AT277)) | L277: =IF(AT277="","","") | M277: =IF(AT277="","","") | N277: =IF(AT277="","",COUNTIF(入力シート!$Q$5:$Q$204,INDEX(入力シート!$Q$5:$Q$204,AT277))+1) | O277: =IF(AT277="","",99) | P277: =IF(AT277="","","") | Q277: =IF(AT277="","","") | R277: =IF(AT277="","","消費税") | S277: =IF(AT277="","",0) | T277: =IF(AT277="","","") | U277: =IF(AT277="","",0) | V277: =IF(AT277="","",0) | W277: =IF(AT277="","","") | X277: =IF(AT277="","",0) | Y277: =IF(AT277="","",0) | Z277: =IF(AT277="","",ROUNDDOWN(SUMIF(入力シート!$Q$5:$Q$204,INDEX(入力シート!$Q$5:$Q$204,AT277),入力シート!$P$5:$P$204)*IF(INDEX(入力シート!$L$5:$L$204,AT277)=13,0.1,IF(INDEX(入力シート!$L$5:$L$204,AT277)=30,0.08,0)),0)) | AA277: =IF(AT277="","","") | AB277: =IF(AT277="","",0) | AC277: =IF(AT277="","",0) | AD277: =IF(AT277="","",0) | AE277: =IF(AT277="","","") | AF277: =IF(AT277="","",0) | AG277: =IF(AT277="","",0) | AH277: =IF(AT277="","","") | AI277: =IF(AT277="","","") | AJ277: =IF(AT277="","","") | AK277: =IF(AT277="","",2) | AL277: =IF(AT277="","","") | AM277: =IF(AT277="","","") | AN277: =IF(AT277="","",INDEX(入力シート!$C$5:$C$204,AT277)) | AO277: =IF(AT277="","","") | AP277: =IF(AT277="","","") | AQ277: =IF(AT277="","","") | AT277: =IFERROR(MATCH(77,入力シート!$T$5:$T$204,0),"")
A278: =IF(AT278="","",1) | B278: =IF(AT278="","",1) | C278: =IF(AT278="","",0) | D278: =IF(AT278="","",TEXT(INDEX(入力シート!$A$5:$A$204,AT278),"YYYYMMDD")) | E278: =IF(AT278="","",TEXT(INDEX(入力シート!$Q$5:$Q$204,AT278),"00000000")) | F278: =IF(AT278="","",14) | G278: =IF(AT278="","",1) | H278: =IF(AT278="","",1) | I278: =IF(AT278="","",3) | J278: =IF(AT278="","",1) | K278: =IF(AT278="","",INDEX(入力シート!$B$5:$B$204,AT278)) | L278: =IF(AT278="","","") | M278: =IF(AT278="","","") | N278: =IF(AT278="","",COUNTIF(入力シート!$Q$5:$Q$204,INDEX(入力シート!$Q$5:$Q$204,AT278))+1) | O278: =IF(AT278="","",99) | P278: =IF(AT278="","","") | Q278: =IF(AT278="","","") | R278: =IF(AT278="","","消費税") | S278: =IF(AT278="","",0) | T278: =IF(AT278="","","") | U278: =IF(AT278="","",0) | V278: =IF(AT278="","",0) | W278: =IF(AT278="","","") | X278: =IF(AT278="","",0) | Y278: =IF(AT278="","",0) | Z278: =IF(AT278="","",ROUNDDOWN(SUMIF(入力シート!$Q$5:$Q$204,INDEX(入力シート!$Q$5:$Q$204,AT278),入力シート!$P$5:$P$204)*IF(INDEX(入力シート!$L$5:$L$204,AT278)=13,0.1,IF(INDEX(入力シート!$L$5:$L$204,AT278)=30,0.08,0)),0)) | AA278: =IF(AT278="","","") | AB278: =IF(AT278="","",0) | AC278: =IF(AT278="","",0) | AD278: =IF(AT278="","",0) | AE278: =IF(AT278="","","") | AF278: =IF(AT278="","",0) | AG278: =IF(AT278="","",0) | AH278: =IF(AT278="","","") | AI278: =IF(AT278="","","") | AJ278: =IF(AT278="","","") | AK278: =IF(AT278="","",2) | AL278: =IF(AT278="","","") | AM278: =IF(AT278="","","") | AN278: =IF(AT278="","",INDEX(入力シート!$C$5:$C$204,AT278)) | AO278: =IF(AT278="","","") | AP278: =IF(AT278="","","") | AQ278: =IF(AT278="","","") | AT278: =IFERROR(MATCH(78,入力シート!$T$5:$T$204,0),"")
A279: =IF(AT279="","",1) | B279: =IF(AT279="","",1) | C279: =IF(AT279="","",0) | D279: =IF(AT279="","",TEXT(INDEX(入力シート!$A$5:$A$204,AT279),"YYYYMMDD")) | E279: =IF(AT279="","",TEXT(INDEX(入力シート!$Q$5:$Q$204,AT279),"00000000")) | F279: =IF(AT279="","",14) | G279: =IF(AT279="","",1) | H279: =IF(AT279="","",1) | I279: =IF(AT279="","",3) | J279: =IF(AT279="","",1) | K279: =IF(AT279="","",INDEX(入力シート!$B$5:$B$204,AT279)) | L279: =IF(AT279="","","") | M279: =IF(AT279="","","") | N279: =IF(AT279="","",COUNTIF(入力シート!$Q$5:$Q$204,INDEX(入力シート!$Q$5:$Q$204,AT279))+1) | O279: =IF(AT279="","",99) | P279: =IF(AT279="","","") | Q279: =IF(AT279="","","") | R279: =IF(AT279="","","消費税") | S279: =IF(AT279="","",0) | T279: =IF(AT279="","","") | U279: =IF(AT279="","",0) | V279: =IF(AT279="","",0) | W279: =IF(AT279="","","") | X279: =IF(AT279="","",0) | Y279: =IF(AT279="","",0) | Z279: =IF(AT279="","",ROUNDDOWN(SUMIF(入力シート!$Q$5:$Q$204,INDEX(入力シート!$Q$5:$Q$204,AT279),入力シート!$P$5:$P$204)*IF(INDEX(入力シート!$L$5:$L$204,AT279)=13,0.1,IF(INDEX(入力シート!$L$5:$L$204,AT279)=30,0.08,0)),0)) | AA279: =IF(AT279="","","") | AB279: =IF(AT279="","",0) | AC279: =IF(AT279="","",0) | AD279: =IF(AT279="","",0) | AE279: =IF(AT279="","","") | AF279: =IF(AT279="","",0) | AG279: =IF(AT279="","",0) | AH279: =IF(AT279="","","") | AI279: =IF(AT279="","","") | AJ279: =IF(AT279="","","") | AK279: =IF(AT279="","",2) | AL279: =IF(AT279="","","") | AM279: =IF(AT279="","","") | AN279: =IF(AT279="","",INDEX(入力シート!$C$5:$C$204,AT279)) | AO279: =IF(AT279="","","") | AP279: =IF(AT279="","","") | AQ279: =IF(AT279="","","") | AT279: =IFERROR(MATCH(79,入力シート!$T$5:$T$204,0),"")
A280: =IF(AT280="","",1) | B280: =IF(AT280="","",1) | C280: =IF(AT280="","",0) | D280: =IF(AT280="","",TEXT(INDEX(入力シート!$A$5:$A$204,AT280),"YYYYMMDD")) | E280: =IF(AT280="","",TEXT(INDEX(入力シート!$Q$5:$Q$204,AT280),"00000000")) | F280: =IF(AT280="","",14) | G280: =IF(AT280="","",1) | H280: =IF(AT280="","",1) | I280: =IF(AT280="","",3) | J280: =IF(AT280="","",1) | K280: =IF(AT280="","",INDEX(入力シート!$B$5:$B$204,AT280)) | L280: =IF(AT280="","","") | M280: =IF(AT280="","","") | N280: =IF(AT280="","",COUNTIF(入力シート!$Q$5:$Q$204,INDEX(入力シート!$Q$5:$Q$204,AT280))+1) | O280: =IF(AT280="","",99) | P280: =IF(AT280="","","") | Q280: =IF(AT280="","","") | R280: =IF(AT280="","","消費税") | S280: =IF(AT280="","",0) | T280: =IF(AT280="","","") | U280: =IF(AT280="","",0) | V280: =IF(AT280="","",0) | W280: =IF(AT280="","","") | X280: =IF(AT280="","",0) | Y280: =IF(AT280="","",0) | Z280: =IF(AT280="","",ROUNDDOWN(SUMIF(入力シート!$Q$5:$Q$204,INDEX(入力シート!$Q$5:$Q$204,AT280),入力シート!$P$5:$P$204)*IF(INDEX(入力シート!$L$5:$L$204,AT280)=13,0.1,IF(INDEX(入力シート!$L$5:$L$204,AT280)=30,0.08,0)),0)) | AA280: =IF(AT280="","","") | AB280: =IF(AT280="","",0) | AC280: =IF(AT280="","",0) | AD280: =IF(AT280="","",0) | AE280: =IF(AT280="","","") | AF280: =IF(AT280="","",0) | AG280: =IF(AT280="","",0) | AH280: =IF(AT280="","","") | AI280: =IF(AT280="","","") | AJ280: =IF(AT280="","","") | AK280: =IF(AT280="","",2) | AL280: =IF(AT280="","","") | AM280: =IF(AT280="","","") | AN280: =IF(AT280="","",INDEX(入力シート!$C$5:$C$204,AT280)) | AO280: =IF(AT280="","","") | AP280: =IF(AT280="","","") | AQ280: =IF(AT280="","","") | AT280: =IFERROR(MATCH(80,入力シート!$T$5:$T$204,0),"")
A281: =IF(AT281="","",1) | B281: =IF(AT281="","",1) | C281: =IF(AT281="","",0) | D281: =IF(AT281="","",TEXT(INDEX(入力シート!$A$5:$A$204,AT281),"YYYYMMDD")) | E281: =IF(AT281="","",TEXT(INDEX(入力シート!$Q$5:$Q$204,AT281),"00000000")) | F281: =IF(AT281="","",14) | G281: =IF(AT281="","",1) | H281: =IF(AT281="","",1) | I281: =IF(AT281="","",3) | J281: =IF(AT281="","",1) | K281: =IF(AT281="","",INDEX(入力シート!$B$5:$B$204,AT281)) | L281: =IF(AT281="","","") | M281: =IF(AT281="","","") | N281: =IF(AT281="","",COUNTIF(入力シート!$Q$5:$Q$204,INDEX(入力シート!$Q$5:$Q$204,AT281))+1) | O281: =IF(AT281="","",99) | P281: =IF(AT281="","","") | Q281: =IF(AT281="","","") | R281: =IF(AT281="","","消費税") | S281: =IF(AT281="","",0) | T281: =IF(AT281="","","") | U281: =IF(AT281="","",0) | V281: =IF(AT281="","",0) | W281: =IF(AT281="","","") | X281: =IF(AT281="","",0) | Y281: =IF(AT281="","",0) | Z281: =IF(AT281="","",ROUNDDOWN(SUMIF(入力シート!$Q$5:$Q$204,INDEX(入力シート!$Q$5:$Q$204,AT281),入力シート!$P$5:$P$204)*IF(INDEX(入力シート!$L$5:$L$204,AT281)=13,0.1,IF(INDEX(入力シート!$L$5:$L$204,AT281)=30,0.08,0)),0)) | AA281: =IF(AT281="","","") | AB281: =IF(AT281="","",0) | AC281: =IF(AT281="","",0) | AD281: =IF(AT281="","",0) | AE281: =IF(AT281="","","") | AF281: =IF(AT281="","",0) | AG281: =IF(AT281="","",0) | AH281: =IF(AT281="","","") | AI281: =IF(AT281="","","") | AJ281: =IF(AT281="","","") | AK281: =IF(AT281="","",2) | AL281: =IF(AT281="","","") | AM281: =IF(AT281="","","") | AN281: =IF(AT281="","",INDEX(入力シート!$C$5:$C$204,AT281)) | AO281: =IF(AT281="","","") | AP281: =IF(AT281="","","") | AQ281: =IF(AT281="","","") | AT281: =IFERROR(MATCH(81,入力シート!$T$5:$T$204,0),"")
A282: =IF(AT282="","",1) | B282: =IF(AT282="","",1) | C282: =IF(AT282="","",0) | D282: =IF(AT282="","",TEXT(INDEX(入力シート!$A$5:$A$204,AT282),"YYYYMMDD")) | E282: =IF(AT282="","",TEXT(INDEX(入力シート!$Q$5:$Q$204,AT282),"00000000")) | F282: =IF(AT282="","",14) | G282: =IF(AT282="","",1) | H282: =IF(AT282="","",1) | I282: =IF(AT282="","",3) | J282: =IF(AT282="","",1) | K282: =IF(AT282="","",INDEX(入力シート!$B$5:$B$204,AT282)) | L282: =IF(AT282="","","") | M282: =IF(AT282="","","") | N282: =IF(AT282="","",COUNTIF(入力シート!$Q$5:$Q$204,INDEX(入力シート!$Q$5:$Q$204,AT282))+1) | O282: =IF(AT282="","",99) | P282: =IF(AT282="","","") | Q282: =IF(AT282="","","") | R282: =IF(AT282="","","消費税") | S282: =IF(AT282="","",0) | T282: =IF(AT282="","","") | U282: =IF(AT282="","",0) | V282: =IF(AT282="","",0) | W282: =IF(AT282="","","") | X282: =IF(AT282="","",0) | Y282: =IF(AT282="","",0) | Z282: =IF(AT282="","",ROUNDDOWN(SUMIF(入力シート!$Q$5:$Q$204,INDEX(入力シート!$Q$5:$Q$204,AT282),入力シート!$P$5:$P$204)*IF(INDEX(入力シート!$L$5:$L$204,AT282)=13,0.1,IF(INDEX(入力シート!$L$5:$L$204,AT282)=30,0.08,0)),0)) | AA282: =IF(AT282="","","") | AB282: =IF(AT282="","",0) | AC282: =IF(AT282="","",0) | AD282: =IF(AT282="","",0) | AE282: =IF(AT282="","","") | AF282: =IF(AT282="","",0) | AG282: =IF(AT282="","",0) | AH282: =IF(AT282="","","") | AI282: =IF(AT282="","","") | AJ282: =IF(AT282="","","") | AK282: =IF(AT282="","",2) | AL282: =IF(AT282="","","") | AM282: =IF(AT282="","","") | AN282: =IF(AT282="","",INDEX(入力シート!$C$5:$C$204,AT282)) | AO282: =IF(AT282="","","") | AP282: =IF(AT282="","","") | AQ282: =IF(AT282="","","") | AT282: =IFERROR(MATCH(82,入力シート!$T$5:$T$204,0),"")
A283: =IF(AT283="","",1) | B283: =IF(AT283="","",1) | C283: =IF(AT283="","",0) | D283: =IF(AT283="","",TEXT(INDEX(入力シート!$A$5:$A$204,AT283),"YYYYMMDD")) | E283: =IF(AT283="","",TEXT(INDEX(入力シート!$Q$5:$Q$204,AT283),"00000000")) | F283: =IF(AT283="","",14) | G283: =IF(AT283="","",1) | H283: =IF(AT283="","",1) | I283: =IF(AT283="","",3) | J283: =IF(AT283="","",1) | K283: =IF(AT283="","",INDEX(入力シート!$B$5:$B$204,AT283)) | L283: =IF(AT283="","","") | M283: =IF(AT283="","","") | N283: =IF(AT283="","",COUNTIF(入力シート!$Q$5:$Q$204,INDEX(入力シート!$Q$5:$Q$204,AT283))+1) | O283: =IF(AT283="","",99) | P283: =IF(AT283="","","") | Q283: =IF(AT283="","","") | R283: =IF(AT283="","","消費税") | S283: =IF(AT283="","",0) | T283: =IF(AT283="","","") | U283: =IF(AT283="","",0) | V283: =IF(AT283="","",0) | W283: =IF(AT283="","","") | X283: =IF(AT283="","",0) | Y283: =IF(AT283="","",0) | Z283: =IF(AT283="","",ROUNDDOWN(SUMIF(入力シート!$Q$5:$Q$204,INDEX(入力シート!$Q$5:$Q$204,AT283),入力シート!$P$5:$P$204)*IF(INDEX(入力シート!$L$5:$L$204,AT283)=13,0.1,IF(INDEX(入力シート!$L$5:$L$204,AT283)=30,0.08,0)),0)) | AA283: =IF(AT283="","","") | AB283: =IF(AT283="","",0) | AC283: =IF(AT283="","",0) | AD283: =IF(AT283="","",0) | AE283: =IF(AT283="","","") | AF283: =IF(AT283="","",0) | AG283: =IF(AT283="","",0) | AH283: =IF(AT283="","","") | AI283: =IF(AT283="","","") | AJ283: =IF(AT283="","","") | AK283: =IF(AT283="","",2) | AL283: =IF(AT283="","","") | AM283: =IF(AT283="","","") | AN283: =IF(AT283="","",INDEX(入力シート!$C$5:$C$204,AT283)) | AO283: =IF(AT283="","","") | AP283: =IF(AT283="","","") | AQ283: =IF(AT283="","","") | AT283: =IFERROR(MATCH(83,入力シート!$T$5:$T$204,0),"")
A284: =IF(AT284="","",1) | B284: =IF(AT284="","",1) | C284: =IF(AT284="","",0) | D284: =IF(AT284="","",TEXT(INDEX(入力シート!$A$5:$A$204,AT284),"YYYYMMDD")) | E284: =IF(AT284="","",TEXT(INDEX(入力シート!$Q$5:$Q$204,AT284),"00000000")) | F284: =IF(AT284="","",14) | G284: =IF(AT284="","",1) | H284: =IF(AT284="","",1) | I284: =IF(AT284="","",3) | J284: =IF(AT284="","",1) | K284: =IF(AT284="","",INDEX(入力シート!$B$5:$B$204,AT284)) | L284: =IF(AT284="","","") | M284: =IF(AT284="","","") | N284: =IF(AT284="","",COUNTIF(入力シート!$Q$5:$Q$204,INDEX(入力シート!$Q$5:$Q$204,AT284))+1) | O284: =IF(AT284="","",99) | P284: =IF(AT284="","","") | Q284: =IF(AT284="","","") | R284: =IF(AT284="","","消費税") | S284: =IF(AT284="","",0) | T284: =IF(AT284="","","") | U284: =IF(AT284="","",0) | V284: =IF(AT284="","",0) | W284: =IF(AT284="","","") | X284: =IF(AT284="","",0) | Y284: =IF(AT284="","",0) | Z284: =IF(AT284="","",ROUNDDOWN(SUMIF(入力シート!$Q$5:$Q$204,INDEX(入力シート!$Q$5:$Q$204,AT284),入力シート!$P$5:$P$204)*IF(INDEX(入力シート!$L$5:$L$204,AT284)=13,0.1,IF(INDEX(入力シート!$L$5:$L$204,AT284)=30,0.08,0)),0)) | AA284: =IF(AT284="","","") | AB284: =IF(AT284="","",0) | AC284: =IF(AT284="","",0) | AD284: =IF(AT284="","",0) | AE284: =IF(AT284="","","") | AF284: =IF(AT284="","",0) | AG284: =IF(AT284="","",0) | AH284: =IF(AT284="","","") | AI284: =IF(AT284="","","") | AJ284: =IF(AT284="","","") | AK284: =IF(AT284="","",2) | AL284: =IF(AT284="","","") | AM284: =IF(AT284="","","") | AN284: =IF(AT284="","",INDEX(入力シート!$C$5:$C$204,AT284)) | AO284: =IF(AT284="","","") | AP284: =IF(AT284="","","") | AQ284: =IF(AT284="","","") | AT284: =IFERROR(MATCH(84,入力シート!$T$5:$T$204,0),"")
A285: =IF(AT285="","",1) | B285: =IF(AT285="","",1) | C285: =IF(AT285="","",0) | D285: =IF(AT285="","",TEXT(INDEX(入力シート!$A$5:$A$204,AT285),"YYYYMMDD")) | E285: =IF(AT285="","",TEXT(INDEX(入力シート!$Q$5:$Q$204,AT285),"00000000")) | F285: =IF(AT285="","",14) | G285: =IF(AT285="","",1) | H285: =IF(AT285="","",1) | I285: =IF(AT285="","",3) | J285: =IF(AT285="","",1) | K285: =IF(AT285="","",INDEX(入力シート!$B$5:$B$204,AT285)) | L285: =IF(AT285="","","") | M285: =IF(AT285="","","") | N285: =IF(AT285="","",COUNTIF(入力シート!$Q$5:$Q$204,INDEX(入力シート!$Q$5:$Q$204,AT285))+1) | O285: =IF(AT285="","",99) | P285: =IF(AT285="","","") | Q285: =IF(AT285="","","") | R285: =IF(AT285="","","消費税") | S285: =IF(AT285="","",0) | T285: =IF(AT285="","","") | U285: =IF(AT285="","",0) | V285: =IF(AT285="","",0) | W285: =IF(AT285="","","") | X285: =IF(AT285="","",0) | Y285: =IF(AT285="","",0) | Z285: =IF(AT285="","",ROUNDDOWN(SUMIF(入力シート!$Q$5:$Q$204,INDEX(入力シート!$Q$5:$Q$204,AT285),入力シート!$P$5:$P$204)*IF(INDEX(入力シート!$L$5:$L$204,AT285)=13,0.1,IF(INDEX(入力シート!$L$5:$L$204,AT285)=30,0.08,0)),0)) | AA285: =IF(AT285="","","") | AB285: =IF(AT285="","",0) | AC285: =IF(AT285="","",0) | AD285: =IF(AT285="","",0) | AE285: =IF(AT285="","","") | AF285: =IF(AT285="","",0) | AG285: =IF(AT285="","",0) | AH285: =IF(AT285="","","") | AI285: =IF(AT285="","","") | AJ285: =IF(AT285="","","") | AK285: =IF(AT285="","",2) | AL285: =IF(AT285="","","") | AM285: =IF(AT285="","","") | AN285: =IF(AT285="","",INDEX(入力シート!$C$5:$C$204,AT285)) | AO285: =IF(AT285="","","") | AP285: =IF(AT285="","","") | AQ285: =IF(AT285="","","") | AT285: =IFERROR(MATCH(85,入力シート!$T$5:$T$204,0),"")
A286: =IF(AT286="","",1) | B286: =IF(AT286="","",1) | C286: =IF(AT286="","",0) | D286: =IF(AT286="","",TEXT(INDEX(入力シート!$A$5:$A$204,AT286),"YYYYMMDD")) | E286: =IF(AT286="","",TEXT(INDEX(入力シート!$Q$5:$Q$204,AT286),"00000000")) | F286: =IF(AT286="","",14) | G286: =IF(AT286="","",1) | H286: =IF(AT286="","",1) | I286: =IF(AT286="","",3) | J286: =IF(AT286="","",1) | K286: =IF(AT286="","",INDEX(入力シート!$B$5:$B$204,AT286)) | L286: =IF(AT286="","","") | M286: =IF(AT286="","","") | N286: =IF(AT286="","",COUNTIF(入力シート!$Q$5:$Q$204,INDEX(入力シート!$Q$5:$Q$204,AT286))+1) | O286: =IF(AT286="","",99) | P286: =IF(AT286="","","") | Q286: =IF(AT286="","","") | R286: =IF(AT286="","","消費税") | S286: =IF(AT286="","",0) | T286: =IF(AT286="","","") | U286: =IF(AT286="","",0) | V286: =IF(AT286="","",0) | W286: =IF(AT286="","","") | X286: =IF(AT286="","",0) | Y286: =IF(AT286="","",0) | Z286: =IF(AT286="","",ROUNDDOWN(SUMIF(入力シート!$Q$5:$Q$204,INDEX(入力シート!$Q$5:$Q$204,AT286),入力シート!$P$5:$P$204)*IF(INDEX(入力シート!$L$5:$L$204,AT286)=13,0.1,IF(INDEX(入力シート!$L$5:$L$204,AT286)=30,0.08,0)),0)) | AA286: =IF(AT286="","","") | AB286: =IF(AT286="","",0) | AC286: =IF(AT286="","",0) | AD286: =IF(AT286="","",0) | AE286: =IF(AT286="","","") | AF286: =IF(AT286="","",0) | AG286: =IF(AT286="","",0) | AH286: =IF(AT286="","","") | AI286: =IF(AT286="","","") | AJ286: =IF(AT286="","","") | AK286: =IF(AT286="","",2) | AL286: =IF(AT286="","","") | AM286: =IF(AT286="","","") | AN286: =IF(AT286="","",INDEX(入力シート!$C$5:$C$204,AT286)) | AO286: =IF(AT286="","","") | AP286: =IF(AT286="","","") | AQ286: =IF(AT286="","","") | AT286: =IFERROR(MATCH(86,入力シート!$T$5:$T$204,0),"")
...
